Workbook

Sheet README
A1: 01 README
A3: Project | B3: Corporate Treasury & Liquidity Optimisation Engine
A4: Company | B4: Unilever plc
A5: Step | B5: Step 2 — Historical Financial Engine
A6: Purpose | B6: This workbook transforms the validated public-data source dataset into a formula-driven historical financial model covering 2021–2025 where data is available and comparable. The model establishes the historical profitability, liquidity, cash-flow, financing and working-capital base required for subsequent treasury forecasting and optimisation.
A7: Units | B7: € million unless otherwise stated.
A8: Source hierarchy | B8: 1. Unilever Annual Reports 2. Unilever Consolidated Financial Statements 3. Derived calculations 4. Explicit modelling assumptions
A9: Data classification | B9: Reported · Derived · Assumption · Unavailable
A10: Critical modelling rule | B10: No confidential Unilever treasury information is assumed. Weekly cash-flow timing, internal cash-pool pricing, internal minimum cash buffers and other non-public treasury information will be constructed only in later modelling stages and explicitly labelled as assumptions.
A11: Source file (frozen) | B11: Unilever_Treasury_FINAL_CLEAN_RAW_DATASET_v4.xlsx — never overwritten. RAW_DATA is a controlled copy of it; each row cites the dataset sheet and row.
A12: Model status | B12: =HISTORICAL_CHECKS!$B$10 -> COMPLETE — all core checks PASS
A13: Source reconciliation | B13: Completed on the v4 dataset: every input used by a core check was traced to an official Unilever document (results announcements FY2022, FY2023, FY2025; Historical Financials excl. Ice Cream; Form 20-F 2025 XBRL). Remaining blanks are line-item detail not needed by any core check; each is documented in the dataset's Source Pass Log.
A14: Period columns | B14: 2021 · 2022 · 2023 Original · 2023 Continuing · 2024 · 2025. 2023 appears twice because the 2025 Annual Report re-presented 2023–2024 for the Ice Cream demerger. Growth rates compare like with like: 2023 Original vs 2022, 2024 vs 2023 Continuing. Balance sheets are not re-presented, so balance-sheet rows have no 2023 Continuing value (grey).
A15: Basis-break warning | B15: 2021–2023 Original include Ice Cream; 2023 Continuing–2025 exclude it. 2021→2025 comparisons and CAGRs are reported-basis, not like-for-like, and are labelled accordingly.
A16: Colour legend | B16: Blue = hard-coded source value (RAW_DATA only) · Green = link to another sheet · Black = calculation · Yellow fill = Unavailable in source (enter value in RAW_DATA) · Grey fill = not applicable.
A17: How to add missing data | B17: Type the reported figure into the yellow cell on RAW_DATA (and into the frozen dataset's next version). Everything downstream, including the checks, updates automatically.
A18: Sheets | B18: 01 README · 02 RAW_DATA (input layer) · 03 HISTORICAL_IS · 04 HISTORICAL_BS · 05 HISTORICAL_CF · 06 WORKING_CAPITAL · 07 HISTORICAL_CHECKS · 08 HISTORICAL_OUTPUTS (the only sheet designed for reading).
A19: Out of scope for Step 2 | B19: 13-week forecast, weekly timing, minimum cash buffer, funding/debt/FX optimisation, investment allocation, Monte Carlo, scenarios, stress tests, live market rates, treasury policy assumptions, final dashboard and report.

Sheet RAW_DATA
A1: 02 RAW_DATA — CONTROLLED COPY OF SOURCE DATA (INPUT LAYER)
A2: Values copied unchanged from the frozen source file Unilever_Treasury_FINAL_CLEAN_RAW_DATASET_v4.xlsx. No calculations on this sheet. Blank yellow = Unavailable in source; grey = not applicable (balance sheets are not re-presented, so no 2023 Continuing).
A4: Variable | B4: 2021 | C4: 2022 | D4: 2023 Original | E4: 2023 Continuing | F4: 2024 | G4: 2025 | H4: Status | I4: Source | J4: Note
A5: INCOME STATEMENT
A6: Turnover | B6: 52444 | C6: 60073 | D6: 59604 | E6: 51680 | F6: 52479 | G6: 50503 | H6: Reported | I6: AR2022; AR2023; AR2025 | dataset: Raw Financials r6 | J6: 2023 Original vs Continuing kept separate.
A7: Cost of sales | B7: 30259 | C7: 35906 | D7: 34429 | E7: 29180 | F7: 27976 | G7: 26794 | H7: Reported | I7: AR2022; AR2023; AR2025 | dataset: Raw Financials r7 | J7: Positive = cost.
A8: Operating profit | B8: 8702 | C8: 10755 | D8: 9758 | E8: 8998 | F8: 8829 | G8: 9037 | H8: Reported | I8: AR2022; AR2023; AR2025 | dataset: Raw Financials r8
A9: Net finance costs | B9: 354 | C9: 493 | D9: 486 | E9: 408 | F9: 520 | G9: 503 | H9: Reported | I9: FY22 results (9 Feb 2023) p.15; FY23 results (8 Feb 2024) p.18; Historical Financials excl. Ice Cream (15 Jan 2026); FY25 results (12 Feb 2026) p.20 | dataset: Raw Financials r9 | J9: Positive = net cost. v4 CORRECTION: 2023 Original 409 → 486 (FY23 results p.18); 2023 Continuing 409 → 408 (excl.-Ice-Cream document). Both corrections make the PBT bridge reconcile exactly.
A10: Net monetary gain/(loss) arising from hyperinflationary economies | B10: -74 | C10: -157 | D10: -142 | E10: -169 | F10: -201 | G10: -68 | H10: Reported | I10: FY22 results (9 Feb 2023) p.15; FY23 results (8 Feb 2024) p.18; Historical Financials excl. Ice Cream (15 Jan 2026); FY25 results (12 Feb 2026) p.20 | dataset: Raw Financials r10 | J10: v4 NEW ROW. Negative = loss. Sits between operating profit and PBT; was missing from v1–v3.
A11: Share of net profit/(loss) of joint ventures and associates | B11: 191 | C11: 208 | D11: 231 | E11: 228 | F11: 250 | G11: 245 | H11: Reported | I11: FY22 results (9 Feb 2023) p.15; FY23 results (8 Feb 2024) p.18; Historical Financials excl. Ice Cream (15 Jan 2026); FY25 results (12 Feb 2026) p.20 | dataset: Raw Financials r11 | J11: Positive = income.
A12: Other income/(loss) from non-current investments and associates | B12: 91 | C12: 24 | D12: -22 | E12: -22 | F12: 13 | G12: -17 | H12: Reported | I12: FY22 results (9 Feb 2023) p.15; FY23 results (8 Feb 2024) p.18; Historical Financials excl. Ice Cream (15 Jan 2026); FY25 results (12 Feb 2026) p.20 | dataset: Raw Financials r12 | J12: Positive = income.
A13: Profit before taxation | B13: 8556 | C13: 10337 | D13: 9339 | E13: 8627 | F13: 8371 | G13: 8693 | H13: Reported | I13: FY22 results (9 Feb 2023) p.15; FY23 results (8 Feb 2024) p.18; Historical Financials excl. Ice Cream (15 Jan 2026); FY25 results (12 Feb 2026) p.20 | dataset: Raw Financials r13 | J13: 2021–2023 Original added in v4.
A14: Taxation | B14: 1935 | C14: 2068 | D14: 2199 | E14: 1990 | F14: 2332 | G14: 2481 | H14: Reported | I14: AR2022; AR2023; AR2025 (2023C via v2) | dataset: Raw Financials r14 | J14: Positive = tax charge.
A15: Net profit | B15: 6621 | C15: 8269 | D15: 7140 | E15: 6637 | F15: 6039 | G15: 6213 | H15: Reported | I15: AR2022; AR2023; AR2025 | dataset: Raw Financials r15 | J15: 2021–2023 Original: total group net profit. 2023 Continuing–2025: net profit from continuing operations.
A16: BALANCE SHEET — OPERATING ITEMS (year-end)
A17: Inventories | B17: 4683 | C17: 5931 | D17: 5119 | F17: 5177 | G17: 4043 | H17: Reported | I17: AR2022; AR2023/24; AR2025 | dataset: Raw Working Capital r6
A18: Trade receivables | B18: 3582 | C18: 4544 | D18: 4023 | F18: 4227 | G18: 4852 | H18: Reported | I18: AR2022; AR2023/24; AR2025 (Note 13) | dataset: Raw Working Capital r7
A19: Total current trade and other receivables | B19: 5422 | C19: 7056 | D19: 5775 | F19: 6011 | G19: 7346 | H19: Reported | I19: AR2022; AR2023/24; AR2025 (Note 13) | dataset: Raw Working Capital r8 | J19: Other current receivables = total − trade receivables (derive in model, not here).
A20: Trade payables | B20: 8896 | C20: 11100 | D20: 10355 | F20: 10258 | G20: 10994 | H20: Reported | I20: AR2022; AR2023/24; AR2025 (Note 14) | dataset: Raw Working Capital r10
A21: Accruals | B21: 4429 | C21: 5232 | D21: 5057 | F21: 5053 | G21: 4649 | H21: Reported | I21: AR2022; AR2023/24; AR2025 (Note 14) | dataset: Raw Working Capital r11
A22: Total trade payables and other current liabilities | B22: 14861 | C22: 18023 | D22: 16857 | F22: 16690 | G22: 16939 | H22: Reported | I22: AR2022; AR2023/24; AR2025 (Note 14) | dataset: Raw Working Capital r12 | J22: Other current operating liabilities = total − trade payables − accruals (derive in model).
A23: BALANCE SHEET — CASH, FINANCIAL ASSETS AND NET DEBT (year-end)
A24: Cash and cash equivalents — balance sheet | B24: 3415 | C24: 4326 | D24: 4159 | F24: 6136 | G24: 3941 | H24: Reported | I24: AR2022; AR2023; AR2025 | dataset: Raw Liquidity & Debt r6
A25: Bank overdrafts (deducted in CF-statement cash) | B25: 106 | C25: 101 | D25: 116 | F25: 180 | G25: 65 | H25: Reported | I25: FY22 results p.12; FY23 results p.15; FY25 results p.16 (net-debt table) | dataset: Raw Liquidity & Debt r7 | J25: Added in v4.
A26: Cash held for sale — reconciling adjustment as printed (brackets = deduction) | B26: -78 | C26: 0 | D26: -2 | F26: 6 | G26: 6 | H26: Reported | I26: FY22 results p.12; FY23 results p.15; FY25 results p.16 (net-debt table) | dataset: Raw Liquidity & Debt r8 | J26: Stored with the sign as printed: 2021 (78), 2022 –, 2023 (2), 2024 6, 2025 6. In every year CF cash + overdrafts + this adjustment = balance-sheet cash. The 2024/25 row is labelled 'Less:' but printed without brackets; the printed sign is kept.
A27: Other current financial assets | B27: 1156 | C27: 1435 | D27: 1731 | F27: 1330 | G27: 1121 | H27: Reported | I27: AR2022; AR2023; AR2025 | dataset: Raw Liquidity & Debt r9
A28: Non-current financial asset derivatives related to financial liabilities | B28: 52 | C28: 51 | D28: 75 | F28: 68 | G28: 140 | H28: Reported | I28: FY22 results p.12; FY23 results p.15; FY25 results p.16 (net-debt table) | dataset: Raw Liquidity & Debt r10 | J28: Added in v4. Equals the gap previously shown in the model's memo row in every year.
A29: Financial liabilities — current | B29: 7252 | C29: 5775 | D29: 5087 | F29: 6987 | G29: 2582 | H29: Reported | I29: AR2022; AR2023; AR2025 | dataset: Raw Liquidity & Debt r12
A30: Financial liabilities — non-current | B30: 22881 | C30: 23713 | D30: 24535 | F30: 25066 | G30: 25696 | H30: Reported | I30: AR2022; AR2023; AR2025 | dataset: Raw Liquidity & Debt r13
A31: Financial liabilities — total | B31: 30133 | C31: 29488 | D31: 29622 | F31: 32053 | G31: 28278 | H31: Reported | I31: AR2022; AR2023; AR2025 | dataset: Raw Liquidity & Debt r14
A32: Net debt (reported) | B32: 25510 | C32: 23676 | D32: 23657 | F32: 24519 | G32: 23076 | H32: Reported | I32: AR2022; AR2023; AR2025 net-debt reconciliation | dataset: Raw Liquidity & Debt r15
A33: FINANCIAL LIABILITIES BY CATEGORY (year-end)
A34: Bonds and other loans — total | B34: 27621 | C34: 26512 | G34: 26038 | H34: Reported (partial) | I34: AR2022; AR2025 (Note 15C) | dataset: Raw Liquidity & Debt r17 | J34: Disclosed in annual-report Note 15C (financial liabilities analysis), which could not be read in this environment; not in the results announcements. Not needed for any core check.
A35: Bank loans and overdrafts — total | B35: 402 | C35: 519 | G35: 233 | H35: Reported (partial) | I35: AR2022; AR2025 (Note 15C) | dataset: Raw Liquidity & Debt r18 | J35: Disclosed in annual-report Note 15C (financial liabilities analysis), which could not be read in this environment; not in the results announcements. Not needed for any core check.
A36: Bank loans and overdrafts — current | H36: Unavailable | I36: AR Note 15C — not extracted | dataset: Raw Liquidity & Debt r20 | J36: Disclosed in annual-report Note 15C (financial liabilities analysis), which could not be read in this environment; not in the results announcements. Not needed for any core check.
A37: Bonds and other loans — current | H37: Unavailable | I37: AR Note 15C — not extracted | dataset: Raw Liquidity & Debt r21 | J37: Disclosed in annual-report Note 15C (financial liabilities analysis), which could not be read in this environment; not in the results announcements. Not needed for any core check.
A38: Lease liabilities — current | H38: Unavailable | I38: AR Note 15C — not extracted | dataset: Raw Liquidity & Debt r22 | J38: Disclosed in annual-report Note 15C (financial liabilities analysis), which could not be read in this environment; not in the results announcements. Not needed for any core check.
A39: Derivatives — current | H39: Unavailable | I39: AR Note 15C — not extracted | dataset: Raw Liquidity & Debt r23 | J39: Disclosed in annual-report Note 15C (financial liabilities analysis), which could not be read in this environment; not in the results announcements. Not needed for any core check.
A40: Other financial liabilities — current | H40: Unavailable | I40: AR Note 15C — not extracted | dataset: Raw Liquidity & Debt r24 | J40: Disclosed in annual-report Note 15C (financial liabilities analysis), which could not be read in this environment; not in the results announcements. Not needed for any core check.
A41: Bank loans and overdrafts — non-current | H41: Unavailable | I41: AR Note 15C — not extracted | dataset: Raw Liquidity & Debt r26 | J41: Disclosed in annual-report Note 15C (financial liabilities analysis), which could not be read in this environment; not in the results announcements. Not needed for any core check.
A42: Bonds and other loans — non-current | H42: Unavailable | I42: AR Note 15C — not extracted | dataset: Raw Liquidity & Debt r27 | J42: Disclosed in annual-report Note 15C (financial liabilities analysis), which could not be read in this environment; not in the results announcements. Not needed for any core check.
A43: Lease liabilities — non-current | H43: Unavailable | I43: AR Note 15C — not extracted | dataset: Raw Liquidity & Debt r28 | J43: Disclosed in annual-report Note 15C (financial liabilities analysis), which could not be read in this environment; not in the results announcements. Not needed for any core check.
A44: Derivatives — non-current | H44: Unavailable | I44: AR Note 15C — not extracted | dataset: Raw Liquidity & Debt r29 | J44: Disclosed in annual-report Note 15C (financial liabilities analysis), which could not be read in this environment; not in the results announcements. Not needed for any core check.
A45: Other financial liabilities — non-current | H45: Unavailable | I45: AR Note 15C — not extracted | dataset: Raw Liquidity & Debt r30 | J45: Disclosed in annual-report Note 15C (financial liabilities analysis), which could not be read in this environment; not in the results announcements. Not needed for any core check.
A46: CASH FLOW — OPERATING
A47: Net profit from continuing operations (CF statement start) | F47: 6039 | G47: 6213 | H47: Reported (partial) | I47: Historical Financials excl. Ice Cream (15 Jan 2026) (2023C); FY25 results (12 Feb 2026) p.24 (2024–25) | dataset: Raw Cash Flow r14 | J47: 2021–2023 Original: disclosed in AR2022/AR2023 cash-flow notes but not extracted (full-report PDFs not readable in this environment); not needed for any core check. 2023 Continuing: the excl.-Ice-Cream document starts this reconciliation at operating profit (8,998), so this line is not printed for 2023C.
A48: Taxation (add-back) | F48: 2332 | G48: 2481 | H48: Reported (partial) | I48: Historical Financials excl. Ice Cream (15 Jan 2026) (2023C); FY25 results (12 Feb 2026) p.24 (2024–25) | dataset: Raw Cash Flow r15 | J48: 2021–2023 Original: disclosed in AR2022/AR2023 cash-flow notes but not extracted (full-report PDFs not readable in this environment); not needed for any core check. 2023 Continuing: the excl.-Ice-Cream document starts this reconciliation at operating profit (8,998), so this line is not printed for 2023C.
A49: Share of net profit of JVs/associates and other income from non-current investments | F49: -263 | G49: -228 | H49: Reported (partial) | I49: Historical Financials excl. Ice Cream (15 Jan 2026) (2023C); FY25 results (12 Feb 2026) p.24 (2024–25) | dataset: Raw Cash Flow r16 | J49: 2021–2023 Original: disclosed in AR2022/AR2023 cash-flow notes but not extracted (full-report PDFs not readable in this environment); not needed for any core check. 2023 Continuing: the excl.-Ice-Cream document starts this reconciliation at operating profit (8,998), so this line is not printed for 2023C.
A50: Net monetary (gain)/loss arising from hyperinflationary economies | F50: 201 | G50: 68 | H50: Reported (partial) | I50: Historical Financials excl. Ice Cream (15 Jan 2026) (2023C); FY25 results (12 Feb 2026) p.24 (2024–25) | dataset: Raw Cash Flow r17 | J50: 2021–2023 Original: disclosed in AR2022/AR2023 cash-flow notes but not extracted (full-report PDFs not readable in this environment); not needed for any core check. 2023 Continuing: the excl.-Ice-Cream document starts this reconciliation at operating profit (8,998), so this line is not printed for 2023C.
A51: Net finance costs (add-back) | F51: 520 | G51: 503 | H51: Reported (partial) | I51: Historical Financials excl. Ice Cream (15 Jan 2026) (2023C); FY25 results (12 Feb 2026) p.24 (2024–25) | dataset: Raw Cash Flow r18 | J51: 2021–2023 Original: disclosed in AR2022/AR2023 cash-flow notes but not extracted (full-report PDFs not readable in this environment); not needed for any core check. 2023 Continuing: the excl.-Ice-Cream document starts this reconciliation at operating profit (8,998), so this line is not printed for 2023C.
A52: Depreciation, amortisation and impairment | E52: 1148 | F52: 1370 | G52: 1353 | H52: Reported (partial) | I52: Historical Financials excl. Ice Cream (15 Jan 2026) (2023C); FY25 results (12 Feb 2026) p.24 (2024–25) | dataset: Raw Cash Flow r19 | J52: 2021–2023 Original: disclosed in AR2022/AR2023 cash-flow notes but not extracted (full-report PDFs not readable in this environment); not needed for any core check.
A53: Changes in working capital | E53: 753 | F53: -188 | G53: 116 | H53: Reported (partial) | I53: Historical Financials excl. Ice Cream (15 Jan 2026) (2023C); FY25 results (12 Feb 2026) p.24 (2024–25) | dataset: Raw Cash Flow r20 | J53: 2021–2023 Original: disclosed in AR2022/AR2023 cash-flow notes but not extracted (full-report PDFs not readable in this environment); not needed for any core check.
A54: Pensions and similar obligations less payments | E54: -251 | F54: -54 | G54: -74 | H54: Reported (partial) | I54: Historical Financials excl. Ice Cream (15 Jan 2026) (2023C); FY25 results (12 Feb 2026) p.24 (2024–25) | dataset: Raw Cash Flow r21 | J54: 2021–2023 Original: disclosed in AR2022/AR2023 cash-flow notes but not extracted (full-report PDFs not readable in this environment); not needed for any core check.
A55: Provisions less payments | E55: -171 | F55: 289 | G55: -130 | H55: Reported (partial) | I55: Historical Financials excl. Ice Cream (15 Jan 2026) (2023C); FY25 results (12 Feb 2026) p.24 (2024–25) | dataset: Raw Cash Flow r22 | J55: 2021–2023 Original: disclosed in AR2022/AR2023 cash-flow notes but not extracted (full-report PDFs not readable in this environment); not needed for any core check.
A56: Elimination of (profits)/losses on disposals | E56: -440 | F56: 259 | G56: 58 | H56: Reported (partial) | I56: Historical Financials excl. Ice Cream (15 Jan 2026) (2023C); FY25 results (12 Feb 2026) p.24 (2024–25) | dataset: Raw Cash Flow r23 | J56: 2021–2023 Original: disclosed in AR2022/AR2023 cash-flow notes but not extracted (full-report PDFs not readable in this environment); not needed for any core check.
A57: Non-cash charge for share-based compensation | E57: 192 | F57: 292 | G57: 255 | H57: Reported (partial) | I57: Historical Financials excl. Ice Cream (15 Jan 2026) (2023C); FY25 results (12 Feb 2026) p.24 (2024–25) | dataset: Raw Cash Flow r24 | J57: 2021–2023 Original: disclosed in AR2022/AR2023 cash-flow notes but not extracted (full-report PDFs not readable in this environment); not needed for any core check.
A58: Other adjustments | E58: 97 | F58: 116 | G58: 157 | H58: Reported (partial) | I58: Historical Financials excl. Ice Cream (15 Jan 2026) (2023C); FY25 results (12 Feb 2026) p.24 (2024–25) | dataset: Raw Cash Flow r25 | J58: 2021–2023 Original: disclosed in AR2022/AR2023 cash-flow notes but not extracted (full-report PDFs not readable in this environment); not needed for any core check.
A59: Cash flow from operating activities (before tax) | B59: 10305 | C59: 10089 | D59: 11561 | E59: 10326 | F59: 10913 | G59: 10772 | H59: Reported | I59: AR2022; AR2023; AR2025 | dataset: Raw Cash Flow r6 | J59: Unilever FCF starting point. 2023 Continuing–2025: continuing operations.
A60: Income tax paid | B60: -2333 | C60: -2807 | D60: -2135 | E60: -1933 | F60: -2452 | G60: -2720 | H60: Reported | I60: AR2022; AR2023; AR2025 | dataset: Raw Cash Flow r7
A61: Net cash flow from operating activities (after tax) | B61: 7972 | C61: 7282 | D61: 9426 | F61: 8461 | G61: 8052 | H61: Reported (partial) | I61: FY22 results (9 Feb 2023) p.18; FY23 results (8 Feb 2024) p.21; FY25 results (12 Feb 2026) p.24 | dataset: Raw Cash Flow r8 | J61: As reported. 2023 Continuing (8,393) is not printed in the sources accessed; the model calculates it.
A62: Net cash flow from operating activities — discontinued | B62: 0 | C62: 0 | D62: 0 | E62: 1033 | F62: 1058 | G62: 298 | H62: Reported | I62: FY22 results (9 Feb 2023) p.18; FY23 results (8 Feb 2024) p.21; Form 20-F 2025 XBRL (SEC 0000217410-26-000007); FY25 results (12 Feb 2026) p.24 | dataset: Raw Cash Flow r9 | J62: 0 = no discontinued operations presented in that year's cash-flow statement.
A63: CASH FLOW — FCF RECONCILIATION (Unilever definition)
A64: Net capital expenditure | B64: -1239 | C64: -1627 | D64: -1703 | E64: -1420 | F64: -1599 | G64: -1465 | H64: Reported | I64: FCF reconciliation | dataset: Raw Cash Flow r10
A65: Net interest payments | B65: -340 | C65: -457 | D65: -632 | E65: -528 | F65: -559 | G65: -666 | H65: Reported | I65: FCF reconciliation | dataset: Raw Cash Flow r11 | J65: Interest paid net of interest received.
A66: Free cash flow (reported) | B66: 6393 | C66: 5198 | D66: 7091 | E66: 6445 | F66: 6304 | G66: 5921 | H66: Reported | I66: AR2022; AR2023; AR2025 | dataset: Raw Cash Flow r12
A67: CASH FLOW — INVESTING
A68: Purchase of intangible assets | F68: -233 | G68: -174 | H68: Reported (partial) | I68: FY25 results (12 Feb 2026) p.24 | dataset: Raw Cash Flow r27 | J68: 2021–2023: line detail disclosed in AR2022/AR2023/AR2025 cash-flow statements but not extracted; not needed for any core check.
A69: Purchase of property, plant and equipment | F69: -1381 | G69: -1417 | H69: Reported (partial) | I69: FY25 results (12 Feb 2026) p.24 | dataset: Raw Cash Flow r28 | J69: 2021–2023: line detail disclosed in AR2022/AR2023/AR2025 cash-flow statements but not extracted; not needed for any core check.
A70: Disposal of property, plant and equipment | F70: 15 | G70: 126 | H70: Reported (partial) | I70: FY25 results (12 Feb 2026) p.24 | dataset: Raw Cash Flow r29 | J70: 2021–2023: line detail disclosed in AR2022/AR2023/AR2025 cash-flow statements but not extracted; not needed for any core check.
A71: Acquisition of businesses and investments in joint ventures and associates | F71: -734 | G71: -1674 | H71: Reported (partial) | I71: FY25 results (12 Feb 2026) p.24 | dataset: Raw Cash Flow r30 | J71: 2021–2023: line detail disclosed in AR2022/AR2023/AR2025 cash-flow statements but not extracted; not needed for any core check.
A72: Disposal of businesses, joint ventures and associates | F72: 910 | G72: 107 | H72: Reported (partial) | I72: FY25 results (12 Feb 2026) p.24 | dataset: Raw Cash Flow r31 | J72: 2021–2023: line detail disclosed in AR2022/AR2023/AR2025 cash-flow statements but not extracted; not needed for any core check.
A73: Acquisition of other non-current investments | F73: -166 | G73: -111 | H73: Reported (partial) | I73: FY25 results (12 Feb 2026) p.24 | dataset: Raw Cash Flow r32 | J73: 2021–2023: line detail disclosed in AR2022/AR2023/AR2025 cash-flow statements but not extracted; not needed for any core check.
A74: Disposal of other non-current investments | F74: 59 | G74: 239 | H74: Reported (partial) | I74: FY25 results (12 Feb 2026) p.24 | dataset: Raw Cash Flow r33 | J74: 2021–2023: line detail disclosed in AR2022/AR2023/AR2025 cash-flow statements but not extracted; not needed for any core check.
A75: Dividends from joint ventures, associates and other non-current investments | F75: 261 | G75: 243 | H75: Reported (partial) | I75: FY25 results (12 Feb 2026) p.24 | dataset: Raw Cash Flow r34 | J75: 2021–2023: line detail disclosed in AR2022/AR2023/AR2025 cash-flow statements but not extracted; not needed for any core check.
A76: Sale/(purchase) of financial assets | F76: 476 | G76: -85 | H76: Reported (partial) | I76: FY25 results (12 Feb 2026) p.24 | dataset: Raw Cash Flow r35 | J76: 2021–2023: line detail disclosed in AR2022/AR2023/AR2025 cash-flow statements but not extracted; not needed for any core check.
A77: Interest received | B77: 148 | C77: 287 | D77: 267 | F77: 370 | G77: 352 | H77: Reported (partial) | I77: FY22 results (9 Feb 2023) p.18; FY23 results (8 Feb 2024) p.21; FY25 results (12 Feb 2026) p.24 | dataset: Raw Cash Flow r36 | J77: 2023 Continuing not printed in sources accessed.
A78: Net cash flow from investing activities — continuing | B78: -3246 | C78: 2453 | D78: -2294 | E78: -1411 | F78: -423 | G78: -2394 | H78: Reported | I78: FY22 results (9 Feb 2023) p.18; FY23 results (8 Feb 2024) p.21; Historical Financials excl. Ice Cream (15 Jan 2026); FY25 results (12 Feb 2026) p.24 | dataset: Raw Cash Flow r37 | J78: 2021–2023 Original: whole group (no split presented).
A79: Net cash flow from investing activities — discontinued | B79: 0 | C79: 0 | D79: 0 | E79: -883 | F79: -202 | G79: -724 | H79: Reported | I79: Form 20-F 2025 XBRL (SEC 0000217410-26-000007); FY25 results (12 Feb 2026) p.24 | dataset: Raw Cash Flow r38 | J79: 0 = no discontinued operations presented in that year's cash-flow statement.
A80: Net cash flow from investing activities — total | B80: -3246 | C80: 2453 | D80: -2294 | E80: -2294 | F80: -625 | G80: -3118 | H80: Reported | I80: FY22 results (9 Feb 2023) p.18; FY23 results (8 Feb 2024) p.21; Form 20-F 2025 XBRL (SEC 0000217410-26-000007); FY25 results (12 Feb 2026) p.24 | dataset: Raw Cash Flow r39 | J80: 2023 total identical on both bases (SEC XBRL FY2023 and FY2025 filings).
A81: CASH FLOW — FINANCING
A82: Dividends paid on ordinary share capital | B82: -4483 | C82: -4329 | D82: -4363 | E82: -4363 | F82: -4319 | G82: -4453 | H82: Reported | I82: FY22 results (9 Feb 2023) p.18; FY23 results (8 Feb 2024) p.21; Form 20-F 2025 XBRL (SEC 0000217410-26-000007); FY25 results (12 Feb 2026) p.24 | dataset: Raw Cash Flow r41 | J82: 2023 on both bases added in v4 (4,363 in FY2023 and FY2025 20-F XBRL).
A83: Interest paid | B83: -488 | C83: -744 | D83: -899 | E83: -751 | F83: -929 | G83: -1018 | H83: Reported | I83: FY22 results (9 Feb 2023) p.18; FY23 results (8 Feb 2024) p.21; Form 20-F 2025 XBRL (SEC 0000217410-26-000007); FY25 results (12 Feb 2026) p.24 | dataset: Raw Cash Flow r42 | J83: 2023 added in v4: Original 899 (FY23 results; 899 − 267 received = 632 net), Continuing 751 (FY2025 20-F XBRL).
A84: Net change in short-term borrowings | F84: 575 | G84: -2228 | H84: Reported (partial) | I84: FY25 results (12 Feb 2026) p.24 | dataset: Raw Cash Flow r43 | J84: 2021–2023: line detail disclosed in AR2022/AR2023/AR2025 cash-flow statements but not extracted; not needed for any core check.
A85: Additional financial liabilities | F85: 4234 | G85: 4278 | H85: Reported (partial) | I85: FY25 results (12 Feb 2026) p.24 | dataset: Raw Cash Flow r44 | J85: 2021–2023: line detail disclosed in AR2022/AR2023/AR2025 cash-flow statements but not extracted; not needed for any core check.
A86: Repayment of financial liabilities | F86: -3846 | G86: -3547 | H86: Reported (partial) | I86: FY25 results (12 Feb 2026) p.24 | dataset: Raw Cash Flow r45 | J86: 2021–2023: line detail disclosed in AR2022/AR2023/AR2025 cash-flow statements but not extracted; not needed for any core check.
A87: Capital element of lease rental payments | F87: -342 | G87: -301 | H87: Reported (partial) | I87: FY25 results (12 Feb 2026) p.24 | dataset: Raw Cash Flow r46 | J87: 2021–2023: line detail disclosed in AR2022/AR2023/AR2025 cash-flow statements but not extracted; not needed for any core check.
A88: Repurchase of shares | B88: -3018 | C88: -1509 | D88: -1507 | F88: -1508 | G88: -1510 | H88: Reported (partial) | I88: FY22 results (9 Feb 2023) p.18; FY23 results (8 Feb 2024) p.21; FY25 results (12 Feb 2026) p.24 | dataset: Raw Cash Flow r47 | J88: 2023 Original added in v4 (FY23 results). 2023 Continuing not printed in sources accessed.
A89: Other financing activities | F89: -694 | G89: -1105 | H89: Reported (partial) | I89: FY25 results (12 Feb 2026) p.24 | dataset: Raw Cash Flow r48 | J89: 2021–2023: line detail disclosed in AR2022/AR2023/AR2025 cash-flow statements but not extracted; not needed for any core check.
A90: Net cash flow from financing activities — continuing | B90: -7099 | C90: -8890 | D90: -7193 | E90: -7084 | F90: -6829 | G90: -9884 | H90: Reported | I90: FY22 results (9 Feb 2023) p.18; FY23 results (8 Feb 2024) p.21; Historical Financials excl. Ice Cream (15 Jan 2026); FY25 results (12 Feb 2026) p.24 | dataset: Raw Cash Flow r49 | J90: 2021–2023 Original: whole group (no split presented).
A91: Net cash flow from financing activities — discontinued | B91: 0 | C91: 0 | D91: 0 | E91: -109 | F91: -112 | G91: 3070 | H91: Reported | I91: Form 20-F 2025 XBRL (SEC 0000217410-26-000007); FY25 results (12 Feb 2026) p.24 | dataset: Raw Cash Flow r50 | J91: 0 = no discontinued operations presented in that year's cash-flow statement.
A92: Net cash flow from financing activities — total | B92: -7099 | C92: -8890 | D92: -7193 | E92: -7193 | F92: -6941 | G92: -6814 | H92: Reported | I92: FY22 results (9 Feb 2023) p.18; FY23 results (8 Feb 2024) p.21; Form 20-F 2025 XBRL (SEC 0000217410-26-000007); FY25 results (12 Feb 2026) p.24 | dataset: Raw Cash Flow r51
A93: CASH FLOW — CASH BRIDGE (cash-flow-statement cash, net of overdrafts)
A94: Cash and cash equivalents at beginning of year (CF statement) | B94: 5475 | C94: 3387 | D94: 4225 | E94: 4225 | F94: 4045 | G94: 5950 | H94: Reported | I94: FY22 results (9 Feb 2023) p.18; FY23 results (8 Feb 2024) p.21; FY25 results (12 Feb 2026) p.24 | dataset: Raw Cash Flow r53 | J94: 2021 opening = 31 Dec 2020 closing (FY22 results). Group cash is unaffected by re-presentation, so 2023 is the same on both bases.
A95: Net increase/(decrease) in cash and cash equivalents | B95: -2373 | C95: 845 | D95: -61 | F95: 1953 | G95: -1582 | H95: Reported (partial) | I95: FY22 results (9 Feb 2023) p.18; FY23 results (8 Feb 2024) p.21; FY25 results (12 Feb 2026) p.24 | dataset: Raw Cash Flow r54 | J95: 2023 Continuing not printed in sources accessed; not used by the bridge (which rebuilds it).
A96: Effect of foreign exchange rate changes | B96: 285 | C96: -7 | D96: -119 | E96: -119 | F96: -48 | G96: -498 | H96: Reported | I96: FY22 results (9 Feb 2023) p.18; FY23 results (8 Feb 2024) p.21; Form 20-F 2025 XBRL (SEC 0000217410-26-000007); FY25 results (12 Feb 2026) p.24 | dataset: Raw Cash Flow r55
A97: Cash and cash equivalents at end of year (CF statement) | B97: 3387 | C97: 4225 | D97: 4045 | E97: 4045 | F97: 5950 | G97: 3870 | H97: Reported | I97: FY22 results (9 Feb 2023) p.18; FY23 results (8 Feb 2024) p.21; FY25 results (12 Feb 2026) p.24 | dataset: Raw Cash Flow r56 | J97: 2025 value 3,870 now confirmed (FY25 results p.24 and net-debt table p.16).

Sheet HISTORICAL_IS
A1: 03 HISTORICAL_IS — INCOME STATEMENT ENGINE
A2: € million. Costs are shown as positive numbers (as reported in the source). Green = link to RAW_DATA; black = calculation.
A4: €m | B4: 2021 | C4: 2022 | D4: 2023 Original | E4: 2023 Continuing | F4: 2024 | G4: 2025 | H4: Notes
A5: A. Input lines (linked to RAW_DATA)
A6: Turnover | B6: =IF(RAW_DATA!B6="","",RAW_DATA!B6) -> 52444 | C6: =IF(RAW_DATA!C6="","",RAW_DATA!C6) -> 60073 | D6: =IF(RAW_DATA!D6="","",RAW_DATA!D6) -> 59604 | E6: =IF(RAW_DATA!E6="","",RAW_DATA!E6) -> 51680 | F6: =IF(RAW_DATA!F6="","",RAW_DATA!F6) -> 52479 | G6: =IF(RAW_DATA!G6="","",RAW_DATA!G6) -> 50503
A7: Cost of sales | B7: =IF(RAW_DATA!B7="","",RAW_DATA!B7) -> 30259 | C7: =IF(RAW_DATA!C7="","",RAW_DATA!C7) -> 35906 | D7: =IF(RAW_DATA!D7="","",RAW_DATA!D7) -> 34429 | E7: =IF(RAW_DATA!E7="","",RAW_DATA!E7) -> 29180 | F7: =IF(RAW_DATA!F7="","",RAW_DATA!F7) -> 27976 | G7: =IF(RAW_DATA!G7="","",RAW_DATA!G7) -> 26794 | H7: Positive = cost.
A8: Operating profit | B8: =IF(RAW_DATA!B8="","",RAW_DATA!B8) -> 8702 | C8: =IF(RAW_DATA!C8="","",RAW_DATA!C8) -> 10755 | D8: =IF(RAW_DATA!D8="","",RAW_DATA!D8) -> 9758 | E8: =IF(RAW_DATA!E8="","",RAW_DATA!E8) -> 8998 | F8: =IF(RAW_DATA!F8="","",RAW_DATA!F8) -> 8829 | G8: =IF(RAW_DATA!G8="","",RAW_DATA!G8) -> 9037
A9: Net finance costs | B9: =IF(RAW_DATA!B9="","",RAW_DATA!B9) -> 354 | C9: =IF(RAW_DATA!C9="","",RAW_DATA!C9) -> 493 | D9: =IF(RAW_DATA!D9="","",RAW_DATA!D9) -> 486 | E9: =IF(RAW_DATA!E9="","",RAW_DATA!E9) -> 408 | F9: =IF(RAW_DATA!F9="","",RAW_DATA!F9) -> 520 | G9: =IF(RAW_DATA!G9="","",RAW_DATA!G9) -> 503 | H9: Positive = net cost.
A10: Net monetary gain/(loss) from hyperinflationary economies | B10: =IF(RAW_DATA!B10="","",RAW_DATA!B10) -> -74 | C10: =IF(RAW_DATA!C10="","",RAW_DATA!C10) -> -157 | D10: =IF(RAW_DATA!D10="","",RAW_DATA!D10) -> -142 | E10: =IF(RAW_DATA!E10="","",RAW_DATA!E10) -> -169 | F10: =IF(RAW_DATA!F10="","",RAW_DATA!F10) -> -201 | G10: =IF(RAW_DATA!G10="","",RAW_DATA!G10) -> -68 | H10: Other PBT item. Negative = loss.
A11: Share of net profit/(loss) of JVs and associates | B11: =IF(RAW_DATA!B11="","",RAW_DATA!B11) -> 191 | C11: =IF(RAW_DATA!C11="","",RAW_DATA!C11) -> 208 | D11: =IF(RAW_DATA!D11="","",RAW_DATA!D11) -> 231 | E11: =IF(RAW_DATA!E11="","",RAW_DATA!E11) -> 228 | F11: =IF(RAW_DATA!F11="","",RAW_DATA!F11) -> 250 | G11: =IF(RAW_DATA!G11="","",RAW_DATA!G11) -> 245 | H11: Other PBT item. Positive = income.
A12: Other income/(loss) from non-current investments | B12: =IF(RAW_DATA!B12="","",RAW_DATA!B12) -> 91 | C12: =IF(RAW_DATA!C12="","",RAW_DATA!C12) -> 24 | D12: =IF(RAW_DATA!D12="","",RAW_DATA!D12) -> -22 | E12: =IF(RAW_DATA!E12="","",RAW_DATA!E12) -> -22 | F12: =IF(RAW_DATA!F12="","",RAW_DATA!F12) -> 13 | G12: =IF(RAW_DATA!G12="","",RAW_DATA!G12) -> -17 | H12: Other PBT item. Positive = income.
A13: Profit before tax | B13: =IF(RAW_DATA!B13="","",RAW_DATA!B13) -> 8556 | C13: =IF(RAW_DATA!C13="","",RAW_DATA!C13) -> 10337 | D13: =IF(RAW_DATA!D13="","",RAW_DATA!D13) -> 9339 | E13: =IF(RAW_DATA!E13="","",RAW_DATA!E13) -> 8627 | F13: =IF(RAW_DATA!F13="","",RAW_DATA!F13) -> 8371 | G13: =IF(RAW_DATA!G13="","",RAW_DATA!G13) -> 8693
A14: Tax | B14: =IF(RAW_DATA!B14="","",RAW_DATA!B14) -> 1935 | C14: =IF(RAW_DATA!C14="","",RAW_DATA!C14) -> 2068 | D14: =IF(RAW_DATA!D14="","",RAW_DATA!D14) -> 2199 | E14: =IF(RAW_DATA!E14="","",RAW_DATA!E14) -> 1990 | F14: =IF(RAW_DATA!F14="","",RAW_DATA!F14) -> 2332 | G14: =IF(RAW_DATA!G14="","",RAW_DATA!G14) -> 2481 | H14: Positive = charge.
A15: Net profit | B15: =IF(RAW_DATA!B15="","",RAW_DATA!B15) -> 6621 | C15: =IF(RAW_DATA!C15="","",RAW_DATA!C15) -> 8269 | D15: =IF(RAW_DATA!D15="","",RAW_DATA!D15) -> 7140 | E15: =IF(RAW_DATA!E15="","",RAW_DATA!E15) -> 6637 | F15: =IF(RAW_DATA!F15="","",RAW_DATA!F15) -> 6039 | G15: =IF(RAW_DATA!G15="","",RAW_DATA!G15) -> 6213 | H15: 2021–2023 Original: total group net profit. 2023 Continuing–2025: continuing operations.
A16: Memo: implied other PBT items (PBT − operating profit + net finance costs) | B16: =IFERROR(B13-B8+B9,"") -> 208 | C16: =IFERROR(C13-C8+C9,"") -> 75 | D16: =IFERROR(D13-D8+D9,"") -> 67 | E16: =IFERROR(E13-E8+E9,"") -> 37 | F16: =IFERROR(F13-F8+F9,"") -> 62 | G16: =IFERROR(G13-G8+G9,"") -> 159 | H16: Diagnostic only: equals hyperinflation + JV/associate share + other income (tested in Check 1). Not used as an input.
A18: B. Income-statement calculations
A19: Revenue growth (like-for-like) | C19: =IFERROR(C6/B6-1,"") -> 0.14546945 | D19: =IFERROR(D6/C6-1,"") -> -0.0078071679 | F19: =IFERROR(F6/E6-1,"") -> 0.015460526 | G19: =IFERROR(G6/F6-1,"") -> -0.037653157 | H19: 2022 vs 2021; 2023 Original vs 2022; 2024 vs 2023 Continuing; 2025 vs 2024. No 2021 (needs 2020) and no 2023 Continuing (no re-presented 2022).
A20: Operating margin | B20: =IFERROR(B8/B6,"") -> 0.16592937 | C20: =IFERROR(C8/C6,"") -> 0.17903218 | D20: =IFERROR(D8/D6,"") -> 0.16371384 | E20: =IFERROR(E8/E6,"") -> 0.17410991 | F20: =IFERROR(F8/F6,"") -> 0.16823872 | G20: =IFERROR(G8/G6,"") -> 0.17893986
A21: Net margin | B21: =IFERROR(B15/B6,"") -> 0.12624895 | C21: =IFERROR(C15/C6,"") -> 0.13764919 | D21: =IFERROR(D15/D6,"") -> 0.11979062 | E21: =IFERROR(E15/E6,"") -> 0.12842492 | F21: =IFERROR(F15/F6,"") -> 0.1150746 | G21: =IFERROR(G15/G6,"") -> 0.12302239
A22: Effective tax rate | B22: =IFERROR(B14/B13,"") -> 0.22615708 | C22: =IFERROR(C14/C13,"") -> 0.20005804 | D22: =IFERROR(D14/D13,"") -> 0.23546418 | E22: =IFERROR(E14/E13,"") -> 0.23067115 | F22: =IFERROR(F14/F13,"") -> 0.27858081 | G22: =IFERROR(G14/G13,"") -> 0.28540205 | H22: Tax ÷ PBT. Effective, not statutory.
A23: Finance-cost ratio | B23: =IFERROR(B9/B6,"") -> 0.0067500572 | C23: =IFERROR(C9/C6,"") -> 0.0082066819 | D23: =IFERROR(D9/D6,"") -> 0.0081538152 | E23: =IFERROR(E9/E6,"") -> 0.0078947368 | F23: =IFERROR(F9/F6,"") -> 0.0099087254 | G23: =IFERROR(G9/G6,"") -> 0.0099598044 | H23: Net finance costs ÷ turnover.

Sheet HISTORICAL_BS
A1: 04 HISTORICAL_BS — TREASURY-RELEVANT BALANCE SHEET ENGINE
A2: € million, year-end. 2023 Continuing column is not applicable (balance sheets are not re-presented); the 2023 year-end sits in 2023 Original.
A4: €m | B4: 2021 | C4: 2022 | D4: 2023 Original | E4: 2023 Continuing | F4: 2024 | G4: 2025 | H4: Notes
A5: A. Operating assets
A6: Inventories | B6: =IF(RAW_DATA!B17="","",RAW_DATA!B17) -> 4683 | C6: =IF(RAW_DATA!C17="","",RAW_DATA!C17) -> 5931 | D6: =IF(RAW_DATA!D17="","",RAW_DATA!D17) -> 5119 | F6: =IF(RAW_DATA!F17="","",RAW_DATA!F17) -> 5177 | G6: =IF(RAW_DATA!G17="","",RAW_DATA!G17) -> 4043
A7: Trade receivables | B7: =IF(RAW_DATA!B18="","",RAW_DATA!B18) -> 3582 | C7: =IF(RAW_DATA!C18="","",RAW_DATA!C18) -> 4544 | D7: =IF(RAW_DATA!D18="","",RAW_DATA!D18) -> 4023 | F7: =IF(RAW_DATA!F18="","",RAW_DATA!F18) -> 4227 | G7: =IF(RAW_DATA!G18="","",RAW_DATA!G18) -> 4852
A8: Other current receivables | B8: =IF(COUNT(RAW_DATA!B19,RAW_DATA!B18)<2,"",RAW_DATA!B19-RAW_DATA!B18) -> 1840 | C8: =IF(COUNT(RAW_DATA!C19,RAW_DATA!C18)<2,"",RAW_DATA!C19-RAW_DATA!C18) -> 2512 | D8: =IF(COUNT(RAW_DATA!D19,RAW_DATA!D18)<2,"",RAW_DATA!D19-RAW_DATA!D18) -> 1752 | F8: =IF(COUNT(RAW_DATA!F19,RAW_DATA!F18)<2,"",RAW_DATA!F19-RAW_DATA!F18) -> 1784 | G8: =IF(COUNT(RAW_DATA!G19,RAW_DATA!G18)<2,"",RAW_DATA!G19-RAW_DATA!G18) -> 2494 | H8: Derived: total current trade and other receivables − trade receivables.
A9: Total current receivables | B9: =IF(RAW_DATA!B19="","",RAW_DATA!B19) -> 5422 | C9: =IF(RAW_DATA!C19="","",RAW_DATA!C19) -> 7056 | D9: =IF(RAW_DATA!D19="","",RAW_DATA!D19) -> 5775 | F9: =IF(RAW_DATA!F19="","",RAW_DATA!F19) -> 6011 | G9: =IF(RAW_DATA!G19="","",RAW_DATA!G19) -> 7346
A11: B. Liquidity
A12: Cash & cash equivalents (balance sheet) | B12: =IF(RAW_DATA!B24="","",RAW_DATA!B24) -> 3415 | C12: =IF(RAW_DATA!C24="","",RAW_DATA!C24) -> 4326 | D12: =IF(RAW_DATA!D24="","",RAW_DATA!D24) -> 4159 | F12: =IF(RAW_DATA!F24="","",RAW_DATA!F24) -> 6136 | G12: =IF(RAW_DATA!G24="","",RAW_DATA!G24) -> 3941
A13: Other current financial assets | B13: =IF(RAW_DATA!B27="","",RAW_DATA!B27) -> 1156 | C13: =IF(RAW_DATA!C27="","",RAW_DATA!C27) -> 1435 | D13: =IF(RAW_DATA!D27="","",RAW_DATA!D27) -> 1731 | F13: =IF(RAW_DATA!F27="","",RAW_DATA!F27) -> 1330 | G13: =IF(RAW_DATA!G27="","",RAW_DATA!G27) -> 1121
A14: Total liquidity | B14: =IFERROR(B12+B13,"") -> 4571 | C14: =IFERROR(C12+C13,"") -> 5761 | D14: =IFERROR(D12+D13,"") -> 5890 | F14: =IFERROR(F12+F13,"") -> 7466 | G14: =IFERROR(G12+G13,"") -> 5062 | H14: Cash + other current financial assets. Excludes undrawn facilities; includes restricted cash.
A16: C. Cash definitions — kept separate, never combined
A17: Cash & equivalents — balance sheet | B17: =IF(RAW_DATA!B24="","",RAW_DATA!B24) -> 3415 | C17: =IF(RAW_DATA!C24="","",RAW_DATA!C24) -> 4326 | D17: =IF(RAW_DATA!D24="","",RAW_DATA!D24) -> 4159 | F17: =IF(RAW_DATA!F24="","",RAW_DATA!F24) -> 6136 | G17: =IF(RAW_DATA!G24="","",RAW_DATA!G24) -> 3941
A18: Cash & equivalents — cash-flow statement (net of overdrafts) | B18: =IF(RAW_DATA!B97="","",RAW_DATA!B97) -> 3387 | C18: =IF(RAW_DATA!C97="","",RAW_DATA!C97) -> 4225 | D18: =IF(RAW_DATA!D97="","",RAW_DATA!D97) -> 4045 | F18: =IF(RAW_DATA!F97="","",RAW_DATA!F97) -> 5950 | G18: =IF(RAW_DATA!G97="","",RAW_DATA!G97) -> 3870 | H18: Cash-flow-statement closing balance.
A19: Bank overdrafts | B19: =IF(RAW_DATA!B25="","",RAW_DATA!B25) -> 106 | C19: =IF(RAW_DATA!C25="","",RAW_DATA!C25) -> 101 | D19: =IF(RAW_DATA!D25="","",RAW_DATA!D25) -> 116 | F19: =IF(RAW_DATA!F25="","",RAW_DATA!F25) -> 180 | G19: =IF(RAW_DATA!G25="","",RAW_DATA!G25) -> 65
A20: Cash held for sale — reconciling adjustment (as printed) | B20: =IF(RAW_DATA!B26="","",RAW_DATA!B26) -> -78 | C20: =IF(RAW_DATA!C26="","",RAW_DATA!C26) -> 0 | D20: =IF(RAW_DATA!D26="","",RAW_DATA!D26) -> -2 | F20: =IF(RAW_DATA!F26="","",RAW_DATA!F26) -> 6 | G20: =IF(RAW_DATA!G26="","",RAW_DATA!G26) -> 6 | H20: Sign as printed in Unilever's net-debt table (brackets = deduction). CF cash + overdrafts + this = balance-sheet cash.
A21: Other current financial assets | B21: =IF(RAW_DATA!B27="","",RAW_DATA!B27) -> 1156 | C21: =IF(RAW_DATA!C27="","",RAW_DATA!C27) -> 1435 | D21: =IF(RAW_DATA!D27="","",RAW_DATA!D27) -> 1731 | F21: =IF(RAW_DATA!F27="","",RAW_DATA!F27) -> 1330 | G21: =IF(RAW_DATA!G27="","",RAW_DATA!G27) -> 1121
A22: Non-current financial asset derivatives related to financial liabilities | B22: =IF(RAW_DATA!B28="","",RAW_DATA!B28) -> 52 | C22: =IF(RAW_DATA!C28="","",RAW_DATA!C28) -> 51 | D22: =IF(RAW_DATA!D28="","",RAW_DATA!D28) -> 75 | F22: =IF(RAW_DATA!F28="","",RAW_DATA!F28) -> 68 | G22: =IF(RAW_DATA!G28="","",RAW_DATA!G28) -> 140
A23: Memo: balance-sheet cash − cash-flow-statement cash | B23: =IFERROR(B17-B18,"") -> 28 | C23: =IFERROR(C17-C18,"") -> 101 | D23: =IFERROR(D17-D18,"") -> 114 | F23: =IFERROR(F17-F18,"") -> 186 | G23: =IFERROR(G17-G18,"") -> 71 | H23: Equals overdrafts + held-for-sale adjustment (tested on HISTORICAL_CHECKS, S1).
A25: D. Operating liabilities
A26: Trade payables | B26: =IF(RAW_DATA!B20="","",RAW_DATA!B20) -> 8896 | C26: =IF(RAW_DATA!C20="","",RAW_DATA!C20) -> 11100 | D26: =IF(RAW_DATA!D20="","",RAW_DATA!D20) -> 10355 | F26: =IF(RAW_DATA!F20="","",RAW_DATA!F20) -> 10258 | G26: =IF(RAW_DATA!G20="","",RAW_DATA!G20) -> 10994
A27: Accruals | B27: =IF(RAW_DATA!B21="","",RAW_DATA!B21) -> 4429 | C27: =IF(RAW_DATA!C21="","",RAW_DATA!C21) -> 5232 | D27: =IF(RAW_DATA!D21="","",RAW_DATA!D21) -> 5057 | F27: =IF(RAW_DATA!F21="","",RAW_DATA!F21) -> 5053 | G27: =IF(RAW_DATA!G21="","",RAW_DATA!G21) -> 4649
A28: Other current operating liabilities | B28: =IF(COUNT(RAW_DATA!B22,RAW_DATA!B20,RAW_DATA!B21)<3,"",RAW_DATA!B22-RAW_DATA!B20-RAW_DATA!B21) -> 1536 | C28: =IF(COUNT(RAW_DATA!C22,RAW_DATA!C20,RAW_DATA!C21)<3,"",RAW_DATA!C22-RAW_DATA!C20-RAW_DATA!C21) -> 1691 | D28: =IF(COUNT(RAW_DATA!D22,RAW_DATA!D20,RAW_DATA!D21)<3,"",RAW_DATA!D22-RAW_DATA!D20-RAW_DATA!D21) -> 1445 | F28: =IF(COUNT(RAW_DATA!F22,RAW_DATA!F20,RAW_DATA!F21)<3,"",RAW_DATA!F22-RAW_DATA!F20-RAW_DATA!F21) -> 1379 | G28: =IF(COUNT(RAW_DATA!G22,RAW_DATA!G20,RAW_DATA!G21)<3,"",RAW_DATA!G22-RAW_DATA!G20-RAW_DATA!G21) -> 1296 | H28: Derived: total trade payables and other current liabilities − trade payables − accruals.
A29: Total operating liabilities | B29: =IF(RAW_DATA!B22="","",RAW_DATA!B22) -> 14861 | C29: =IF(RAW_DATA!C22="","",RAW_DATA!C22) -> 18023 | D29: =IF(RAW_DATA!D22="","",RAW_DATA!D22) -> 16857 | F29: =IF(RAW_DATA!F22="","",RAW_DATA!F22) -> 16690 | G29: =IF(RAW_DATA!G22="","",RAW_DATA!G22) -> 16939 | H29: Reported 'trade payables and other current liabilities'.
A30: Operating NWC (inventories + total current receivables − total operating liabilities) | B30: =IFERROR(B6+B9-B29,"") -> -4756 | C30: =IFERROR(C6+C9-C29,"") -> -5036 | D30: =IFERROR(D6+D9-D29,"") -> -5963 | F30: =IFERROR(F6+F9-F29,"") -> -5502 | G30: =IFERROR(G6+G9-G29,"") -> -5550 | H30: Historical base only — not used for forecasting in Step 2. Negative = operating liabilities exceed operating assets.
A32: E. Financial liabilities — current
A33: Bank loans and overdrafts | B33: =IF(RAW_DATA!B36="","",RAW_DATA!B36) | C33: =IF(RAW_DATA!C36="","",RAW_DATA!C36) | D33: =IF(RAW_DATA!D36="","",RAW_DATA!D36) | F33: =IF(RAW_DATA!F36="","",RAW_DATA!F36) | G33: =IF(RAW_DATA!G36="","",RAW_DATA!G36)
A34: Bonds and other loans | B34: =IF(RAW_DATA!B37="","",RAW_DATA!B37) | C34: =IF(RAW_DATA!C37="","",RAW_DATA!C37) | D34: =IF(RAW_DATA!D37="","",RAW_DATA!D37) | F34: =IF(RAW_DATA!F37="","",RAW_DATA!F37) | G34: =IF(RAW_DATA!G37="","",RAW_DATA!G37)
A35: Lease liabilities | B35: =IF(RAW_DATA!B38="","",RAW_DATA!B38) | C35: =IF(RAW_DATA!C38="","",RAW_DATA!C38) | D35: =IF(RAW_DATA!D38="","",RAW_DATA!D38) | F35: =IF(RAW_DATA!F38="","",RAW_DATA!F38) | G35: =IF(RAW_DATA!G38="","",RAW_DATA!G38)
A36: Derivatives | B36: =IF(RAW_DATA!B39="","",RAW_DATA!B39) | C36: =IF(RAW_DATA!C39="","",RAW_DATA!C39) | D36: =IF(RAW_DATA!D39="","",RAW_DATA!D39) | F36: =IF(RAW_DATA!F39="","",RAW_DATA!F39) | G36: =IF(RAW_DATA!G39="","",RAW_DATA!G39)
A37: Other financial liabilities | B37: =IF(RAW_DATA!B40="","",RAW_DATA!B40) | C37: =IF(RAW_DATA!C40="","",RAW_DATA!C40) | D37: =IF(RAW_DATA!D40="","",RAW_DATA!D40) | F37: =IF(RAW_DATA!F40="","",RAW_DATA!F40) | G37: =IF(RAW_DATA!G40="","",RAW_DATA!G40)
A38: Sum of current categories | B38: =IFERROR(B33+B34+B35+B36+B37,"") | C38: =IFERROR(C33+C34+C35+C36+C37,"") | D38: =IFERROR(D33+D34+D35+D36+D37,"") | F38: =IFERROR(F33+F34+F35+F36+F37,"") | G38: =IFERROR(G33+G34+G35+G36+G37,"") | H38: Blank until every category is sourced.
A39: Total current financial liabilities (reported) | B39: =IF(RAW_DATA!B29="","",RAW_DATA!B29) -> 7252 | C39: =IF(RAW_DATA!C29="","",RAW_DATA!C29) -> 5775 | D39: =IF(RAW_DATA!D29="","",RAW_DATA!D29) -> 5087 | F39: =IF(RAW_DATA!F29="","",RAW_DATA!F29) -> 6987 | G39: =IF(RAW_DATA!G29="","",RAW_DATA!G29) -> 2582
A40: E. Financial liabilities — non-current
A41: Bank loans and overdrafts | B41: =IF(RAW_DATA!B41="","",RAW_DATA!B41) | C41: =IF(RAW_DATA!C41="","",RAW_DATA!C41) | D41: =IF(RAW_DATA!D41="","",RAW_DATA!D41) | F41: =IF(RAW_DATA!F41="","",RAW_DATA!F41) | G41: =IF(RAW_DATA!G41="","",RAW_DATA!G41)
A42: Bonds and other loans | B42: =IF(RAW_DATA!B42="","",RAW_DATA!B42) | C42: =IF(RAW_DATA!C42="","",RAW_DATA!C42) | D42: =IF(RAW_DATA!D42="","",RAW_DATA!D42) | F42: =IF(RAW_DATA!F42="","",RAW_DATA!F42) | G42: =IF(RAW_DATA!G42="","",RAW_DATA!G42)
A43: Lease liabilities | B43: =IF(RAW_DATA!B43="","",RAW_DATA!B43) | C43: =IF(RAW_DATA!C43="","",RAW_DATA!C43) | D43: =IF(RAW_DATA!D43="","",RAW_DATA!D43) | F43: =IF(RAW_DATA!F43="","",RAW_DATA!F43) | G43: =IF(RAW_DATA!G43="","",RAW_DATA!G43)
A44: Derivatives | B44: =IF(RAW_DATA!B44="","",RAW_DATA!B44) | C44: =IF(RAW_DATA!C44="","",RAW_DATA!C44) | D44: =IF(RAW_DATA!D44="","",RAW_DATA!D44) | F44: =IF(RAW_DATA!F44="","",RAW_DATA!F44) | G44: =IF(RAW_DATA!G44="","",RAW_DATA!G44)
A45: Other financial liabilities | B45: =IF(RAW_DATA!B45="","",RAW_DATA!B45) | C45: =IF(RAW_DATA!C45="","",RAW_DATA!C45) | D45: =IF(RAW_DATA!D45="","",RAW_DATA!D45) | F45: =IF(RAW_DATA!F45="","",RAW_DATA!F45) | G45: =IF(RAW_DATA!G45="","",RAW_DATA!G45)
A46: Sum of non-current categories | B46: =IFERROR(B41+B42+B43+B44+B45,"") | C46: =IFERROR(C41+C42+C43+C44+C45,"") | D46: =IFERROR(D41+D42+D43+D44+D45,"") | F46: =IFERROR(F41+F42+F43+F44+F45,"") | G46: =IFERROR(G41+G42+G43+G44+G45,"")
A47: Total non-current financial liabilities (reported) | B47: =IF(RAW_DATA!B30="","",RAW_DATA!B30) -> 22881 | C47: =IF(RAW_DATA!C30="","",RAW_DATA!C30) -> 23713 | D47: =IF(RAW_DATA!D30="","",RAW_DATA!D30) -> 24535 | F47: =IF(RAW_DATA!F30="","",RAW_DATA!F30) -> 25066 | G47: =IF(RAW_DATA!G30="","",RAW_DATA!G30) -> 25696
A48: E. Financial liabilities — total
A49: Total financial liabilities (current + non-current) | B49: =IFERROR(B39+B47,"") -> 30133 | C49: =IFERROR(C39+C47,"") -> 29488 | D49: =IFERROR(D39+D47,"") -> 29622 | F49: =IFERROR(F39+F47,"") -> 32053 | G49: =IFERROR(G39+G47,"") -> 28278
A50: Total financial liabilities (reported) | B50: =IF(RAW_DATA!B31="","",RAW_DATA!B31) -> 30133 | C50: =IF(RAW_DATA!C31="","",RAW_DATA!C31) -> 29488 | D50: =IF(RAW_DATA!D31="","",RAW_DATA!D31) -> 29622 | F50: =IF(RAW_DATA!F31="","",RAW_DATA!F31) -> 32053 | G50: =IF(RAW_DATA!G31="","",RAW_DATA!G31) -> 28278
A51: Memo: bonds and other loans — total (reported) | B51: =IF(RAW_DATA!B34="","",RAW_DATA!B34) -> 27621 | C51: =IF(RAW_DATA!C34="","",RAW_DATA!C34) -> 26512 | D51: =IF(RAW_DATA!D34="","",RAW_DATA!D34) | F51: =IF(RAW_DATA!F34="","",RAW_DATA!F34) | G51: =IF(RAW_DATA!G34="","",RAW_DATA!G34) -> 26038
A52: Memo: bank loans and overdrafts — total (reported) | B52: =IF(RAW_DATA!B35="","",RAW_DATA!B35) -> 402 | C52: =IF(RAW_DATA!C35="","",RAW_DATA!C35) -> 519 | D52: =IF(RAW_DATA!D35="","",RAW_DATA!D35) | F52: =IF(RAW_DATA!F35="","",RAW_DATA!F35) | G52: =IF(RAW_DATA!G35="","",RAW_DATA!G35) -> 233
A54: F. Net debt — Unilever reconciliation
A55: Total financial liabilities | B55: =B49 -> 30133 | C55: =C49 -> 29488 | D55: =D49 -> 29622 | F55: =F49 -> 32053 | G55: =G49 -> 28278
A56: Less: cash & cash equivalents (balance sheet) | B56: =IFERROR(-B12,"") -> -3415 | C56: =IFERROR(-C12,"") -> -4326 | D56: =IFERROR(-D12,"") -> -4159 | F56: =IFERROR(-F12,"") -> -6136 | G56: =IFERROR(-G12,"") -> -3941 | H56: Balance-sheet cash = CF-statement cash + overdrafts + held-for-sale adjustment (section C). Using it directly avoids double-counting those items.
A57: Less: other current financial assets | B57: =IFERROR(-B13,"") -> -1156 | C57: =IFERROR(-C13,"") -> -1435 | D57: =IFERROR(-D13,"") -> -1731 | F57: =IFERROR(-F13,"") -> -1330 | G57: =IFERROR(-G13,"") -> -1121
A58: Less: non-current financial asset derivatives related to financial liabilities | B58: =IFERROR(-B22,"") -> -52 | C58: =IFERROR(-C22,"") -> -51 | D58: =IFERROR(-D22,"") -> -75 | F58: =IFERROR(-F22,"") -> -68 | G58: =IFERROR(-G22,"") -> -140 | H58: From Unilever's net-debt reconciliation.
A59: Model net debt | B59: =IFERROR(B55+B56+B57+B58,"") -> 25510 | C59: =IFERROR(C55+C56+C57+C58,"") -> 23676 | D59: =IFERROR(D55+D56+D57+D58,"") -> 23657 | F59: =IFERROR(F55+F56+F57+F58,"") -> 24519 | G59: =IFERROR(G55+G56+G57+G58,"") -> 23076
A60: Reported net debt | B60: =IF(RAW_DATA!B32="","",RAW_DATA!B32) -> 25510 | C60: =IF(RAW_DATA!C32="","",RAW_DATA!C32) -> 23676 | D60: =IF(RAW_DATA!D32="","",RAW_DATA!D32) -> 23657 | F60: =IF(RAW_DATA!F32="","",RAW_DATA!F32) -> 24519 | G60: =IF(RAW_DATA!G32="","",RAW_DATA!G32) -> 23076
A61: Net debt check (model − reported) | B61: =IFERROR(B59-B60,"") -> 0 | C61: =IFERROR(C59-C60,"") -> 0 | D61: =IFERROR(D59-D60,"") -> 0 | F61: =IFERROR(F59-F60,"") -> 0 | G61: =IFERROR(G59-G60,"") -> 0
A62: Memo: gap before non-current derivatives (TFL − cash − other CFA − reported ND) | B62: =IFERROR(B55+B56+B57-B60,"") -> 52 | C62: =IFERROR(C55+C56+C57-C60,"") -> 51 | D62: =IFERROR(D55+D56+D57-D60,"") -> 75 | F62: =IFERROR(F55+F56+F57-F60,"") -> 68 | G62: =IFERROR(G55+G56+G57-G60,"") -> 140 | H62: Diagnostic: equals the reported derivative line above in every year. Not a plug.

Sheet HISTORICAL_CF
A1: 05 HISTORICAL_CF — CASH-FLOW ENGINE
A2: € million. Inflows positive, outflows negative (as reported). 2023 Continuing–2025 on the AR2025 continuing basis.
A4: €m | B4: 2021 | C4: 2022 | D4: 2023 Original | E4: 2023 Continuing | F4: 2024 | G4: 2025 | H4: Notes
A5: A. Operating cash flow
A6: Net profit from continuing operations | B6: =IF(RAW_DATA!B47="","",RAW_DATA!B47) | C6: =IF(RAW_DATA!C47="","",RAW_DATA!C47) | D6: =IF(RAW_DATA!D47="","",RAW_DATA!D47) | E6: =IF(RAW_DATA!E47="","",RAW_DATA!E47) | F6: =IF(RAW_DATA!F47="","",RAW_DATA!F47) -> 6039 | G6: =IF(RAW_DATA!G47="","",RAW_DATA!G47) -> 6213
A7: Taxation | B7: =IF(RAW_DATA!B48="","",RAW_DATA!B48) | C7: =IF(RAW_DATA!C48="","",RAW_DATA!C48) | D7: =IF(RAW_DATA!D48="","",RAW_DATA!D48) | E7: =IF(RAW_DATA!E48="","",RAW_DATA!E48) | F7: =IF(RAW_DATA!F48="","",RAW_DATA!F48) -> 2332 | G7: =IF(RAW_DATA!G48="","",RAW_DATA!G48) -> 2481
A8: JV/associate and non-current investment income | B8: =IF(RAW_DATA!B49="","",RAW_DATA!B49) | C8: =IF(RAW_DATA!C49="","",RAW_DATA!C49) | D8: =IF(RAW_DATA!D49="","",RAW_DATA!D49) | E8: =IF(RAW_DATA!E49="","",RAW_DATA!E49) | F8: =IF(RAW_DATA!F49="","",RAW_DATA!F49) -> -263 | G8: =IF(RAW_DATA!G49="","",RAW_DATA!G49) -> -228
A9: Hyperinflationary adjustments | B9: =IF(RAW_DATA!B50="","",RAW_DATA!B50) | C9: =IF(RAW_DATA!C50="","",RAW_DATA!C50) | D9: =IF(RAW_DATA!D50="","",RAW_DATA!D50) | E9: =IF(RAW_DATA!E50="","",RAW_DATA!E50) | F9: =IF(RAW_DATA!F50="","",RAW_DATA!F50) -> 201 | G9: =IF(RAW_DATA!G50="","",RAW_DATA!G50) -> 68
A10: Net finance costs | B10: =IF(RAW_DATA!B51="","",RAW_DATA!B51) | C10: =IF(RAW_DATA!C51="","",RAW_DATA!C51) | D10: =IF(RAW_DATA!D51="","",RAW_DATA!D51) | E10: =IF(RAW_DATA!E51="","",RAW_DATA!E51) | F10: =IF(RAW_DATA!F51="","",RAW_DATA!F51) -> 520 | G10: =IF(RAW_DATA!G51="","",RAW_DATA!G51) -> 503
A11: Depreciation, amortisation and impairment | B11: =IF(RAW_DATA!B52="","",RAW_DATA!B52) | C11: =IF(RAW_DATA!C52="","",RAW_DATA!C52) | D11: =IF(RAW_DATA!D52="","",RAW_DATA!D52) | E11: =IF(RAW_DATA!E52="","",RAW_DATA!E52) -> 1148 | F11: =IF(RAW_DATA!F52="","",RAW_DATA!F52) -> 1370 | G11: =IF(RAW_DATA!G52="","",RAW_DATA!G52) -> 1353
A12: Changes in working capital | B12: =IF(RAW_DATA!B53="","",RAW_DATA!B53) | C12: =IF(RAW_DATA!C53="","",RAW_DATA!C53) | D12: =IF(RAW_DATA!D53="","",RAW_DATA!D53) | E12: =IF(RAW_DATA!E53="","",RAW_DATA!E53) -> 753 | F12: =IF(RAW_DATA!F53="","",RAW_DATA!F53) -> -188 | G12: =IF(RAW_DATA!G53="","",RAW_DATA!G53) -> 116
A13: Pensions | B13: =IF(RAW_DATA!B54="","",RAW_DATA!B54) | C13: =IF(RAW_DATA!C54="","",RAW_DATA!C54) | D13: =IF(RAW_DATA!D54="","",RAW_DATA!D54) | E13: =IF(RAW_DATA!E54="","",RAW_DATA!E54) -> -251 | F13: =IF(RAW_DATA!F54="","",RAW_DATA!F54) -> -54 | G13: =IF(RAW_DATA!G54="","",RAW_DATA!G54) -> -74
A14: Provisions | B14: =IF(RAW_DATA!B55="","",RAW_DATA!B55) | C14: =IF(RAW_DATA!C55="","",RAW_DATA!C55) | D14: =IF(RAW_DATA!D55="","",RAW_DATA!D55) | E14: =IF(RAW_DATA!E55="","",RAW_DATA!E55) -> -171 | F14: =IF(RAW_DATA!F55="","",RAW_DATA!F55) -> 289 | G14: =IF(RAW_DATA!G55="","",RAW_DATA!G55) -> -130
A15: Disposal adjustments | B15: =IF(RAW_DATA!B56="","",RAW_DATA!B56) | C15: =IF(RAW_DATA!C56="","",RAW_DATA!C56) | D15: =IF(RAW_DATA!D56="","",RAW_DATA!D56) | E15: =IF(RAW_DATA!E56="","",RAW_DATA!E56) -> -440 | F15: =IF(RAW_DATA!F56="","",RAW_DATA!F56) -> 259 | G15: =IF(RAW_DATA!G56="","",RAW_DATA!G56) -> 58
A16: Share-based compensation | B16: =IF(RAW_DATA!B57="","",RAW_DATA!B57) | C16: =IF(RAW_DATA!C57="","",RAW_DATA!C57) | D16: =IF(RAW_DATA!D57="","",RAW_DATA!D57) | E16: =IF(RAW_DATA!E57="","",RAW_DATA!E57) -> 192 | F16: =IF(RAW_DATA!F57="","",RAW_DATA!F57) -> 292 | G16: =IF(RAW_DATA!G57="","",RAW_DATA!G57) -> 255
A17: Other adjustments | B17: =IF(RAW_DATA!B58="","",RAW_DATA!B58) | C17: =IF(RAW_DATA!C58="","",RAW_DATA!C58) | D17: =IF(RAW_DATA!D58="","",RAW_DATA!D58) | E17: =IF(RAW_DATA!E58="","",RAW_DATA!E58) -> 97 | F17: =IF(RAW_DATA!F58="","",RAW_DATA!F58) -> 116 | G17: =IF(RAW_DATA!G58="","",RAW_DATA!G58) -> 157
A18: Sum of components | B18: =IFERROR(B6+B7+B8+B9+B10+B11+B12+B13+B14+B15+B16+B17,"") | C18: =IFERROR(C6+C7+C8+C9+C10+C11+C12+C13+C14+C15+C16+C17,"") | D18: =IFERROR(D6+D7+D8+D9+D10+D11+D12+D13+D14+D15+D16+D17,"") | E18: =IFERROR(E6+E7+E8+E9+E10+E11+E12+E13+E14+E15+E16+E17,"") | F18: =IFERROR(F6+F7+F8+F9+F10+F11+F12+F13+F14+F15+F16+F17,"") -> 10913 | G18: =IFERROR(G6+G7+G8+G9+G10+G11+G12+G13+G14+G15+G16+G17,"") -> 10772 | H18: Blank until every component is sourced; tested against reported operating cash flow (S4).
A19: Operating cash flow (cash flow from operating activities, before tax) | B19: =IF(RAW_DATA!B59="","",RAW_DATA!B59) -> 10305 | C19: =IF(RAW_DATA!C59="","",RAW_DATA!C59) -> 10089 | D19: =IF(RAW_DATA!D59="","",RAW_DATA!D59) -> 11561 | E19: =IF(RAW_DATA!E59="","",RAW_DATA!E59) -> 10326 | F19: =IF(RAW_DATA!F59="","",RAW_DATA!F59) -> 10913 | G19: =IF(RAW_DATA!G59="","",RAW_DATA!G59) -> 10772 | H19: Unilever's FCF starting point. 2023 Continuing–2025 are continuing operations only.
A20: Income tax paid | B20: =IF(RAW_DATA!B60="","",RAW_DATA!B60) -> -2333 | C20: =IF(RAW_DATA!C60="","",RAW_DATA!C60) -> -2807 | D20: =IF(RAW_DATA!D60="","",RAW_DATA!D60) -> -2135 | E20: =IF(RAW_DATA!E60="","",RAW_DATA!E60) -> -1933 | F20: =IF(RAW_DATA!F60="","",RAW_DATA!F60) -> -2452 | G20: =IF(RAW_DATA!G60="","",RAW_DATA!G60) -> -2720
A21: Net operating cash flow after tax — continuing (calculated) | B21: =IFERROR(B19+B20,"") -> 7972 | C21: =IFERROR(C19+C20,"") -> 7282 | D21: =IFERROR(D19+D20,"") -> 9426 | E21: =IFERROR(E19+E20,"") -> 8393 | F21: =IFERROR(F19+F20,"") -> 8461 | G21: =IFERROR(G19+G20,"") -> 8052 | H21: 2021–2023 Original: whole group (no discontinued split then).
A22: Net operating cash flow after tax (reported) | B22: =IF(RAW_DATA!B61="","",RAW_DATA!B61) -> 7972 | C22: =IF(RAW_DATA!C61="","",RAW_DATA!C61) -> 7282 | D22: =IF(RAW_DATA!D61="","",RAW_DATA!D61) -> 9426 | E22: =IF(RAW_DATA!E61="","",RAW_DATA!E61) | F22: =IF(RAW_DATA!F61="","",RAW_DATA!F61) -> 8461 | G22: =IF(RAW_DATA!G61="","",RAW_DATA!G61) -> 8052 | H22: As printed; 2023 Continuing not printed in sources accessed. Tested in S7.
A23: Net operating cash flow — discontinued | B23: =IF(RAW_DATA!B62="","",RAW_DATA!B62) -> 0 | C23: =IF(RAW_DATA!C62="","",RAW_DATA!C62) -> 0 | D23: =IF(RAW_DATA!D62="","",RAW_DATA!D62) -> 0 | E23: =IF(RAW_DATA!E62="","",RAW_DATA!E62) -> 1033 | F23: =IF(RAW_DATA!F62="","",RAW_DATA!F62) -> 1058 | G23: =IF(RAW_DATA!G62="","",RAW_DATA!G62) -> 298 | H23: 0 for 2021–2023 Original: no discontinued operations presented then.
A24: Net operating cash flow — total | B24: =IFERROR(B21+B23,"") -> 7972 | C24: =IFERROR(C21+C23,"") -> 7282 | D24: =IFERROR(D21+D23,"") -> 9426 | E24: =IFERROR(E21+E23,"") -> 9426 | F24: =IFERROR(F21+F23,"") -> 9519 | G24: =IFERROR(G21+G23,"") -> 8350
A26: B. Investing cash flow
A27: Net capital expenditure | B27: =IF(RAW_DATA!B64="","",RAW_DATA!B64) -> -1239 | C27: =IF(RAW_DATA!C64="","",RAW_DATA!C64) -> -1627 | D27: =IF(RAW_DATA!D64="","",RAW_DATA!D64) -> -1703 | E27: =IF(RAW_DATA!E64="","",RAW_DATA!E64) -> -1420 | F27: =IF(RAW_DATA!F64="","",RAW_DATA!F64) -> -1599 | G27: =IF(RAW_DATA!G64="","",RAW_DATA!G64) -> -1465 | H27: Per Unilever FCF reconciliation.
A28: Acquisitions (businesses and JV/associate investments) | B28: =IF(RAW_DATA!B71="","",RAW_DATA!B71) | C28: =IF(RAW_DATA!C71="","",RAW_DATA!C71) | D28: =IF(RAW_DATA!D71="","",RAW_DATA!D71) | E28: =IF(RAW_DATA!E71="","",RAW_DATA!E71) | F28: =IF(RAW_DATA!F71="","",RAW_DATA!F71) -> -734 | G28: =IF(RAW_DATA!G71="","",RAW_DATA!G71) -> -1674
A29: Disposals (businesses, JVs and associates) | B29: =IF(RAW_DATA!B72="","",RAW_DATA!B72) | C29: =IF(RAW_DATA!C72="","",RAW_DATA!C72) | D29: =IF(RAW_DATA!D72="","",RAW_DATA!D72) | E29: =IF(RAW_DATA!E72="","",RAW_DATA!E72) | F29: =IF(RAW_DATA!F72="","",RAW_DATA!F72) -> 910 | G29: =IF(RAW_DATA!G72="","",RAW_DATA!G72) -> 107
A30: Financial investments (sale/(purchase) of financial assets) | B30: =IF(RAW_DATA!B76="","",RAW_DATA!B76) | C30: =IF(RAW_DATA!C76="","",RAW_DATA!C76) | D30: =IF(RAW_DATA!D76="","",RAW_DATA!D76) | E30: =IF(RAW_DATA!E76="","",RAW_DATA!E76) | F30: =IF(RAW_DATA!F76="","",RAW_DATA!F76) -> 476 | G30: =IF(RAW_DATA!G76="","",RAW_DATA!G76) -> -85
A31: Interest received | B31: =IF(RAW_DATA!B77="","",RAW_DATA!B77) -> 148 | C31: =IF(RAW_DATA!C77="","",RAW_DATA!C77) -> 287 | D31: =IF(RAW_DATA!D77="","",RAW_DATA!D77) -> 267 | E31: =IF(RAW_DATA!E77="","",RAW_DATA!E77) | F31: =IF(RAW_DATA!F77="","",RAW_DATA!F77) -> 370 | G31: =IF(RAW_DATA!G77="","",RAW_DATA!G77) -> 352
A32: Other investing movements | B32: =IF(COUNT(RAW_DATA!B73,RAW_DATA!B74,RAW_DATA!B75)<3,"",RAW_DATA!B73+RAW_DATA!B74+RAW_DATA!B75) | C32: =IF(COUNT(RAW_DATA!C73,RAW_DATA!C74,RAW_DATA!C75)<3,"",RAW_DATA!C73+RAW_DATA!C74+RAW_DATA!C75) | D32: =IF(COUNT(RAW_DATA!D73,RAW_DATA!D74,RAW_DATA!D75)<3,"",RAW_DATA!D73+RAW_DATA!D74+RAW_DATA!D75) | E32: =IF(COUNT(RAW_DATA!E73,RAW_DATA!E74,RAW_DATA!E75)<3,"",RAW_DATA!E73+RAW_DATA!E74+RAW_DATA!E75) | F32: =IF(COUNT(RAW_DATA!F73,RAW_DATA!F74,RAW_DATA!F75)<3,"",RAW_DATA!F73+RAW_DATA!F74+RAW_DATA!F75) -> 154 | G32: =IF(COUNT(RAW_DATA!G73,RAW_DATA!G74,RAW_DATA!G75)<3,"",RAW_DATA!G73+RAW_DATA!G74+RAW_DATA!G75) -> 371 | H32: Derived: other non-current investments acquired + disposed + dividends from JVs/associates (reported lines in RAW_DATA).
A33: Memo: sum of investing lines | B33: =IFERROR(B27+B28+B29+B30+B31+B32,"") | C33: =IFERROR(C27+C28+C29+C30+C31+C32,"") | D33: =IFERROR(D27+D28+D29+D30+D31+D32,"") | E33: =IFERROR(E27+E28+E29+E30+E31+E32,"") | F33: =IFERROR(F27+F28+F29+F30+F31+F32,"") -> -423 | G33: =IFERROR(G27+G28+G29+G30+G31+G32,"") -> -2394 | H33: Should equal continuing investing cash flow (S8).
A34: Continuing investing cash flow | B34: =IF(RAW_DATA!B78="","",RAW_DATA!B78) -> -3246 | C34: =IF(RAW_DATA!C78="","",RAW_DATA!C78) -> 2453 | D34: =IF(RAW_DATA!D78="","",RAW_DATA!D78) -> -2294 | E34: =IF(RAW_DATA!E78="","",RAW_DATA!E78) -> -1411 | F34: =IF(RAW_DATA!F78="","",RAW_DATA!F78) -> -423 | G34: =IF(RAW_DATA!G78="","",RAW_DATA!G78) -> -2394
A35: Discontinued investing cash flow | B35: =IF(RAW_DATA!B79="","",RAW_DATA!B79) -> 0 | C35: =IF(RAW_DATA!C79="","",RAW_DATA!C79) -> 0 | D35: =IF(RAW_DATA!D79="","",RAW_DATA!D79) -> 0 | E35: =IF(RAW_DATA!E79="","",RAW_DATA!E79) -> -883 | F35: =IF(RAW_DATA!F79="","",RAW_DATA!F79) -> -202 | G35: =IF(RAW_DATA!G79="","",RAW_DATA!G79) -> -724
A36: Total investing cash flow | B36: =IF(RAW_DATA!B80="","",RAW_DATA!B80) -> -3246 | C36: =IF(RAW_DATA!C80="","",RAW_DATA!C80) -> 2453 | D36: =IF(RAW_DATA!D80="","",RAW_DATA!D80) -> -2294 | E36: =IF(RAW_DATA!E80="","",RAW_DATA!E80) -> -2294 | F36: =IF(RAW_DATA!F80="","",RAW_DATA!F80) -> -625 | G36: =IF(RAW_DATA!G80="","",RAW_DATA!G80) -> -3118 | H36: Total is used in the cash bridge; continuing ≠ total.
A38: C. Financing cash flow
A39: Dividends | B39: =IF(RAW_DATA!B82="","",RAW_DATA!B82) -> -4483 | C39: =IF(RAW_DATA!C82="","",RAW_DATA!C82) -> -4329 | D39: =IF(RAW_DATA!D82="","",RAW_DATA!D82) -> -4363 | E39: =IF(RAW_DATA!E82="","",RAW_DATA!E82) -> -4363 | F39: =IF(RAW_DATA!F82="","",RAW_DATA!F82) -> -4319 | G39: =IF(RAW_DATA!G82="","",RAW_DATA!G82) -> -4453
A40: Interest paid | B40: =IF(RAW_DATA!B83="","",RAW_DATA!B83) -> -488 | C40: =IF(RAW_DATA!C83="","",RAW_DATA!C83) -> -744 | D40: =IF(RAW_DATA!D83="","",RAW_DATA!D83) -> -899 | E40: =IF(RAW_DATA!E83="","",RAW_DATA!E83) -> -751 | F40: =IF(RAW_DATA!F83="","",RAW_DATA!F83) -> -929 | G40: =IF(RAW_DATA!G83="","",RAW_DATA!G83) -> -1018
A41: Short-term borrowing movement | B41: =IF(RAW_DATA!B84="","",RAW_DATA!B84) | C41: =IF(RAW_DATA!C84="","",RAW_DATA!C84) | D41: =IF(RAW_DATA!D84="","",RAW_DATA!D84) | E41: =IF(RAW_DATA!E84="","",RAW_DATA!E84) | F41: =IF(RAW_DATA!F84="","",RAW_DATA!F84) -> 575 | G41: =IF(RAW_DATA!G84="","",RAW_DATA!G84) -> -2228
A42: Additional financial liabilities | B42: =IF(RAW_DATA!B85="","",RAW_DATA!B85) | C42: =IF(RAW_DATA!C85="","",RAW_DATA!C85) | D42: =IF(RAW_DATA!D85="","",RAW_DATA!D85) | E42: =IF(RAW_DATA!E85="","",RAW_DATA!E85) | F42: =IF(RAW_DATA!F85="","",RAW_DATA!F85) -> 4234 | G42: =IF(RAW_DATA!G85="","",RAW_DATA!G85) -> 4278
A43: Repayment of financial liabilities | B43: =IF(RAW_DATA!B86="","",RAW_DATA!B86) | C43: =IF(RAW_DATA!C86="","",RAW_DATA!C86) | D43: =IF(RAW_DATA!D86="","",RAW_DATA!D86) | E43: =IF(RAW_DATA!E86="","",RAW_DATA!E86) | F43: =IF(RAW_DATA!F86="","",RAW_DATA!F86) -> -3846 | G43: =IF(RAW_DATA!G86="","",RAW_DATA!G86) -> -3547
A44: Lease principal payments | B44: =IF(RAW_DATA!B87="","",RAW_DATA!B87) | C44: =IF(RAW_DATA!C87="","",RAW_DATA!C87) | D44: =IF(RAW_DATA!D87="","",RAW_DATA!D87) | E44: =IF(RAW_DATA!E87="","",RAW_DATA!E87) | F44: =IF(RAW_DATA!F87="","",RAW_DATA!F87) -> -342 | G44: =IF(RAW_DATA!G87="","",RAW_DATA!G87) -> -301
A45: Share repurchases | B45: =IF(RAW_DATA!B88="","",RAW_DATA!B88) -> -3018 | C45: =IF(RAW_DATA!C88="","",RAW_DATA!C88) -> -1509 | D45: =IF(RAW_DATA!D88="","",RAW_DATA!D88) -> -1507 | E45: =IF(RAW_DATA!E88="","",RAW_DATA!E88) | F45: =IF(RAW_DATA!F88="","",RAW_DATA!F88) -> -1508 | G45: =IF(RAW_DATA!G88="","",RAW_DATA!G88) -> -1510
A46: Other financing activities | B46: =IF(RAW_DATA!B89="","",RAW_DATA!B89) | C46: =IF(RAW_DATA!C89="","",RAW_DATA!C89) | D46: =IF(RAW_DATA!D89="","",RAW_DATA!D89) | E46: =IF(RAW_DATA!E89="","",RAW_DATA!E89) | F46: =IF(RAW_DATA!F89="","",RAW_DATA!F89) -> -694 | G46: =IF(RAW_DATA!G89="","",RAW_DATA!G89) -> -1105
A47: Memo: sum of financing lines | B47: =IFERROR(B39+B40+B41+B42+B43+B44+B45+B46,"") | C47: =IFERROR(C39+C40+C41+C42+C43+C44+C45+C46,"") | D47: =IFERROR(D39+D40+D41+D42+D43+D44+D45+D46,"") | E47: =IFERROR(E39+E40+E41+E42+E43+E44+E45+E46,"") | F47: =IFERROR(F39+F40+F41+F42+F43+F44+F45+F46,"") -> -6829 | G47: =IFERROR(G39+G40+G41+G42+G43+G44+G45+G46,"") -> -9884 | H47: Should equal continuing financing cash flow (S9).
A48: Continuing financing cash flow | B48: =IF(RAW_DATA!B90="","",RAW_DATA!B90) -> -7099 | C48: =IF(RAW_DATA!C90="","",RAW_DATA!C90) -> -8890 | D48: =IF(RAW_DATA!D90="","",RAW_DATA!D90) -> -7193 | E48: =IF(RAW_DATA!E90="","",RAW_DATA!E90) -> -7084 | F48: =IF(RAW_DATA!F90="","",RAW_DATA!F90) -> -6829 | G48: =IF(RAW_DATA!G90="","",RAW_DATA!G90) -> -9884
A49: Discontinued financing cash flow | B49: =IF(RAW_DATA!B91="","",RAW_DATA!B91) -> 0 | C49: =IF(RAW_DATA!C91="","",RAW_DATA!C91) -> 0 | D49: =IF(RAW_DATA!D91="","",RAW_DATA!D91) -> 0 | E49: =IF(RAW_DATA!E91="","",RAW_DATA!E91) -> -109 | F49: =IF(RAW_DATA!F91="","",RAW_DATA!F91) -> -112 | G49: =IF(RAW_DATA!G91="","",RAW_DATA!G91) -> 3070
A50: Total financing cash flow | B50: =IF(RAW_DATA!B92="","",RAW_DATA!B92) -> -7099 | C50: =IF(RAW_DATA!C92="","",RAW_DATA!C92) -> -8890 | D50: =IF(RAW_DATA!D92="","",RAW_DATA!D92) -> -7193 | E50: =IF(RAW_DATA!E92="","",RAW_DATA!E92) -> -7193 | F50: =IF(RAW_DATA!F92="","",RAW_DATA!F92) -> -6941 | G50: =IF(RAW_DATA!G92="","",RAW_DATA!G92) -> -6814 | H50: Total is used in the cash bridge. Do not substitute the continuing figure (e.g. 2025 continuing −9,884 vs total −6,814 per brief).
A52: D. Free cash flow (Unilever definition)
A53: Operating cash flow | B53: =B19 -> 10305 | C53: =C19 -> 10089 | D53: =D19 -> 11561 | E53: =E19 -> 10326 | F53: =F19 -> 10913 | G53: =G19 -> 10772
A54: Less: income tax paid | B54: =B20 -> -2333 | C54: =C20 -> -2807 | D54: =D20 -> -2135 | E54: =E20 -> -1933 | F54: =F20 -> -2452 | G54: =G20 -> -2720
A55: Less: net capital expenditure | B55: =B27 -> -1239 | C55: =C27 -> -1627 | D55: =D27 -> -1703 | E55: =E27 -> -1420 | F55: =F27 -> -1599 | G55: =G27 -> -1465
A56: Less: net interest payments | B56: =IF(RAW_DATA!B65="","",RAW_DATA!B65) -> -340 | C56: =IF(RAW_DATA!C65="","",RAW_DATA!C65) -> -457 | D56: =IF(RAW_DATA!D65="","",RAW_DATA!D65) -> -632 | E56: =IF(RAW_DATA!E65="","",RAW_DATA!E65) -> -528 | F56: =IF(RAW_DATA!F65="","",RAW_DATA!F65) -> -559 | G56: =IF(RAW_DATA!G65="","",RAW_DATA!G65) -> -666
A57: Calculated FCF | B57: =IFERROR(B53+B54+B55+B56,"") -> 6393 | C57: =IFERROR(C53+C54+C55+C56,"") -> 5198 | D57: =IFERROR(D53+D54+D55+D56,"") -> 7091 | E57: =IFERROR(E53+E54+E55+E56,"") -> 6445 | F57: =IFERROR(F53+F54+F55+F56,"") -> 6303 | G57: =IFERROR(G53+G54+G55+G56,"") -> 5921
A58: Reported FCF | B58: =IF(RAW_DATA!B66="","",RAW_DATA!B66) -> 6393 | C58: =IF(RAW_DATA!C66="","",RAW_DATA!C66) -> 5198 | D58: =IF(RAW_DATA!D66="","",RAW_DATA!D66) -> 7091 | E58: =IF(RAW_DATA!E66="","",RAW_DATA!E66) -> 6445 | F58: =IF(RAW_DATA!F66="","",RAW_DATA!F66) -> 6304 | G58: =IF(RAW_DATA!G66="","",RAW_DATA!G66) -> 5921
A59: Difference | B59: =IFERROR(B57-B58,"") -> 0 | C59: =IFERROR(C57-C58,"") -> 0 | D59: =IFERROR(D57-D58,"") -> 0 | E59: =IFERROR(E57-E58,"") -> 0 | F59: =IFERROR(F57-F58,"") -> -1 | G59: =IFERROR(G57-G58,"") -> 0 | H59: €1m differences are rounding in the reported figures.
A61: E. Cash bridge (cash-flow-statement cash)
A62: Opening cash | B62: =IF(RAW_DATA!B94="","",RAW_DATA!B94) -> 5475 | C62: =IF(RAW_DATA!C94="","",RAW_DATA!C94) -> 3387 | D62: =IF(RAW_DATA!D94="","",RAW_DATA!D94) -> 4225 | E62: =IF(RAW_DATA!E94="","",RAW_DATA!E94) -> 4225 | F62: =IF(RAW_DATA!F94="","",RAW_DATA!F94) -> 4045 | G62: =IF(RAW_DATA!G94="","",RAW_DATA!G94) -> 5950
A63: + Operating cash flow (net, after tax, total) | B63: =B24 -> 7972 | C63: =C24 -> 7282 | D63: =D24 -> 9426 | E63: =E24 -> 9426 | F63: =F24 -> 9519 | G63: =G24 -> 8350
A64: + Investing cash flow (total) | B64: =B36 -> -3246 | C64: =C36 -> 2453 | D64: =D36 -> -2294 | E64: =E36 -> -2294 | F64: =F36 -> -625 | G64: =G36 -> -3118
A65: + Financing cash flow (total) | B65: =B50 -> -7099 | C65: =C50 -> -8890 | D65: =D50 -> -7193 | E65: =E50 -> -7193 | F65: =F50 -> -6941 | G65: =G50 -> -6814
A66: + FX effect | B66: =IF(RAW_DATA!B96="","",RAW_DATA!B96) -> 285 | C66: =IF(RAW_DATA!C96="","",RAW_DATA!C96) -> -7 | D66: =IF(RAW_DATA!D96="","",RAW_DATA!D96) -> -119 | E66: =IF(RAW_DATA!E96="","",RAW_DATA!E96) -> -119 | F66: =IF(RAW_DATA!F96="","",RAW_DATA!F96) -> -48 | G66: =IF(RAW_DATA!G96="","",RAW_DATA!G96) -> -498
A67: Calculated closing cash | B67: =IFERROR(B62+B63+B64+B65+B66,"") -> 3387 | C67: =IFERROR(C62+C63+C64+C65+C66,"") -> 4225 | D67: =IFERROR(D62+D63+D64+D65+D66,"") -> 4045 | E67: =IFERROR(E62+E63+E64+E65+E66,"") -> 4045 | F67: =IFERROR(F62+F63+F64+F65+F66,"") -> 5950 | G67: =IFERROR(G62+G63+G64+G65+G66,"") -> 3870
A68: Reported closing cash (cash-flow statement) | B68: =IF(RAW_DATA!B97="","",RAW_DATA!B97) -> 3387 | C68: =IF(RAW_DATA!C97="","",RAW_DATA!C97) -> 4225 | D68: =IF(RAW_DATA!D97="","",RAW_DATA!D97) -> 4045 | E68: =IF(RAW_DATA!E97="","",RAW_DATA!E97) -> 4045 | F68: =IF(RAW_DATA!F97="","",RAW_DATA!F97) -> 5950 | G68: =IF(RAW_DATA!G97="","",RAW_DATA!G97) -> 3870 | H68: Cash-flow-statement cash, not balance-sheet cash (2025: 3,870 vs 3,941).
A69: Cash bridge error | B69: =IFERROR(B67-B68,"") -> 0 | C69: =IFERROR(C67-C68,"") -> 0 | D69: =IFERROR(D67-D68,"") -> 0 | E69: =IFERROR(E67-E68,"") -> 0 | F69: =IFERROR(F67-F68,"") -> 0 | G69: =IFERROR(G67-G68,"") -> 0
A71: F. Historical cash metrics
A72: OCF conversion (operating CF ÷ operating profit) | B72: =IFERROR(B19/HISTORICAL_IS!B8,"") -> 1.1842105 | C72: =IFERROR(C19/HISTORICAL_IS!C8,"") -> 0.93807531 | D72: =IFERROR(D19/HISTORICAL_IS!D8,"") -> 1.1847715 | E72: =IFERROR(E19/HISTORICAL_IS!E8,"") -> 1.1475884 | F72: =IFERROR(F19/HISTORICAL_IS!F8,"") -> 1.2360403 | G72: =IFERROR(G19/HISTORICAL_IS!G8,"") -> 1.1919885 | H72: Operating CF is before tax.
A73: Simple FCF conversion (FCF ÷ net profit) | B73: =IFERROR(B57/HISTORICAL_IS!B15,"") -> 0.96556411 | C73: =IFERROR(C57/HISTORICAL_IS!C15,"") -> 0.62861289 | D73: =IFERROR(D57/HISTORICAL_IS!D15,"") -> 0.99313725 | E73: =IFERROR(E57/HISTORICAL_IS!E15,"") -> 0.97107127 | F73: =IFERROR(F57/HISTORICAL_IS!F15,"") -> 1.0437158 | G73: =IFERROR(G57/HISTORICAL_IS!G15,"") -> 0.95300177 | H73: Not Unilever's reported cash-conversion KPI, which excludes certain disposal/JV/associate effects.
A74: Capex intensity (|net capex| ÷ revenue) | B74: =IFERROR(ABS(B27)/HISTORICAL_IS!B6,"") -> 0.0236252 | C74: =IFERROR(ABS(C27)/HISTORICAL_IS!C6,"") -> 0.027083715 | D74: =IFERROR(ABS(D27)/HISTORICAL_IS!D6,"") -> 0.028571908 | E74: =IFERROR(ABS(E27)/HISTORICAL_IS!E6,"") -> 0.02747678 | F74: =IFERROR(ABS(F27)/HISTORICAL_IS!F6,"") -> 0.030469331 | G74: =IFERROR(ABS(G27)/HISTORICAL_IS!G6,"") -> 0.029008178
A75: Dividend coverage (FCF ÷ dividends) | B75: =IFERROR(B57/ABS(B39),"") -> 1.426054 | C75: =IFERROR(C57/ABS(C39),"") -> 1.2007392 | D75: =IFERROR(D57/ABS(D39),"") -> 1.6252579 | E75: =IFERROR(E57/ABS(E39),"") -> 1.4771946 | F75: =IFERROR(F57/ABS(F39),"") -> 1.4593656 | G75: =IFERROR(G57/ABS(G39),"") -> 1.3296654
A76: Distribution ratio ((dividends + buybacks) ÷ FCF) | B76: =IFERROR((ABS(B39)+ABS(B45))/B57,"") -> 1.1733146 | C76: =IFERROR((ABS(C39)+ABS(C45))/C57,"") -> 1.1231243 | D76: =IFERROR((ABS(D39)+ABS(D45))/D57,"") -> 0.8278099 | E76: =IFERROR((ABS(E39)+ABS(E45))/E57,"") | F76: =IFERROR((ABS(F39)+ABS(F45))/F57,"") -> 0.92448041 | G76: =IFERROR((ABS(G39)+ABS(G45))/G57,"") -> 1.0070934 | H76: Above 100% = distributions exceeded FCF.

Sheet WORKING_CAPITAL
A1: 06 WORKING_CAPITAL — BASIC MOVEMENTS ONLY (Step 3 builds DSO/DIO/DPO/CCC)
A2: € million. Movements compare year-end balances: 2022 vs 2021, 2023 vs 2022, 2024 vs 2023, 2025 vs 2024. 2021 needs 2020 balances (not in source).
A4: €m | B4: 2021 | C4: 2022 | D4: 2023 Original | E4: 2023 Continuing | F4: 2024 | G4: 2025 | H4: Notes
A5: Balances (from HISTORICAL_BS)
A6: Inventories | B6: =HISTORICAL_BS!B6 -> 4683 | C6: =HISTORICAL_BS!C6 -> 5931 | D6: =HISTORICAL_BS!D6 -> 5119 | F6: =HISTORICAL_BS!F6 -> 5177 | G6: =HISTORICAL_BS!G6 -> 4043
A7: Trade receivables | B7: =HISTORICAL_BS!B7 -> 3582 | C7: =HISTORICAL_BS!C7 -> 4544 | D7: =HISTORICAL_BS!D7 -> 4023 | F7: =HISTORICAL_BS!F7 -> 4227 | G7: =HISTORICAL_BS!G7 -> 4852
A8: Trade payables | B8: =HISTORICAL_BS!B26 -> 8896 | C8: =HISTORICAL_BS!C26 -> 11100 | D8: =HISTORICAL_BS!D26 -> 10355 | F8: =HISTORICAL_BS!F26 -> 10258 | G8: =HISTORICAL_BS!G26 -> 10994
A10: Movements
A11: Δ Inventory | C11: =IFERROR(C6-B6,"") -> 1248 | D11: =IFERROR(D6-C6,"") -> -812 | F11: =IFERROR(F6-D6,"") -> 58 | G11: =IFERROR(G6-F6,"") -> -1134
A12: Δ Receivables (trade) | C12: =IFERROR(C7-B7,"") -> 962 | D12: =IFERROR(D7-C7,"") -> -521 | F12: =IFERROR(F7-D7,"") -> 204 | G12: =IFERROR(G7-F7,"") -> 625
A13: Δ Payables (trade) | C13: =IFERROR(C8-B8,"") -> 2204 | D13: =IFERROR(D8-C8,"") -> -745 | F13: =IFERROR(F8-D8,"") -> -97 | G13: =IFERROR(G8-F8,"") -> 736
A15: Cash impact (sign convention: positive = cash released)
A16: Inventory cash impact (−Δ inventory) | C16: =IFERROR(-C11,"") -> -1248 | D16: =IFERROR(-D11,"") -> 812 | F16: =IFERROR(-F11,"") -> -58 | G16: =IFERROR(-G11,"") -> 1134
A17: Receivables cash impact (−Δ receivables) | C17: =IFERROR(-C12,"") -> -962 | D17: =IFERROR(-D12,"") -> 521 | F17: =IFERROR(-F12,"") -> -204 | G17: =IFERROR(-G12,"") -> -625
A18: Payables cash impact (+Δ payables) | C18: =IFERROR(C13,"") -> 2204 | D18: =IFERROR(D13,"") -> -745 | F18: =IFERROR(F13,"") -> -97 | G18: =IFERROR(G13,"") -> 736
A19: Simplified working-capital cash impact | C19: =IFERROR(C16+C17+C18,"") -> -6 | D19: =IFERROR(D16+D17+D18,"") -> 588 | F19: =IFERROR(F16+F17+F18,"") -> -359 | G19: =IFERROR(G16+G17+G18,"") -> 1245
A20: Memo: change in working capital per cash-flow statement | B20: =HISTORICAL_CF!B12 | C20: =HISTORICAL_CF!C12 | D20: =HISTORICAL_CF!D12 | E20: =HISTORICAL_CF!E12 -> 753 | F20: =HISTORICAL_CF!F12 -> -188 | G20: =HISTORICAL_CF!G12 -> 116 | H20: Reported cash effect (continuing), available 2023 Continuing–2025. Differs from the simplified balance-sheet impact above — see notes.
A22: Interpretation notes
A23: • Balance-sheet movements are not cash flows: they include FX translation, acquisitions/disposals and reclassifications. The cash-flow statement figure is the reported cash effect.
A24: • 2025 vs 2024: the Ice Cream demerger completed in December 2025, so 2025 year-end balances exclude Ice Cream while 2024 balances were reported before it. Part of the 2025 movement is a demerger effect, not trading cash.
A25: • Only trade receivables and trade payables are used here, as specified. Other receivables, accruals and other operating liabilities are on HISTORICAL_BS.
A26: • DSO, DIO, DPO, CCC, cash-release calculations and sensitivities belong to Step 3.

Sheet HISTORICAL_CHECKS
A1: 07 HISTORICAL_CHECKS — RECONCILIATIONS AND AUTOMATIC STATUS FLAGS
A2: Every status is a formula. N/A = at least one input for that period is Unavailable in the source. Differences in € million.
A3: Tolerance (€m) | B3: 1 | C3: Reported figures are rounded to €1m, so a €1m difference is rounding (e.g. 2025 PBT 8,693 − tax 2,481 = 6,212 vs reported 6,213). A 0.1 tolerance would flag rounding as ERROR.
A5: Summary
A6: Core checks with status PASS | B6: =(H14="PASS")*1+(H16="PASS")*1+(H18="PASS")*1+(H20="PASS")*1+(H22="PASS")*1+(H24="PASS")*1 -> 6
A7: Core checks with status ERROR | B7: =(H14="ERROR")*1+(H16="ERROR")*1+(H18="ERROR")*1+(H20="ERROR")*1+(H22="ERROR")*1+(H24="ERROR")*1 -> 0
A8: Core checks fully N/A (not yet testable — source data missing) | B8: =(H14="N/A")*1+(H16="N/A")*1+(H18="N/A")*1+(H20="N/A")*1+(H22="N/A")*1+(H24="N/A")*1 -> 0
A9: Period-level ERROR flags (core + supplementary) | B9: =COUNTIF(B15:G15,"ERROR")+COUNTIF(B17:G17,"ERROR")+COUNTIF(B19:G19,"ERROR")+COUNTIF(B21:G21,"ERROR")+COUNTIF(B23:G23,"ERROR")+COUNTIF(B25:G25,"ERROR")+COUNTIF(B30:G30,"ERROR")+COUNTIF(B32:G32,"ERROR")+COUNTIF(B34:G34,"ERROR")+COUNTIF(B36:G36,"ERROR")+COUNTIF(B38:G38,"ERROR")+COUNTIF(B40:G40,"ERROR")+COUNTIF(B42:G42,"ERROR")+COUNTIF(B44:G44,"ERROR")+COUNTIF(B46:G46,"ERROR") -> 0
A10: STEP 2 STATUS | B10: =IF(B7+B9>0,"NOT COMPLETE — resolve ERROR flags",IF(B8>0,"BUILT — "&B8&" of 6 core checks awaiting source data","COMPLETE — all core checks PASS")) -> COMPLETE — all core checks PASS
A12: Core checks (Step 2 specification)
A13: Check | B13: 2021 | C13: 2022 | D13: 2023 Original | E13: 2023 Continuing | F13: 2024 | G13: 2025 | H13: Status | I13: Periods tested | J13: What it tests / why N/A
A14: Check 1 — PBT: operating profit − net finance costs + hyperinflation + JV/associate share + other income − PBT | B14: =IF(COUNT(HISTORICAL_IS!B8,HISTORICAL_IS!B9,HISTORICAL_IS!B10,HISTORICAL_IS!B11,HISTORICAL_IS!B12,HISTORICAL_IS!B13)<6,"N/A",HISTORICAL_IS!B8-HISTORICAL_IS!B9+HISTORICAL_IS!B10+HISTORICAL_IS!B11+HISTORICAL_IS!B12-HISTORICAL_IS!B13) -> 0 | C14: =IF(COUNT(HISTORICAL_IS!C8,HISTORICAL_IS!C9,HISTORICAL_IS!C10,HISTORICAL_IS!C11,HISTORICAL_IS!C12,HISTORICAL_IS!C13)<6,"N/A",HISTORICAL_IS!C8-HISTORICAL_IS!C9+HISTORICAL_IS!C10+HISTORICAL_IS!C11+HISTORICAL_IS!C12-HISTORICAL_IS!C13) -> 0 | D14: =IF(COUNT(HISTORICAL_IS!D8,HISTORICAL_IS!D9,HISTORICAL_IS!D10,HISTORICAL_IS!D11,HISTORICAL_IS!D12,HISTORICAL_IS!D13)<6,"N/A",HISTORICAL_IS!D8-HISTORICAL_IS!D9+HISTORICAL_IS!D10+HISTORICAL_IS!D11+HISTORICAL_IS!D12-HISTORICAL_IS!D13) -> 0 | E14: =IF(COUNT(HISTORICAL_IS!E8,HISTORICAL_IS!E9,HISTORICAL_IS!E10,HISTORICAL_IS!E11,HISTORICAL_IS!E12,HISTORICAL_IS!E13)<6,"N/A",HISTORICAL_IS!E8-HISTORICAL_IS!E9+HISTORICAL_IS!E10+HISTORICAL_IS!E11+HISTORICAL_IS!E12-HISTORICAL_IS!E13) -> 0 | F14: =IF(COUNT(HISTORICAL_IS!F8,HISTORICAL_IS!F9,HISTORICAL_IS!F10,HISTORICAL_IS!F11,HISTORICAL_IS!F12,HISTORICAL_IS!F13)<6,"N/A",HISTORICAL_IS!F8-HISTORICAL_IS!F9+HISTORICAL_IS!F10+HISTORICAL_IS!F11+HISTORICAL_IS!F12-HISTORICAL_IS!F13) -> 0 | G14: =IF(COUNT(HISTORICAL_IS!G8,HISTORICAL_IS!G9,HISTORICAL_IS!G10,HISTORICAL_IS!G11,HISTORICAL_IS!G12,HISTORICAL_IS!G13)<6,"N/A",HISTORICAL_IS!G8-HISTORICAL_IS!G9+HISTORICAL_IS!G10+HISTORICAL_IS!G11+HISTORICAL_IS!G12-HISTORICAL_IS!G13) -> 1 | H14: =IF(COUNTIF(B15:G15,"ERROR")>0,"ERROR",IF(COUNTIF(B15:G15,"PASS")>0,"PASS","N/A")) -> PASS | I14: =COUNTIF(B15:G15,"PASS")+COUNTIF(B15:G15,"ERROR")&" of 6" -> 6 of 6 | J14: Unilever's reported structure between operating profit and PBT (all five lines).
A15: status | B15: =IF(B14="N/A","N/A",IF(ABS(B14)<=$B$3,"PASS","ERROR")) -> PASS | C15: =IF(C14="N/A","N/A",IF(ABS(C14)<=$B$3,"PASS","ERROR")) -> PASS | D15: =IF(D14="N/A","N/A",IF(ABS(D14)<=$B$3,"PASS","ERROR")) -> PASS | E15: =IF(E14="N/A","N/A",IF(ABS(E14)<=$B$3,"PASS","ERROR")) -> PASS | F15: =IF(F14="N/A","N/A",IF(ABS(F14)<=$B$3,"PASS","ERROR")) -> PASS | G15: =IF(G14="N/A","N/A",IF(ABS(G14)<=$B$3,"PASS","ERROR")) -> PASS
A16: Check 2 — Net income: PBT − tax − net profit | B16: =IF(COUNT(HISTORICAL_IS!B13,HISTORICAL_IS!B14,HISTORICAL_IS!B15)<3,"N/A",HISTORICAL_IS!B13-HISTORICAL_IS!B14-HISTORICAL_IS!B15) -> 0 | C16: =IF(COUNT(HISTORICAL_IS!C13,HISTORICAL_IS!C14,HISTORICAL_IS!C15)<3,"N/A",HISTORICAL_IS!C13-HISTORICAL_IS!C14-HISTORICAL_IS!C15) -> 0 | D16: =IF(COUNT(HISTORICAL_IS!D13,HISTORICAL_IS!D14,HISTORICAL_IS!D15)<3,"N/A",HISTORICAL_IS!D13-HISTORICAL_IS!D14-HISTORICAL_IS!D15) -> 0 | E16: =IF(COUNT(HISTORICAL_IS!E13,HISTORICAL_IS!E14,HISTORICAL_IS!E15)<3,"N/A",HISTORICAL_IS!E13-HISTORICAL_IS!E14-HISTORICAL_IS!E15) -> 0 | F16: =IF(COUNT(HISTORICAL_IS!F13,HISTORICAL_IS!F14,HISTORICAL_IS!F15)<3,"N/A",HISTORICAL_IS!F13-HISTORICAL_IS!F14-HISTORICAL_IS!F15) -> 0 | G16: =IF(COUNT(HISTORICAL_IS!G13,HISTORICAL_IS!G14,HISTORICAL_IS!G15)<3,"N/A",HISTORICAL_IS!G13-HISTORICAL_IS!G14-HISTORICAL_IS!G15) -> -1 | H16: =IF(COUNTIF(B17:G17,"ERROR")>0,"ERROR",IF(COUNTIF(B17:G17,"PASS")>0,"PASS","N/A")) -> PASS | I16: =COUNTIF(B17:G17,"PASS")+COUNTIF(B17:G17,"ERROR")&" of 6" -> 6 of 6
A17: status | B17: =IF(B16="N/A","N/A",IF(ABS(B16)<=$B$3,"PASS","ERROR")) -> PASS | C17: =IF(C16="N/A","N/A",IF(ABS(C16)<=$B$3,"PASS","ERROR")) -> PASS | D17: =IF(D16="N/A","N/A",IF(ABS(D16)<=$B$3,"PASS","ERROR")) -> PASS | E17: =IF(E16="N/A","N/A",IF(ABS(E16)<=$B$3,"PASS","ERROR")) -> PASS | F17: =IF(F16="N/A","N/A",IF(ABS(F16)<=$B$3,"PASS","ERROR")) -> PASS | G17: =IF(G16="N/A","N/A",IF(ABS(G16)<=$B$3,"PASS","ERROR")) -> PASS
A18: Check 3 — Financial liabilities: current + non-current − reported total | B18: =IF(COUNT(HISTORICAL_BS!B49,HISTORICAL_BS!B50)<2,"N/A",HISTORICAL_BS!B49-HISTORICAL_BS!B50) -> 0 | C18: =IF(COUNT(HISTORICAL_BS!C49,HISTORICAL_BS!C50)<2,"N/A",HISTORICAL_BS!C49-HISTORICAL_BS!C50) -> 0 | D18: =IF(COUNT(HISTORICAL_BS!D49,HISTORICAL_BS!D50)<2,"N/A",HISTORICAL_BS!D49-HISTORICAL_BS!D50) -> 0 | F18: =IF(COUNT(HISTORICAL_BS!F49,HISTORICAL_BS!F50)<2,"N/A",HISTORICAL_BS!F49-HISTORICAL_BS!F50) -> 0 | G18: =IF(COUNT(HISTORICAL_BS!G49,HISTORICAL_BS!G50)<2,"N/A",HISTORICAL_BS!G49-HISTORICAL_BS!G50) -> 0 | H18: =IF(COUNTIF(B19:G19,"ERROR")>0,"ERROR",IF(COUNTIF(B19:G19,"PASS")>0,"PASS","N/A")) -> PASS | I18: =COUNTIF(B19:G19,"PASS")+COUNTIF(B19:G19,"ERROR")&" of 5" -> 5 of 5
A19: status | B19: =IF(B18="N/A","N/A",IF(ABS(B18)<=$B$3,"PASS","ERROR")) -> PASS | C19: =IF(C18="N/A","N/A",IF(ABS(C18)<=$B$3,"PASS","ERROR")) -> PASS | D19: =IF(D18="N/A","N/A",IF(ABS(D18)<=$B$3,"PASS","ERROR")) -> PASS | F19: =IF(F18="N/A","N/A",IF(ABS(F18)<=$B$3,"PASS","ERROR")) -> PASS | G19: =IF(G18="N/A","N/A",IF(ABS(G18)<=$B$3,"PASS","ERROR")) -> PASS
A20: Check 4 — FCF: calculated − reported | B20: =IF(COUNT(HISTORICAL_CF!B57,HISTORICAL_CF!B58)<2,"N/A",HISTORICAL_CF!B57-HISTORICAL_CF!B58) -> 0 | C20: =IF(COUNT(HISTORICAL_CF!C57,HISTORICAL_CF!C58)<2,"N/A",HISTORICAL_CF!C57-HISTORICAL_CF!C58) -> 0 | D20: =IF(COUNT(HISTORICAL_CF!D57,HISTORICAL_CF!D58)<2,"N/A",HISTORICAL_CF!D57-HISTORICAL_CF!D58) -> 0 | E20: =IF(COUNT(HISTORICAL_CF!E57,HISTORICAL_CF!E58)<2,"N/A",HISTORICAL_CF!E57-HISTORICAL_CF!E58) -> 0 | F20: =IF(COUNT(HISTORICAL_CF!F57,HISTORICAL_CF!F58)<2,"N/A",HISTORICAL_CF!F57-HISTORICAL_CF!F58) -> -1 | G20: =IF(COUNT(HISTORICAL_CF!G57,HISTORICAL_CF!G58)<2,"N/A",HISTORICAL_CF!G57-HISTORICAL_CF!G58) -> 0 | H20: =IF(COUNTIF(B21:G21,"ERROR")>0,"ERROR",IF(COUNTIF(B21:G21,"PASS")>0,"PASS","N/A")) -> PASS | I20: =COUNTIF(B21:G21,"PASS")+COUNTIF(B21:G21,"ERROR")&" of 6" -> 6 of 6
A21: status | B21: =IF(B20="N/A","N/A",IF(ABS(B20)<=$B$3,"PASS","ERROR")) -> PASS | C21: =IF(C20="N/A","N/A",IF(ABS(C20)<=$B$3,"PASS","ERROR")) -> PASS | D21: =IF(D20="N/A","N/A",IF(ABS(D20)<=$B$3,"PASS","ERROR")) -> PASS | E21: =IF(E20="N/A","N/A",IF(ABS(E20)<=$B$3,"PASS","ERROR")) -> PASS | F21: =IF(F20="N/A","N/A",IF(ABS(F20)<=$B$3,"PASS","ERROR")) -> PASS | G21: =IF(G20="N/A","N/A",IF(ABS(G20)<=$B$3,"PASS","ERROR")) -> PASS
A22: Check 5 — Net debt: model − reported | B22: =IF(COUNT(HISTORICAL_BS!B59,HISTORICAL_BS!B60)<2,"N/A",HISTORICAL_BS!B59-HISTORICAL_BS!B60) -> 0 | C22: =IF(COUNT(HISTORICAL_BS!C59,HISTORICAL_BS!C60)<2,"N/A",HISTORICAL_BS!C59-HISTORICAL_BS!C60) -> 0 | D22: =IF(COUNT(HISTORICAL_BS!D59,HISTORICAL_BS!D60)<2,"N/A",HISTORICAL_BS!D59-HISTORICAL_BS!D60) -> 0 | F22: =IF(COUNT(HISTORICAL_BS!F59,HISTORICAL_BS!F60)<2,"N/A",HISTORICAL_BS!F59-HISTORICAL_BS!F60) -> 0 | G22: =IF(COUNT(HISTORICAL_BS!G59,HISTORICAL_BS!G60)<2,"N/A",HISTORICAL_BS!G59-HISTORICAL_BS!G60) -> 0 | H22: =IF(COUNTIF(B23:G23,"ERROR")>0,"ERROR",IF(COUNTIF(B23:G23,"PASS")>0,"PASS","N/A")) -> PASS | I22: =COUNTIF(B23:G23,"PASS")+COUNTIF(B23:G23,"ERROR")&" of 5" -> 5 of 5 | J22: Total financial liabilities − BS cash − other current financial assets − non-current derivative assets.
A23: status | B23: =IF(B22="N/A","N/A",IF(ABS(B22)<=$B$3,"PASS","ERROR")) -> PASS | C23: =IF(C22="N/A","N/A",IF(ABS(C22)<=$B$3,"PASS","ERROR")) -> PASS | D23: =IF(D22="N/A","N/A",IF(ABS(D22)<=$B$3,"PASS","ERROR")) -> PASS | F23: =IF(F22="N/A","N/A",IF(ABS(F22)<=$B$3,"PASS","ERROR")) -> PASS | G23: =IF(G22="N/A","N/A",IF(ABS(G22)<=$B$3,"PASS","ERROR")) -> PASS
A24: Check 6 — Cash bridge: opening + operating + investing + financing + FX − closing | B24: =IF(COUNT(HISTORICAL_CF!B67,HISTORICAL_CF!B68)<2,"N/A",HISTORICAL_CF!B67-HISTORICAL_CF!B68) -> 0 | C24: =IF(COUNT(HISTORICAL_CF!C67,HISTORICAL_CF!C68)<2,"N/A",HISTORICAL_CF!C67-HISTORICAL_CF!C68) -> 0 | D24: =IF(COUNT(HISTORICAL_CF!D67,HISTORICAL_CF!D68)<2,"N/A",HISTORICAL_CF!D67-HISTORICAL_CF!D68) -> 0 | E24: =IF(COUNT(HISTORICAL_CF!E67,HISTORICAL_CF!E68)<2,"N/A",HISTORICAL_CF!E67-HISTORICAL_CF!E68) -> 0 | F24: =IF(COUNT(HISTORICAL_CF!F67,HISTORICAL_CF!F68)<2,"N/A",HISTORICAL_CF!F67-HISTORICAL_CF!F68) -> 0 | G24: =IF(COUNT(HISTORICAL_CF!G67,HISTORICAL_CF!G68)<2,"N/A",HISTORICAL_CF!G67-HISTORICAL_CF!G68) -> 0 | H24: =IF(COUNTIF(B25:G25,"ERROR")>0,"ERROR",IF(COUNTIF(B25:G25,"PASS")>0,"PASS","N/A")) -> PASS | I24: =COUNTIF(B25:G25,"PASS")+COUNTIF(B25:G25,"ERROR")&" of 6" -> 6 of 6 | J24: Cash-flow-statement cash throughout; balance-sheet cash is never forced in.
A25: status | B25: =IF(B24="N/A","N/A",IF(ABS(B24)<=$B$3,"PASS","ERROR")) -> PASS | C25: =IF(C24="N/A","N/A",IF(ABS(C24)<=$B$3,"PASS","ERROR")) -> PASS | D25: =IF(D24="N/A","N/A",IF(ABS(D24)<=$B$3,"PASS","ERROR")) -> PASS | E25: =IF(E24="N/A","N/A",IF(ABS(E24)<=$B$3,"PASS","ERROR")) -> PASS | F25: =IF(F24="N/A","N/A",IF(ABS(F24)<=$B$3,"PASS","ERROR")) -> PASS | G25: =IF(G24="N/A","N/A",IF(ABS(G24)<=$B$3,"PASS","ERROR")) -> PASS
A27: Supplementary checks (not required by the spec; they locate problems when a core check fails)
A28: Check | B28: 2021 | C28: 2022 | D28: 2023 Original | E28: 2023 Continuing | F28: 2024 | G28: 2025 | H28: Status | I28: Periods tested | J28: What it tests / why N/A
A29: S1 — Cash definitions: CF cash + overdrafts + held-for-sale adjustment − balance-sheet cash | B29: =IF(COUNT(HISTORICAL_BS!B18,HISTORICAL_BS!B19,HISTORICAL_BS!B20,HISTORICAL_BS!B17)<4,"N/A",HISTORICAL_BS!B18+HISTORICAL_BS!B19+HISTORICAL_BS!B20-HISTORICAL_BS!B17) -> 0 | C29: =IF(COUNT(HISTORICAL_BS!C18,HISTORICAL_BS!C19,HISTORICAL_BS!C20,HISTORICAL_BS!C17)<4,"N/A",HISTORICAL_BS!C18+HISTORICAL_BS!C19+HISTORICAL_BS!C20-HISTORICAL_BS!C17) -> 0 | D29: =IF(COUNT(HISTORICAL_BS!D18,HISTORICAL_BS!D19,HISTORICAL_BS!D20,HISTORICAL_BS!D17)<4,"N/A",HISTORICAL_BS!D18+HISTORICAL_BS!D19+HISTORICAL_BS!D20-HISTORICAL_BS!D17) -> 0 | F29: =IF(COUNT(HISTORICAL_BS!F18,HISTORICAL_BS!F19,HISTORICAL_BS!F20,HISTORICAL_BS!F17)<4,"N/A",HISTORICAL_BS!F18+HISTORICAL_BS!F19+HISTORICAL_BS!F20-HISTORICAL_BS!F17) -> 0 | G29: =IF(COUNT(HISTORICAL_BS!G18,HISTORICAL_BS!G19,HISTORICAL_BS!G20,HISTORICAL_BS!G17)<4,"N/A",HISTORICAL_BS!G18+HISTORICAL_BS!G19+HISTORICAL_BS!G20-HISTORICAL_BS!G17) -> 0 | H29: =IF(COUNTIF(B30:G30,"ERROR")>0,"ERROR",IF(COUNTIF(B30:G30,"PASS")>0,"PASS","N/A")) -> PASS | I29: =COUNTIF(B30:G30,"PASS")+COUNTIF(B30:G30,"ERROR")&" of 5" -> 5 of 5 | J29: Held-for-sale adjustment carries the sign printed by Unilever (brackets = deduction).
A30: status | B30: =IF(B29="N/A","N/A",IF(ABS(B29)<=$B$3,"PASS","ERROR")) -> PASS | C30: =IF(C29="N/A","N/A",IF(ABS(C29)<=$B$3,"PASS","ERROR")) -> PASS | D30: =IF(D29="N/A","N/A",IF(ABS(D29)<=$B$3,"PASS","ERROR")) -> PASS | F30: =IF(F29="N/A","N/A",IF(ABS(F29)<=$B$3,"PASS","ERROR")) -> PASS | G30: =IF(G29="N/A","N/A",IF(ABS(G29)<=$B$3,"PASS","ERROR")) -> PASS
A31: S2 — Current financial-liability categories − reported current total | B31: =IF(COUNT(HISTORICAL_BS!B38,HISTORICAL_BS!B39)<2,"N/A",HISTORICAL_BS!B38-HISTORICAL_BS!B39) -> N/A | C31: =IF(COUNT(HISTORICAL_BS!C38,HISTORICAL_BS!C39)<2,"N/A",HISTORICAL_BS!C38-HISTORICAL_BS!C39) -> N/A | D31: =IF(COUNT(HISTORICAL_BS!D38,HISTORICAL_BS!D39)<2,"N/A",HISTORICAL_BS!D38-HISTORICAL_BS!D39) -> N/A | F31: =IF(COUNT(HISTORICAL_BS!F38,HISTORICAL_BS!F39)<2,"N/A",HISTORICAL_BS!F38-HISTORICAL_BS!F39) -> N/A | G31: =IF(COUNT(HISTORICAL_BS!G38,HISTORICAL_BS!G39)<2,"N/A",HISTORICAL_BS!G38-HISTORICAL_BS!G39) -> N/A | H31: =IF(COUNTIF(B32:G32,"ERROR")>0,"ERROR",IF(COUNTIF(B32:G32,"PASS")>0,"PASS","N/A")) -> N/A | I31: =COUNTIF(B32:G32,"PASS")+COUNTIF(B32:G32,"ERROR")&" of 5" -> 0 of 5
A32: status | B32: =IF(B31="N/A","N/A",IF(ABS(B31)<=$B$3,"PASS","ERROR")) -> N/A | C32: =IF(C31="N/A","N/A",IF(ABS(C31)<=$B$3,"PASS","ERROR")) -> N/A | D32: =IF(D31="N/A","N/A",IF(ABS(D31)<=$B$3,"PASS","ERROR")) -> N/A | F32: =IF(F31="N/A","N/A",IF(ABS(F31)<=$B$3,"PASS","ERROR")) -> N/A | G32: =IF(G31="N/A","N/A",IF(ABS(G31)<=$B$3,"PASS","ERROR")) -> N/A
A33: S3 — Non-current financial-liability categories − reported non-current total | B33: =IF(COUNT(HISTORICAL_BS!B46,HISTORICAL_BS!B47)<2,"N/A",HISTORICAL_BS!B46-HISTORICAL_BS!B47) -> N/A | C33: =IF(COUNT(HISTORICAL_BS!C46,HISTORICAL_BS!C47)<2,"N/A",HISTORICAL_BS!C46-HISTORICAL_BS!C47) -> N/A | D33: =IF(COUNT(HISTORICAL_BS!D46,HISTORICAL_BS!D47)<2,"N/A",HISTORICAL_BS!D46-HISTORICAL_BS!D47) -> N/A | F33: =IF(COUNT(HISTORICAL_BS!F46,HISTORICAL_BS!F47)<2,"N/A",HISTORICAL_BS!F46-HISTORICAL_BS!F47) -> N/A | G33: =IF(COUNT(HISTORICAL_BS!G46,HISTORICAL_BS!G47)<2,"N/A",HISTORICAL_BS!G46-HISTORICAL_BS!G47) -> N/A | H33: =IF(COUNTIF(B34:G34,"ERROR")>0,"ERROR",IF(COUNTIF(B34:G34,"PASS")>0,"PASS","N/A")) -> N/A | I33: =COUNTIF(B34:G34,"PASS")+COUNTIF(B34:G34,"ERROR")&" of 5" -> 0 of 5
A34: status | B34: =IF(B33="N/A","N/A",IF(ABS(B33)<=$B$3,"PASS","ERROR")) -> N/A | C34: =IF(C33="N/A","N/A",IF(ABS(C33)<=$B$3,"PASS","ERROR")) -> N/A | D34: =IF(D33="N/A","N/A",IF(ABS(D33)<=$B$3,"PASS","ERROR")) -> N/A | F34: =IF(F33="N/A","N/A",IF(ABS(F33)<=$B$3,"PASS","ERROR")) -> N/A | G34: =IF(G33="N/A","N/A",IF(ABS(G33)<=$B$3,"PASS","ERROR")) -> N/A
A35: S4 — Operating-cash-flow components − reported operating cash flow | B35: =IF(COUNT(HISTORICAL_CF!B18,HISTORICAL_CF!B19)<2,"N/A",HISTORICAL_CF!B18-HISTORICAL_CF!B19) -> N/A | C35: =IF(COUNT(HISTORICAL_CF!C18,HISTORICAL_CF!C19)<2,"N/A",HISTORICAL_CF!C18-HISTORICAL_CF!C19) -> N/A | D35: =IF(COUNT(HISTORICAL_CF!D18,HISTORICAL_CF!D19)<2,"N/A",HISTORICAL_CF!D18-HISTORICAL_CF!D19) -> N/A | E35: =IF(COUNT(HISTORICAL_CF!E18,HISTORICAL_CF!E19)<2,"N/A",HISTORICAL_CF!E18-HISTORICAL_CF!E19) -> N/A | F35: =IF(COUNT(HISTORICAL_CF!F18,HISTORICAL_CF!F19)<2,"N/A",HISTORICAL_CF!F18-HISTORICAL_CF!F19) -> 0 | G35: =IF(COUNT(HISTORICAL_CF!G18,HISTORICAL_CF!G19)<2,"N/A",HISTORICAL_CF!G18-HISTORICAL_CF!G19) -> 0 | H35: =IF(COUNTIF(B36:G36,"ERROR")>0,"ERROR",IF(COUNTIF(B36:G36,"PASS")>0,"PASS","N/A")) -> PASS | I35: =COUNTIF(B36:G36,"PASS")+COUNTIF(B36:G36,"ERROR")&" of 6" -> 2 of 6
A36: status | B36: =IF(B35="N/A","N/A",IF(ABS(B35)<=$B$3,"PASS","ERROR")) -> N/A | C36: =IF(C35="N/A","N/A",IF(ABS(C35)<=$B$3,"PASS","ERROR")) -> N/A | D36: =IF(D35="N/A","N/A",IF(ABS(D35)<=$B$3,"PASS","ERROR")) -> N/A | E36: =IF(E35="N/A","N/A",IF(ABS(E35)<=$B$3,"PASS","ERROR")) -> N/A | F36: =IF(F35="N/A","N/A",IF(ABS(F35)<=$B$3,"PASS","ERROR")) -> PASS | G36: =IF(G35="N/A","N/A",IF(ABS(G35)<=$B$3,"PASS","ERROR")) -> PASS
A37: S5 — Investing: continuing + discontinued − total | B37: =IF(COUNT(HISTORICAL_CF!B34,HISTORICAL_CF!B35,HISTORICAL_CF!B36)<3,"N/A",HISTORICAL_CF!B34+HISTORICAL_CF!B35-HISTORICAL_CF!B36) -> 0 | C37: =IF(COUNT(HISTORICAL_CF!C34,HISTORICAL_CF!C35,HISTORICAL_CF!C36)<3,"N/A",HISTORICAL_CF!C34+HISTORICAL_CF!C35-HISTORICAL_CF!C36) -> 0 | D37: =IF(COUNT(HISTORICAL_CF!D34,HISTORICAL_CF!D35,HISTORICAL_CF!D36)<3,"N/A",HISTORICAL_CF!D34+HISTORICAL_CF!D35-HISTORICAL_CF!D36) -> 0 | E37: =IF(COUNT(HISTORICAL_CF!E34,HISTORICAL_CF!E35,HISTORICAL_CF!E36)<3,"N/A",HISTORICAL_CF!E34+HISTORICAL_CF!E35-HISTORICAL_CF!E36) -> 0 | F37: =IF(COUNT(HISTORICAL_CF!F34,HISTORICAL_CF!F35,HISTORICAL_CF!F36)<3,"N/A",HISTORICAL_CF!F34+HISTORICAL_CF!F35-HISTORICAL_CF!F36) -> 0 | G37: =IF(COUNT(HISTORICAL_CF!G34,HISTORICAL_CF!G35,HISTORICAL_CF!G36)<3,"N/A",HISTORICAL_CF!G34+HISTORICAL_CF!G35-HISTORICAL_CF!G36) -> 0 | H37: =IF(COUNTIF(B38:G38,"ERROR")>0,"ERROR",IF(COUNTIF(B38:G38,"PASS")>0,"PASS","N/A")) -> PASS | I37: =COUNTIF(B38:G38,"PASS")+COUNTIF(B38:G38,"ERROR")&" of 6" -> 6 of 6
A38: status | B38: =IF(B37="N/A","N/A",IF(ABS(B37)<=$B$3,"PASS","ERROR")) -> PASS | C38: =IF(C37="N/A","N/A",IF(ABS(C37)<=$B$3,"PASS","ERROR")) -> PASS | D38: =IF(D37="N/A","N/A",IF(ABS(D37)<=$B$3,"PASS","ERROR")) -> PASS | E38: =IF(E37="N/A","N/A",IF(ABS(E37)<=$B$3,"PASS","ERROR")) -> PASS | F38: =IF(F37="N/A","N/A",IF(ABS(F37)<=$B$3,"PASS","ERROR")) -> PASS | G38: =IF(G37="N/A","N/A",IF(ABS(G37)<=$B$3,"PASS","ERROR")) -> PASS
A39: S6 — Financing: continuing + discontinued − total | B39: =IF(COUNT(HISTORICAL_CF!B48,HISTORICAL_CF!B49,HISTORICAL_CF!B50)<3,"N/A",HISTORICAL_CF!B48+HISTORICAL_CF!B49-HISTORICAL_CF!B50) -> 0 | C39: =IF(COUNT(HISTORICAL_CF!C48,HISTORICAL_CF!C49,HISTORICAL_CF!C50)<3,"N/A",HISTORICAL_CF!C48+HISTORICAL_CF!C49-HISTORICAL_CF!C50) -> 0 | D39: =IF(COUNT(HISTORICAL_CF!D48,HISTORICAL_CF!D49,HISTORICAL_CF!D50)<3,"N/A",HISTORICAL_CF!D48+HISTORICAL_CF!D49-HISTORICAL_CF!D50) -> 0 | E39: =IF(COUNT(HISTORICAL_CF!E48,HISTORICAL_CF!E49,HISTORICAL_CF!E50)<3,"N/A",HISTORICAL_CF!E48+HISTORICAL_CF!E49-HISTORICAL_CF!E50) -> 0 | F39: =IF(COUNT(HISTORICAL_CF!F48,HISTORICAL_CF!F49,HISTORICAL_CF!F50)<3,"N/A",HISTORICAL_CF!F48+HISTORICAL_CF!F49-HISTORICAL_CF!F50) -> 0 | G39: =IF(COUNT(HISTORICAL_CF!G48,HISTORICAL_CF!G49,HISTORICAL_CF!G50)<3,"N/A",HISTORICAL_CF!G48+HISTORICAL_CF!G49-HISTORICAL_CF!G50) -> 0 | H39: =IF(COUNTIF(B40:G40,"ERROR")>0,"ERROR",IF(COUNTIF(B40:G40,"PASS")>0,"PASS","N/A")) -> PASS | I39: =COUNTIF(B40:G40,"PASS")+COUNTIF(B40:G40,"ERROR")&" of 6" -> 6 of 6
A40: status | B40: =IF(B39="N/A","N/A",IF(ABS(B39)<=$B$3,"PASS","ERROR")) -> PASS | C40: =IF(C39="N/A","N/A",IF(ABS(C39)<=$B$3,"PASS","ERROR")) -> PASS | D40: =IF(D39="N/A","N/A",IF(ABS(D39)<=$B$3,"PASS","ERROR")) -> PASS | E40: =IF(E39="N/A","N/A",IF(ABS(E39)<=$B$3,"PASS","ERROR")) -> PASS | F40: =IF(F39="N/A","N/A",IF(ABS(F39)<=$B$3,"PASS","ERROR")) -> PASS | G40: =IF(G39="N/A","N/A",IF(ABS(G39)<=$B$3,"PASS","ERROR")) -> PASS
A41: S7 — Net operating cash flow after tax: calculated − reported | B41: =IF(COUNT(HISTORICAL_CF!B21,HISTORICAL_CF!B22)<2,"N/A",HISTORICAL_CF!B21-HISTORICAL_CF!B22) -> 0 | C41: =IF(COUNT(HISTORICAL_CF!C21,HISTORICAL_CF!C22)<2,"N/A",HISTORICAL_CF!C21-HISTORICAL_CF!C22) -> 0 | D41: =IF(COUNT(HISTORICAL_CF!D21,HISTORICAL_CF!D22)<2,"N/A",HISTORICAL_CF!D21-HISTORICAL_CF!D22) -> 0 | E41: =IF(COUNT(HISTORICAL_CF!E21,HISTORICAL_CF!E22)<2,"N/A",HISTORICAL_CF!E21-HISTORICAL_CF!E22) -> N/A | F41: =IF(COUNT(HISTORICAL_CF!F21,HISTORICAL_CF!F22)<2,"N/A",HISTORICAL_CF!F21-HISTORICAL_CF!F22) -> 0 | G41: =IF(COUNT(HISTORICAL_CF!G21,HISTORICAL_CF!G22)<2,"N/A",HISTORICAL_CF!G21-HISTORICAL_CF!G22) -> 0 | H41: =IF(COUNTIF(B42:G42,"ERROR")>0,"ERROR",IF(COUNTIF(B42:G42,"PASS")>0,"PASS","N/A")) -> PASS | I41: =COUNTIF(B42:G42,"PASS")+COUNTIF(B42:G42,"ERROR")&" of 6" -> 5 of 6 | J41: e.g. 2023 Original: 11,561 − 2,135 = 9,426.
A42: status | B42: =IF(B41="N/A","N/A",IF(ABS(B41)<=$B$3,"PASS","ERROR")) -> PASS | C42: =IF(C41="N/A","N/A",IF(ABS(C41)<=$B$3,"PASS","ERROR")) -> PASS | D42: =IF(D41="N/A","N/A",IF(ABS(D41)<=$B$3,"PASS","ERROR")) -> PASS | E42: =IF(E41="N/A","N/A",IF(ABS(E41)<=$B$3,"PASS","ERROR")) -> N/A | F42: =IF(F41="N/A","N/A",IF(ABS(F41)<=$B$3,"PASS","ERROR")) -> PASS | G42: =IF(G41="N/A","N/A",IF(ABS(G41)<=$B$3,"PASS","ERROR")) -> PASS
A43: S8 — Investing lines − continuing investing cash flow | B43: =IF(COUNT(HISTORICAL_CF!B33,HISTORICAL_CF!B34)<2,"N/A",HISTORICAL_CF!B33-HISTORICAL_CF!B34) -> N/A | C43: =IF(COUNT(HISTORICAL_CF!C33,HISTORICAL_CF!C34)<2,"N/A",HISTORICAL_CF!C33-HISTORICAL_CF!C34) -> N/A | D43: =IF(COUNT(HISTORICAL_CF!D33,HISTORICAL_CF!D34)<2,"N/A",HISTORICAL_CF!D33-HISTORICAL_CF!D34) -> N/A | E43: =IF(COUNT(HISTORICAL_CF!E33,HISTORICAL_CF!E34)<2,"N/A",HISTORICAL_CF!E33-HISTORICAL_CF!E34) -> N/A | F43: =IF(COUNT(HISTORICAL_CF!F33,HISTORICAL_CF!F34)<2,"N/A",HISTORICAL_CF!F33-HISTORICAL_CF!F34) -> 0 | G43: =IF(COUNT(HISTORICAL_CF!G33,HISTORICAL_CF!G34)<2,"N/A",HISTORICAL_CF!G33-HISTORICAL_CF!G34) -> 0 | H43: =IF(COUNTIF(B44:G44,"ERROR")>0,"ERROR",IF(COUNTIF(B44:G44,"PASS")>0,"PASS","N/A")) -> PASS | I43: =COUNTIF(B44:G44,"PASS")+COUNTIF(B44:G44,"ERROR")&" of 6" -> 2 of 6 | J43: Line detail available for 2024–2025 only.
A44: status | B44: =IF(B43="N/A","N/A",IF(ABS(B43)<=$B$3,"PASS","ERROR")) -> N/A | C44: =IF(C43="N/A","N/A",IF(ABS(C43)<=$B$3,"PASS","ERROR")) -> N/A | D44: =IF(D43="N/A","N/A",IF(ABS(D43)<=$B$3,"PASS","ERROR")) -> N/A | E44: =IF(E43="N/A","N/A",IF(ABS(E43)<=$B$3,"PASS","ERROR")) -> N/A | F44: =IF(F43="N/A","N/A",IF(ABS(F43)<=$B$3,"PASS","ERROR")) -> PASS | G44: =IF(G43="N/A","N/A",IF(ABS(G43)<=$B$3,"PASS","ERROR")) -> PASS
A45: S9 — Financing lines − continuing financing cash flow | B45: =IF(COUNT(HISTORICAL_CF!B47,HISTORICAL_CF!B48)<2,"N/A",HISTORICAL_CF!B47-HISTORICAL_CF!B48) -> N/A | C45: =IF(COUNT(HISTORICAL_CF!C47,HISTORICAL_CF!C48)<2,"N/A",HISTORICAL_CF!C47-HISTORICAL_CF!C48) -> N/A | D45: =IF(COUNT(HISTORICAL_CF!D47,HISTORICAL_CF!D48)<2,"N/A",HISTORICAL_CF!D47-HISTORICAL_CF!D48) -> N/A | E45: =IF(COUNT(HISTORICAL_CF!E47,HISTORICAL_CF!E48)<2,"N/A",HISTORICAL_CF!E47-HISTORICAL_CF!E48) -> N/A | F45: =IF(COUNT(HISTORICAL_CF!F47,HISTORICAL_CF!F48)<2,"N/A",HISTORICAL_CF!F47-HISTORICAL_CF!F48) -> 0 | G45: =IF(COUNT(HISTORICAL_CF!G47,HISTORICAL_CF!G48)<2,"N/A",HISTORICAL_CF!G47-HISTORICAL_CF!G48) -> 0 | H45: =IF(COUNTIF(B46:G46,"ERROR")>0,"ERROR",IF(COUNTIF(B46:G46,"PASS")>0,"PASS","N/A")) -> PASS | I45: =COUNTIF(B46:G46,"PASS")+COUNTIF(B46:G46,"ERROR")&" of 6" -> 2 of 6 | J45: Line detail available for 2024–2025 only.
A46: status | B46: =IF(B45="N/A","N/A",IF(ABS(B45)<=$B$3,"PASS","ERROR")) -> N/A | C46: =IF(C45="N/A","N/A",IF(ABS(C45)<=$B$3,"PASS","ERROR")) -> N/A | D46: =IF(D45="N/A","N/A",IF(ABS(D45)<=$B$3,"PASS","ERROR")) -> N/A | E46: =IF(E45="N/A","N/A",IF(ABS(E45)<=$B$3,"PASS","ERROR")) -> N/A | F46: =IF(F45="N/A","N/A",IF(ABS(F45)<=$B$3,"PASS","ERROR")) -> PASS | G46: =IF(G45="N/A","N/A",IF(ABS(G45)<=$B$3,"PASS","ERROR")) -> PASS

Sheet HISTORICAL_OUTPUTS
A1: 08 HISTORICAL_OUTPUTS — STEP 2 FINDINGS
A2: € million unless stated. Every figure is a formula linked to the engine sheets. 2023 is shown on both bases; balance-sheet items have no 2023 Continuing column.
A3: Model status: | B3: =HISTORICAL_CHECKS!$B$10 -> COMPLETE — all core checks PASS
J4: Chart data (€bn, formula-linked; blank cells break the line at the basis change)
A5: Metric | B5: 2021 | C5: 2022 | D5: 2023 Original | E5: 2023 Continuing | F5: 2024 | G5: 2025 | H5: Note | K5: 2021 | L5: 2022 | M5: 2023 O | N5: 2023 C | O5: 2024 | P5: 2025
A6: Section 1 — Financial performance | J6: Revenue — original basis | K6: =IFERROR(HISTORICAL_IS!B6/1000,"") -> 52.444 | L6: =IFERROR(HISTORICAL_IS!C6/1000,"") -> 60.073 | M6: =IFERROR(HISTORICAL_IS!D6/1000,"") -> 59.604
A7: Revenue | B7: =HISTORICAL_IS!B6 -> 52444 | C7: =HISTORICAL_IS!C6 -> 60073 | D7: =HISTORICAL_IS!D6 -> 59604 | E7: =HISTORICAL_IS!E6 -> 51680 | F7: =HISTORICAL_IS!F6 -> 52479 | G7: =HISTORICAL_IS!G6 -> 50503 | J7: Revenue — continuing basis | N7: =IFERROR(HISTORICAL_IS!E6/1000,"") -> 51.68 | O7: =IFERROR(HISTORICAL_IS!F6/1000,"") -> 52.479 | P7: =IFERROR(HISTORICAL_IS!G6/1000,"") -> 50.503
A8: Revenue growth (like-for-like) | C8: =HISTORICAL_IS!C19 -> 0.14546945 | D8: =HISTORICAL_IS!D19 -> -0.0078071679 | F8: =HISTORICAL_IS!F19 -> 0.015460526 | G8: =HISTORICAL_IS!G19 -> -0.037653157 | J8: Operating profit — original basis | K8: =IFERROR(HISTORICAL_IS!B8/1000,"") -> 8.702 | L8: =IFERROR(HISTORICAL_IS!C8/1000,"") -> 10.755 | M8: =IFERROR(HISTORICAL_IS!D8/1000,"") -> 9.758
A9: Operating profit | B9: =HISTORICAL_IS!B8 -> 8702 | C9: =HISTORICAL_IS!C8 -> 10755 | D9: =HISTORICAL_IS!D8 -> 9758 | E9: =HISTORICAL_IS!E8 -> 8998 | F9: =HISTORICAL_IS!F8 -> 8829 | G9: =HISTORICAL_IS!G8 -> 9037 | J9: Operating profit — continuing basis | N9: =IFERROR(HISTORICAL_IS!E8/1000,"") -> 8.998 | O9: =IFERROR(HISTORICAL_IS!F8/1000,"") -> 8.829 | P9: =IFERROR(HISTORICAL_IS!G8/1000,"") -> 9.037
A10: Operating margin | B10: =HISTORICAL_IS!B20 -> 0.16592937 | C10: =HISTORICAL_IS!C20 -> 0.17903218 | D10: =HISTORICAL_IS!D20 -> 0.16371384 | E10: =HISTORICAL_IS!E20 -> 0.17410991 | F10: =HISTORICAL_IS!F20 -> 0.16823872 | G10: =HISTORICAL_IS!G20 -> 0.17893986 | J10: Operating CF — original basis | K10: =IFERROR(HISTORICAL_CF!B19/1000,"") -> 10.305 | L10: =IFERROR(HISTORICAL_CF!C19/1000,"") -> 10.089 | M10: =IFERROR(HISTORICAL_CF!D19/1000,"") -> 11.561
A11: Net profit | B11: =HISTORICAL_IS!B15 -> 6621 | C11: =HISTORICAL_IS!C15 -> 8269 | D11: =HISTORICAL_IS!D15 -> 7140 | E11: =HISTORICAL_IS!E15 -> 6637 | F11: =HISTORICAL_IS!F15 -> 6039 | G11: =HISTORICAL_IS!G15 -> 6213 | H11: 2023 Continuing onward: continuing operations. | J11: Operating CF — continuing basis | N11: =IFERROR(HISTORICAL_CF!E19/1000,"") -> 10.326 | O11: =IFERROR(HISTORICAL_CF!F19/1000,"") -> 10.913 | P11: =IFERROR(HISTORICAL_CF!G19/1000,"") -> 10.772
A12: Net margin | B12: =HISTORICAL_IS!B21 -> 0.12624895 | C12: =HISTORICAL_IS!C21 -> 0.13764919 | D12: =HISTORICAL_IS!D21 -> 0.11979062 | E12: =HISTORICAL_IS!E21 -> 0.12842492 | F12: =HISTORICAL_IS!F21 -> 0.1150746 | G12: =HISTORICAL_IS!G21 -> 0.12302239 | J12: FCF — original basis | K12: =IFERROR(HISTORICAL_CF!B57/1000,"") -> 6.393 | L12: =IFERROR(HISTORICAL_CF!C57/1000,"") -> 5.198 | M12: =IFERROR(HISTORICAL_CF!D57/1000,"") -> 7.091
J13: FCF — continuing basis | N13: =IFERROR(HISTORICAL_CF!E57/1000,"") -> 6.445 | O13: =IFERROR(HISTORICAL_CF!F57/1000,"") -> 6.303 | P13: =IFERROR(HISTORICAL_CF!G57/1000,"") -> 5.921
A14: Section 2 — Liquidity (year-end)
A15: Cash (balance sheet) | B15: =HISTORICAL_BS!B12 -> 3415 | C15: =HISTORICAL_BS!C12 -> 4326 | D15: =HISTORICAL_BS!D12 -> 4159 | F15: =HISTORICAL_BS!F12 -> 6136 | G15: =HISTORICAL_BS!G12 -> 3941 | K15: 2021 | L15: 2022 | M15: 2023 | N15: 2024 | O15: 2025
A16: Current financial assets | B16: =HISTORICAL_BS!B13 -> 1156 | C16: =HISTORICAL_BS!C13 -> 1435 | D16: =HISTORICAL_BS!D13 -> 1731 | F16: =HISTORICAL_BS!F13 -> 1330 | G16: =HISTORICAL_BS!G13 -> 1121 | J16: Cash (balance sheet) | K16: =IFERROR(HISTORICAL_BS!B12/1000,"") -> 3.415 | L16: =IFERROR(HISTORICAL_BS!C12/1000,"") -> 4.326 | M16: =IFERROR(HISTORICAL_BS!D12/1000,"") -> 4.159 | N16: =IFERROR(HISTORICAL_BS!F12/1000,"") -> 6.136 | O16: =IFERROR(HISTORICAL_BS!G12/1000,"") -> 3.941
A17: Total liquidity | B17: =HISTORICAL_BS!B14 -> 4571 | C17: =HISTORICAL_BS!C14 -> 5761 | D17: =HISTORICAL_BS!D14 -> 5890 | F17: =HISTORICAL_BS!F14 -> 7466 | G17: =HISTORICAL_BS!G14 -> 5062 | J17: Net debt (reported) | K17: =IFERROR(HISTORICAL_BS!B60/1000,"") -> 25.51 | L17: =IFERROR(HISTORICAL_BS!C60/1000,"") -> 23.676 | M17: =IFERROR(HISTORICAL_BS!D60/1000,"") -> 23.657 | N17: =IFERROR(HISTORICAL_BS!F60/1000,"") -> 24.519 | O17: =IFERROR(HISTORICAL_BS!G60/1000,"") -> 23.076
A18: Net debt (reported) | B18: =HISTORICAL_BS!B60 -> 25510 | C18: =HISTORICAL_BS!C60 -> 23676 | D18: =HISTORICAL_BS!D60 -> 23657 | F18: =HISTORICAL_BS!F60 -> 24519 | G18: =HISTORICAL_BS!G60 -> 23076
A20: Section 3 — Cash generation
A21: Operating cash flow (before tax) | B21: =HISTORICAL_CF!B19 -> 10305 | C21: =HISTORICAL_CF!C19 -> 10089 | D21: =HISTORICAL_CF!D19 -> 11561 | E21: =HISTORICAL_CF!E19 -> 10326 | F21: =HISTORICAL_CF!F19 -> 10913 | G21: =HISTORICAL_CF!G19 -> 10772
A22: Free cash flow (calculated; reconciles to reported) | B22: =HISTORICAL_CF!B57 -> 6393 | C22: =HISTORICAL_CF!C57 -> 5198 | D22: =HISTORICAL_CF!D57 -> 7091 | E22: =HISTORICAL_CF!E57 -> 6445 | F22: =HISTORICAL_CF!F57 -> 6303 | G22: =HISTORICAL_CF!G57 -> 5921
A23: Net capital expenditure | B23: =HISTORICAL_CF!B27 -> -1239 | C23: =HISTORICAL_CF!C27 -> -1627 | D23: =HISTORICAL_CF!D27 -> -1703 | E23: =HISTORICAL_CF!E27 -> -1420 | F23: =HISTORICAL_CF!F27 -> -1599 | G23: =HISTORICAL_CF!G27 -> -1465
A24: Dividends paid | B24: =HISTORICAL_CF!B39 -> -4483 | C24: =HISTORICAL_CF!C39 -> -4329 | D24: =HISTORICAL_CF!D39 -> -4363 | E24: =HISTORICAL_CF!E39 -> -4363 | F24: =HISTORICAL_CF!F39 -> -4319 | G24: =HISTORICAL_CF!G39 -> -4453
A25: Share buybacks | B25: =HISTORICAL_CF!B45 -> -3018 | C25: =HISTORICAL_CF!C45 -> -1509 | D25: =HISTORICAL_CF!D45 -> -1507 | E25: =HISTORICAL_CF!E45 | F25: =HISTORICAL_CF!F45 -> -1508 | G25: =HISTORICAL_CF!G45 -> -1510 | H25: 2023 Continuing not printed in sources accessed.
A27: Section 4 — Working-capital movements (simplified)
A28: Inventory change | C28: =WORKING_CAPITAL!C11 -> 1248 | D28: =WORKING_CAPITAL!D11 -> -812 | F28: =WORKING_CAPITAL!F11 -> 58 | G28: =WORKING_CAPITAL!G11 -> -1134
A29: Receivables change (trade) | C29: =WORKING_CAPITAL!C12 -> 962 | D29: =WORKING_CAPITAL!D12 -> -521 | F29: =WORKING_CAPITAL!F12 -> 204 | G29: =WORKING_CAPITAL!G12 -> 625
A30: Payables change (trade) | C30: =WORKING_CAPITAL!C13 -> 2204 | D30: =WORKING_CAPITAL!D13 -> -745 | F30: =WORKING_CAPITAL!F13 -> -97 | G30: =WORKING_CAPITAL!G13 -> 736
A31: Simplified cash impact (+ = cash released) | C31: =WORKING_CAPITAL!C19 -> -6 | D31: =WORKING_CAPITAL!D19 -> 588 | F31: =WORKING_CAPITAL!F19 -> -359 | G31: =WORKING_CAPITAL!G19 -> 1245 | H31: 2025 includes the Ice Cream demerger effect on balances.
A33: Section 5 — Historical growth (YoY, like-for-like)
A34: Revenue — YoY | C34: =IFERROR(HISTORICAL_IS!C6/HISTORICAL_IS!B6-1,"") -> 0.14546945 | D34: =IFERROR(HISTORICAL_IS!D6/HISTORICAL_IS!C6-1,"") -> -0.0078071679 | F34: =IFERROR(HISTORICAL_IS!F6/HISTORICAL_IS!E6-1,"") -> 0.015460526 | G34: =IFERROR(HISTORICAL_IS!G6/HISTORICAL_IS!F6-1,"") -> -0.037653157 | H34: 2024 vs 2023 Continuing.
A35: Operating profit — YoY | C35: =IFERROR(HISTORICAL_IS!C8/HISTORICAL_IS!B8-1,"") -> 0.23592278 | D35: =IFERROR(HISTORICAL_IS!D8/HISTORICAL_IS!C8-1,"") -> -0.092701069 | F35: =IFERROR(HISTORICAL_IS!F8/HISTORICAL_IS!E8-1,"") -> -0.018781952 | G35: =IFERROR(HISTORICAL_IS!G8/HISTORICAL_IS!F8-1,"") -> 0.023558727 | H35: 2024 vs 2023 Continuing.
A36: Net profit — YoY | C36: =IFERROR(HISTORICAL_IS!C15/HISTORICAL_IS!B15-1,"") -> 0.248905 | D36: =IFERROR(HISTORICAL_IS!D15/HISTORICAL_IS!C15-1,"") -> -0.13653404 | F36: =IFERROR(HISTORICAL_IS!F15/HISTORICAL_IS!E15-1,"") -> -0.090100949 | G36: =IFERROR(HISTORICAL_IS!G15/HISTORICAL_IS!F15-1,"") -> 0.028812717 | H36: 2024 vs 2023 Continuing.
A37: Operating CF — YoY | C37: =IFERROR(HISTORICAL_CF!C19/HISTORICAL_CF!B19-1,"") -> -0.020960699 | D37: =IFERROR(HISTORICAL_CF!D19/HISTORICAL_CF!C19-1,"") -> 0.14590148 | F37: =IFERROR(HISTORICAL_CF!F19/HISTORICAL_CF!E19-1,"") -> 0.056846794 | G37: =IFERROR(HISTORICAL_CF!G19/HISTORICAL_CF!F19-1,"") -> -0.01292037 | H37: 2024 vs 2023 Continuing.
A38: FCF — YoY | C38: =IFERROR(HISTORICAL_CF!C57/HISTORICAL_CF!B57-1,"") -> -0.1869232 | D38: =IFERROR(HISTORICAL_CF!D57/HISTORICAL_CF!C57-1,"") -> 0.36417853 | F38: =IFERROR(HISTORICAL_CF!F57/HISTORICAL_CF!E57-1,"") -> -0.022032583 | G38: =IFERROR(HISTORICAL_CF!G57/HISTORICAL_CF!F57-1,"") -> -0.060606061 | H38: 2024 vs 2023 Continuing.
A39: Cash (balance sheet) — YoY | C39: =IFERROR(HISTORICAL_BS!C12/HISTORICAL_BS!B12-1,"") -> 0.26676428 | D39: =IFERROR(HISTORICAL_BS!D12/HISTORICAL_BS!C12-1,"") -> -0.038603791 | F39: =IFERROR(HISTORICAL_BS!F12/HISTORICAL_BS!D12-1,"") -> 0.47535465 | G39: =IFERROR(HISTORICAL_BS!G12/HISTORICAL_BS!F12-1,"") -> -0.3577249 | H39: 2024 vs 2023 Original year-end; 2025 vs 2024 includes demerger.
A40: Current financial assets — YoY | C40: =IFERROR(HISTORICAL_BS!C13/HISTORICAL_BS!B13-1,"") -> 0.24134948 | D40: =IFERROR(HISTORICAL_BS!D13/HISTORICAL_BS!C13-1,"") -> 0.20627178 | F40: =IFERROR(HISTORICAL_BS!F13/HISTORICAL_BS!D13-1,"") -> -0.231658 | G40: =IFERROR(HISTORICAL_BS!G13/HISTORICAL_BS!F13-1,"") -> -0.15714286 | H40: 2024 vs 2023 Original year-end; 2025 vs 2024 includes demerger.
A41: Net debt (reported) — YoY | C41: =IFERROR(HISTORICAL_BS!C60/HISTORICAL_BS!B60-1,"") -> -0.071893375 | D41: =IFERROR(HISTORICAL_BS!D60/HISTORICAL_BS!C60-1,"") -> -0.00080250042 | F41: =IFERROR(HISTORICAL_BS!F60/HISTORICAL_BS!D60-1,"") -> 0.036437418 | G41: =IFERROR(HISTORICAL_BS!G60/HISTORICAL_BS!F60-1,"") -> -0.058852319 | H41: 2024 vs 2023 Original year-end; 2025 vs 2024 includes demerger.
A42: Trade receivables — YoY | C42: =IFERROR(HISTORICAL_BS!C7/HISTORICAL_BS!B7-1,"") -> 0.26856505 | D42: =IFERROR(HISTORICAL_BS!D7/HISTORICAL_BS!C7-1,"") -> -0.11465669 | F42: =IFERROR(HISTORICAL_BS!F7/HISTORICAL_BS!D7-1,"") -> 0.050708427 | G42: =IFERROR(HISTORICAL_BS!G7/HISTORICAL_BS!F7-1,"") -> 0.147859 | H42: 2024 vs 2023 Original year-end; 2025 vs 2024 includes demerger.
A43: Inventories — YoY | C43: =IFERROR(HISTORICAL_BS!C6/HISTORICAL_BS!B6-1,"") -> 0.26649584 | D43: =IFERROR(HISTORICAL_BS!D6/HISTORICAL_BS!C6-1,"") -> -0.13690777 | F43: =IFERROR(HISTORICAL_BS!F6/HISTORICAL_BS!D6-1,"") -> 0.011330338 | G43: =IFERROR(HISTORICAL_BS!G6/HISTORICAL_BS!F6-1,"") -> -0.21904578 | H43: 2024 vs 2023 Original year-end; 2025 vs 2024 includes demerger.
A44: Trade payables — YoY | C44: =IFERROR(HISTORICAL_BS!C26/HISTORICAL_BS!B26-1,"") -> 0.2477518 | D44: =IFERROR(HISTORICAL_BS!D26/HISTORICAL_BS!C26-1,"") -> -0.067117117 | F44: =IFERROR(HISTORICAL_BS!F26/HISTORICAL_BS!D26-1,"") -> -0.0093674553 | G44: =IFERROR(HISTORICAL_BS!G26/HISTORICAL_BS!F26-1,"") -> 0.071748879 | H44: 2024 vs 2023 Original year-end; 2025 vs 2024 includes demerger.
A46: Section 5b — CAGR (flows and stocks only; no CAGR on ratios)
A47: Metric | B47: 2021→2025 (4 yrs) | C47: 2023C→2025 (2 yrs) | H47: Note
A48: Revenue | B48: =IFERROR((HISTORICAL_IS!G6/HISTORICAL_IS!B6)^(1/4)-1,"") -> -0.0093839912 | C48: =IFERROR((HISTORICAL_IS!G6/HISTORICAL_IS!E6)^(1/2)-1,"") -> -0.011452969 | H48: 2021→2025 is NOT like-for-like: 2021 includes Ice Cream, 2025 excludes it. 2023C→2025 is the like-for-like continuing measure.
A49: Operating profit | B49: =IFERROR((HISTORICAL_IS!G8/HISTORICAL_IS!B8)^(1/4)-1,"") -> 0.0094883256 | C49: =IFERROR((HISTORICAL_IS!G8/HISTORICAL_IS!E8)^(1/2)-1,"") -> 0.0021648051 | H49: 2021→2025 is NOT like-for-like: 2021 includes Ice Cream, 2025 excludes it. 2023C→2025 is the like-for-like continuing measure.
A50: Operating CF | B50: =IFERROR((HISTORICAL_CF!G19/HISTORICAL_CF!B19)^(1/4)-1,"") -> 0.011141853 | C50: =IFERROR((HISTORICAL_CF!G19/HISTORICAL_CF!E19)^(1/2)-1,"") -> 0.021367682 | H50: 2021→2025 is NOT like-for-like: 2021 includes Ice Cream, 2025 excludes it. 2023C→2025 is the like-for-like continuing measure.
A51: FCF | B51: =IFERROR((HISTORICAL_CF!G57/HISTORICAL_CF!B57)^(1/4)-1,"") -> -0.018991909 | C51: =IFERROR((HISTORICAL_CF!G57/HISTORICAL_CF!E57)^(1/2)-1,"") -> -0.041513347 | H51: 2021→2025 is NOT like-for-like: 2021 includes Ice Cream, 2025 excludes it. 2023C→2025 is the like-for-like continuing measure.
A52: Cash (balance sheet) | B52: =IFERROR((HISTORICAL_BS!G12/HISTORICAL_BS!B12)^(1/4)-1,"") -> 0.036463307 | C52: n/a | H52: 2021→2025 is NOT like-for-like: 2021 includes Ice Cream, 2025 excludes it. No 2023 Continuing balance sheet.
A54: Section 5c — Descriptive statistics of growth drivers (descriptive only — too few observations for statistical inference)
A55: Driver | B55: Average | C55: Std dev | D55: Min | E55: Max | F55: Observations | H55: Note
A56: Revenue growth | B56: =IFERROR(AVERAGE(B34:G34),"") -> 0.028867414 | C56: =IFERROR(STDEV(B34:G34),"") -> 0.080717184 | D56: =IFERROR(MIN(B34:G34),"") -> -0.037653157 | E56: =IFERROR(MAX(B34:G34),"") -> 0.14546945 | F56: =COUNT(B34:G34) -> 4 | H56: Sample std dev over like-for-like YoY rates (2022, 2023 Original, 2024, 2025).
A57: Operating CF growth | B57: =IFERROR(AVERAGE(B37:G37),"") -> 0.042216801 | C57: =IFERROR(STDEV(B37:G37),"") -> 0.077451174 | D57: =IFERROR(MIN(B37:G37),"") -> -0.020960699 | E57: =IFERROR(MAX(B37:G37),"") -> 0.14590148 | F57: =COUNT(B37:G37) -> 4 | H57: Sample std dev over like-for-like YoY rates (2022, 2023 Original, 2024, 2025).
A58: FCF growth | B58: =IFERROR(AVERAGE(B38:G38),"") -> 0.023654172 | C58: =IFERROR(STDEV(B38:G38),"") -> 0.23768798 | D58: =IFERROR(MIN(B38:G38),"") -> -0.1869232 | E58: =IFERROR(MAX(B38:G38),"") -> 0.36417853 | F58: =COUNT(B38:G38) -> 4 | H58: Sample std dev over like-for-like YoY rates (2022, 2023 Original, 2024, 2025).
A59: DSO | H59: Step 3 (Working Capital Engine).
A60: DIO | H60: Step 3 (Working Capital Engine).
A61: DPO | H61: Step 3 (Working Capital Engine).
A63: Charts — historical, explanatory (not the treasury dashboard). Solid = original basis (incl. Ice Cream); dashed = continuing basis (AR2025).
A116: Historical observations (factual; every number is a live formula)
A117: ="Revenue changed from €"&TEXT(HISTORICAL_IS!B6/1000,"0.0")&"bn in 2021 to €"&TEXT(HISTORICAL_IS!G6/1000,"0.0")&"bn in 2025 on a reported basis (2021 includes Ice Cream). On the continuing basis it moved from €"&TEXT(HISTORICAL_IS!E6/1000,"0.0")&"bn in 2023 to €"&TEXT(HISTORICAL_IS!G6/1000,"0.0")&"bn in 2025." -> Revenue changed from €52.4bn in 2021 to €50.5bn in 2025 on a reported basis (2021 includes Ice Cream). On the continuing basis it moved from €51.7bn in 2023 to €50.5bn in 2025.
A118: ="Operating margin was "&TEXT(HISTORICAL_IS!G20,"0.0%")&" in 2025, compared with "&TEXT(HISTORICAL_IS!E20,"0.0%")&" in 2023 on the continuing basis." -> Operating margin was 17.9% in 2025, compared with 17.4% in 2023 on the continuing basis.
A119: ="Operating cash flow (before tax) was €"&TEXT(HISTORICAL_CF!G19/1000,"0.0")&"bn in 2025." -> Operating cash flow (before tax) was €10.8bn in 2025.
A120: ="Free cash flow was €"&TEXT(HISTORICAL_CF!G57/1000,"0.0")&"bn in 2025, reconciling to Unilever's reported figure (Check 4 for 2025: "&HISTORICAL_CHECKS!G21&")." -> Free cash flow was €5.9bn in 2025, reconciling to Unilever's reported figure (Check 4 for 2025: PASS).
A121: ="Reported net debt was €"&TEXT(HISTORICAL_BS!G60/1000,"0.0")&"bn at year-end 2025, compared with €"&TEXT(HISTORICAL_BS!F60/1000,"0.0")&"bn at year-end 2024." -> Reported net debt was €23.1bn at year-end 2025, compared with €24.5bn at year-end 2024.
A122: ="Cash and current financial assets totalled €"&TEXT(HISTORICAL_BS!G14/1000,"0.0")&"bn at year-end 2025 (balance-sheet cash €"&TEXT(HISTORICAL_BS!G12/1000,"0.0")&"bn)." -> Cash and current financial assets totalled €5.1bn at year-end 2025 (balance-sheet cash €3.9bn).
A123: ="Simplified working-capital movements "&IF(WORKING_CAPITAL!G19>=0,"released","consumed")&" €"&TEXT(ABS(WORKING_CAPITAL!G19)/1000,"0.0")&"bn of cash in 2025 (inventory, trade receivables and trade payables only); this includes the effect of Ice Cream balances leaving the balance sheet at demerger." -> Simplified working-capital movements released €1.2bn of cash in 2025 (inventory, trade receivables and trade payables only); this includes the effect of Ice Cream balances leaving the balance sheet at demerger.
A124: ="Dividends and buybacks totalled "&TEXT(HISTORICAL_CF!G76,"0.0%")&" of FCF in 2025." -> Dividends and buybacks totalled 100.7% of FCF in 2025.

Sheet STEP3_README
A1: STEP 3 — TREASURY LIQUIDITY MODEL
A2: Documentation and logic map. Step 2 sheets are unchanged and act as the source layer.
A4: IMPORTANT MODELLING RULE | B4: Forecast cash flows are model assumptions and model outputs. They are not Unilever confidential treasury forecasts.
A5: Project | B5: Corporate Treasury & Liquidity Optimisation Engine
A6: Company | B6: Unilever plc
A7: Step 3 objective | B7: Estimate near-term liquidity requirements under base and stressed scenarios, identify potential liquidity deficits or surplus cash, and evaluate the funding/investment trade-off subject to an explicit minimum liquidity buffer.
A8: Step 2 status | B8: Frozen. All Step 2 sheets, checks and charts are unchanged and act as the source layer; the v4 raw dataset is not altered.
A9: Forecast horizon | B9: 13 weeks, starting the day after the 31 Dec 2025 balance sheet (weekly buckets; dates generated by formula on 13W_FORECAST).
A10: Scenario selector | B10: 13W_FORECAST!C4 (yellow dropdown: Base / Downside / Severe). One engine responds to it; there are no model copies.
A11: Base case | B11: Normal operating environment: 2025 continuing-basis run-rate, no growth, no working-capital stress, no rate or FX shock.
A12: Downside case | B12: Moderately adverse: customers pay 7 days later; +50bp on floating debt and new funding; non-EUR currencies −5% vs EUR. Supplier payments, tax and capex unchanged.
A13: Severe downside case | B13: Significant stress: collections 5% weaker AND 15 days later; +5 inventory days; −5 payables days; +200bp; non-EUR −10%. No management actions (capex, buyback or supplier cuts) assumed.
A14: Liquidity buffer methodology | B14: Modelled minimum liquidity = Base weekly gross operating outflows × 1.10 stress uplift × 3 weeks' coverage + restricted cash. NOT Unilever's internal policy. Coverage of 1–6 weeks is tested on LIQUIDITY_BUFFER.
A15: Funding assumptions | B15: Shortfalls below the buffer are drawn on the disclosed undrawn committed facilities (USD 5.2bn + EUR 2.6bn), revolver-style: draw when below the buffer, repay when above. Modelled rate = disclosed 2025 average short-term borrowing rate (4.3%) + scenario shock. Not bank pricing.
... A23: Limitations | B23: • No disclosed weekly timing: profiles are even or month-end. • Opening position is 31 Dec 2025; later interim data are not used. • ~85% of cash sits in foreign subsidiaries, so not all surplus can be pooled; the investable share is a simplification. • Currency allocation percentages are illustrative modelling assumptions, not Unilever-disclosed data. • Debt maturities are spread evenly over 12 months, with no bond-level schedule. • The next dividend (10 Apr 2026, secondary source) falls just outside the horizon. • No management actions in stress cases. • Interest and yields are accrued weekly on ACT/365 and not compounded.

Sheet ASSUMPTIONS
A1: ASSUMPTIONS — EVERY STEP 3 ASSUMPTION ORIGINATES HERE
A2: Blue = hard-coded input. Active column follows the scenario selected on 13W_FORECAST. Class: Disclosed = Unilever/official data not in the v4 dataset; Derived = calculated from disclosures; Model assumption = modeller's choice.
A4: Assumption | B4: Base | C4: Downside | D4: Severe | E4: ACTIVE | F4: Unit | G4: Class | H4: Source / rationale
A5: A. Calendar, opening position and committed facilities
A6: Opening balance-sheet date | B6: 46022 | C6: 46022 | D6: 46022 | E6: =INDEX($B6:$D6,MATCH(13W_FORECAST!$C$4,$B$4:$D$4,0)) -> 46022 | F6: date | G6: Disclosed | H6: Latest balance sheet in Step 2 (AR2025). Week 1 starts the following day.
A7: Days per forecast week | B7: 7 | C7: 7 | D7: 7 | E7: =INDEX($B7:$D7,MATCH(13W_FORECAST!$C$4,$B$4:$D$4,0)) -> 7 | F7: days | G7: Model assumption | H7: Weekly buckets.
A8: Day-count basis for interest | B8: 365 | C8: 365 | D8: 365 | E8: =INDEX($B8:$D8,MATCH(13W_FORECAST!$C$4,$B$4:$D$4,0)) -> 365 | F8: days | G8: Model assumption | H8: ACT/365 convention used for all funding and investment accruals.
A9: Cash restricted by FX / legal controls (YE2025) | B9: 160 | C9: 160 | D9: 160 | E9: =INDEX($B9:$D9,MATCH(13W_FORECAST!$C$4,$B$4:$D$4,0)) -> 160 | F9: €m | G9: Disclosed | H9: AR2025 treasury disclosure; dataset v4 'Raw Treasury Structure' (not in RAW_DATA). Treated as unavailable for group liquidity.
A10: Undrawn committed revolving facilities — USD | B10: 5200 | C10: 5200 | D10: 5200 | E10: =INDEX($B10:$D10,MATCH(13W_FORECAST!$C$4,$B$4:$D$4,0)) -> 5200 | F10: USD m | G10: Disclosed | H10: AR2025 Note 16A; dataset v4 'Raw Liquidity & Debt'.
A11: Undrawn committed revolving facilities — EUR | B11: 2600 | C11: 2600 | D11: 2600 | E11: =INDEX($B11:$D11,MATCH(13W_FORECAST!$C$4,$B$4:$D$4,0)) -> 2600 | F11: €m | G11: Disclosed | H11: AR2025 Note 16A; dataset v4 'Raw Liquidity & Debt'.
A12: EUR/USD rate for converting USD facilities | B12: 1.175 | C12: 1.175 | D12: 1.175 | E12: =INDEX($B12:$D12,MATCH(13W_FORECAST!$C$4,$B$4:$D$4,0)) -> 1.175 | F12: USD per € | G12: Disclosed | H12: ECB euro reference rate, 31 Dec 2025: 1 EUR = 1.1750 USD (ECB daily reference-rate sheet; also published in the EU Official Journal, C/2026/44). Held constant over the horizon.
A13: B. Operating assumptions — revenue, collections and working capital
A14: Revenue growth vs 2025 continuing run-rate (annualised) | B14: 0 | C14: 0 | D14: 0 | E14: =INDEX($B14:$D14,MATCH(13W_FORECAST!$C$4,$B$4:$D$4,0)) -> 0 | F14: % | G14: Model assumption | H14: 13-week horizon anchored to the 2025 continuing run-rate. No growth assumed; historical like-for-like growth (−3.8% 2025, +1.5% 2024) shown on LIQUIDITY_DRIVERS.
A15: Customer collections shock (level) | B15: 0 | C15: 0 | D15: -0.05 | E15: =INDEX($B15:$D15,MATCH(13W_FORECAST!$C$4,$B$4:$D$4,0)) -> 0 | F15: % | G15: Model assumption | H15: Severe: collections 5% weaker (volume/price). Supplier payments are NOT reduced in response (conservative: no management action assumed).
A16: Additional collection delay | B16: 0 | C16: 7 | D16: 15 | E16: =INDEX($B16:$D16,MATCH(13W_FORECAST!$C$4,$B$4:$D$4,0)) -> 0 | F16: days | G16: Model assumption | H16: 2025 DSO = 35.1 days (derived). Downside +7 days (≈ +20%); Severe +15 days (≈ +43%). Cash tied up = daily collections × extra days, phased in day by day.
A17: Collections timing profile | B17: Even | C17: Even | D17: Even | E17: =INDEX($B17:$D17,MATCH(13W_FORECAST!$C$4,$B$4:$D$4,0)) -> Even | F17: profile | G17: Model assumption | H17: 'Even' = annual/52 each week; 'Month-end' = annual/12 in weeks containing a month end. No disclosed weekly seasonality, so collections are flat.
A18: Additional inventory days (inventory build) | B18: 0 | C18: 0 | D18: 5 | E18: =INDEX($B18:$D18,MATCH(13W_FORECAST!$C$4,$B$4:$D$4,0)) -> 0 | F18: days | G18: Model assumption | H18: 2025 DIO = 55.1 days (derived). Severe: +5 days of cost of sales tied up in stock.
A19: Reduction in payables support (earlier supplier payment) | B19: 0 | C19: 0 | D19: 5 | E19: =INDEX($B19:$D19,MATCH(13W_FORECAST!$C$4,$B$4:$D$4,0)) -> 0 | F19: days | G19: Model assumption | H19: 2025 DPO = 149.8 days (derived; inflated by supplier financing of €2.7bn). Severe: −5 days, e.g. partial withdrawal of supplier-finance programmes.
A20: Supplier payment timing profile | B20: Even | C20: Even | D20: Even | E20: =INDEX($B20:$D20,MATCH(13W_FORECAST!$C$4,$B$4:$D$4,0)) -> Even | F20: profile | G20: Model assumption | H20: Supplier runs assumed weekly.
A21: Employee benefits expense — cash payroll proxy | B21: 6644 | C21: 6644 | D21: 6644 | E21: =INDEX($B21:$D21,MATCH(13W_FORECAST!$C$4,$B$4:$D$4,0)) -> 6644 | F21: €m | G21: Disclosed | H21: Employee benefits expense 2025, Unilever Form 20-F 2025 (XBRL ifrs-full:EmployeeBenefitsExpense). Not in dataset v4. Used as a modelling proxy for cash payroll; not a disclosed cash-payroll figure.
A22: Payroll timing profile | B22: Month-end | C22: Month-end | D22: Month-end | E22: =INDEX($B22:$D22,MATCH(13W_FORECAST!$C$4,$B$4:$D$4,0)) -> Month-end | F22: profile | G22: Model assumption | H22: Monthly payroll, paid in the week containing the month end.
A23: Tax cash payments vs run-rate | B23: 1 | C23: 1 | D23: 1 | E23: =INDEX($B23:$D23,MATCH(13W_FORECAST!$C$4,$B$4:$D$4,0)) -> 1 | F23: × | G23: Model assumption | H23: Tax unchanged in all scenarios (Step 3 brief).
A24: Tax payment timing profile | B24: Month-end | C24: Month-end | D24: Month-end | E24: =INDEX($B24:$D24,MATCH(13W_FORECAST!$C$4,$B$4:$D$4,0)) -> Month-end | F24: profile | G24: Model assumption | H24: Many jurisdictions; modelled as monthly instalments in month-end weeks.
A25: Capex vs run-rate | B25: 1 | C25: 1 | D25: 1 | E25: =INDEX($B25:$D25,MATCH(13W_FORECAST!$C$4,$B$4:$D$4,0)) -> 1 | F25: × | G25: Model assumption | H25: Capex unchanged in all scenarios (Step 3 brief): no discretionary capex cuts assumed.
A26: Capex timing profile | B26: Even | C26: Even | D26: Even | E26: =INDEX($B26:$D26,MATCH(13W_FORECAST!$C$4,$B$4:$D$4,0)) -> Even | F26: profile | G26: Model assumption
A27: Other operating outflows timing profile | B27: Even | C27: Even | D27: Even | E27: =INDEX($B27:$D27,MATCH(13W_FORECAST!$C$4,$B$4:$D$4,0)) -> Even | F27: profile | G27: Model assumption | H27: Pension contributions and provision utilisation (2025 run-rate).
A28: Other operating inflows timing profile | B28: Even | C28: Even | D28: Even | E28: =INDEX($B28:$D28,MATCH(13W_FORECAST!$C$4,$B$4:$D$4,0)) -> Even | F28: profile | G28: Model assumption | H28: Dividends from JVs/associates (2025 run-rate).
A29: Asset / investment maturities over 13 weeks (net inflow) | B29: 0 | C29: 0 | D29: 0 | E29: =INDEX($B29:$D29,MATCH(13W_FORECAST!$C$4,$B$4:$D$4,0)) -> 0 | F29: €m | G29: Model assumption | H29: Other current financial assets (€1.1bn) assumed rolled over; no net maturity inflow. They stay in available liquidity.
A30: C. Interest and funding
A31: Interest-rate shock | B31: 0 | C31: 50 | D31: 200 | E31: =INDEX($B31:$D31,MATCH(13W_FORECAST!$C$4,$B$4:$D$4,0)) -> 0 | F31: bp | G31: Model assumption | H31: Applied to floating-rate debt and to new liquidity funding. AR2025 gives €47m per +100bp full-year sensitivity (derived check on LIQUIDITY_DRIVERS).
A32: Share of financial liabilities at fixed rate (2026) | B32: 0.84 | C32: 0.84 | D32: 0.84 | E32: =INDEX($B32:$D32,MATCH(13W_FORECAST!$C$4,$B$4:$D$4,0)) -> 0.84 | F32: % | G32: Disclosed | H32: AR2025: expected liabilities fixed for 2026, after swaps, excl. leases (dataset v4 'Raw Risk & FX').
A33: Interest on existing debt timing profile | B33: Even | C33: Even | D33: Even | E33: =INDEX($B33:$D33,MATCH(13W_FORECAST!$C$4,$B$4:$D$4,0)) -> Even | F33: profile | G33: Model assumption | H33: No coupon calendar in the dataset, so spread evenly.
A34: Modelled funding rate on liquidity drawings (before shock) | B34: 0.043 | C34: 0.043 | D34: 0.043 | E34: =INDEX($B34:$D34,MATCH(13W_FORECAST!$C$4,$B$4:$D$4,0)) -> 0.043 | F34: % | G34: Derived | H34: Anchored to Unilever's disclosed 2025 average short-term borrowing rate (AR2025 Note 16B). NOT actual facility or bank pricing.
A35: Maximum facility utilisation before breach flag | B35: 1 | C35: 1 | D35: 1 | E35: =INDEX($B35:$D35,MATCH(13W_FORECAST!$C$4,$B$4:$D$4,0)) -> 1 | F35: % | G35: Model assumption | H35: Utilisation above this is flagged red and fails Check 7.
A36: D. Distributions and scheduled financing
A37: Dividend growth vs 2025 quarterly average | B37: 0 | C37: 0 | D37: 0 | E37: =INDEX($B37:$D37,MATCH(13W_FORECAST!$C$4,$B$4:$D$4,0)) -> 0 | F37: % | G37: Model assumption | H37: 2025 dividends paid ÷ 4. 2025 includes pre-demerger quarters, so this is an approximation.
A38: Next dividend payment date | B38: 46122 | C38: 46122 | D38: 46122 | E38: =INDEX($B38:$D38,MATCH(13W_FORECAST!$C$4,$B$4:$D$4,0)) -> 46122 | F38: date | G38: Disclosed | H38: Q4 2025 dividend payable 10 Apr 2026 (secondary source: dividendregistry.com; confirm with Unilever). Falls just AFTER the 13-week window, so it does not enter the forecast unless this date is changed.
A39: Share buybacks vs 2025 run-rate | B39: 1 | C39: 1 | D39: 1 | E39: =INDEX($B39:$D39,MATCH(13W_FORECAST!$C$4,$B$4:$D$4,0)) -> 1 | F39: × | G39: Model assumption | H39: 2025 buybacks continued at the same pace in all scenarios (no management action assumed).
A40: Buyback timing profile | B40: Even | C40: Even | D40: Even | E40: =INDEX($B40:$D40,MATCH(13W_FORECAST!$C$4,$B$4:$D$4,0)) -> Even | F40: profile | G40: Model assumption
A41: Refinancing of scheduled debt maturities | B41: 1 | C41: 1 | D41: 1 | E41: =INDEX($B41:$D41,MATCH(13W_FORECAST!$C$4,$B$4:$D$4,0)) -> 1 | F41: % | G41: Model assumption | H41: Maturing debt (current financial liabilities, spread evenly over 12 months) assumed refinanced at maturity. Liquidity gaps are met by the facility module, not here.
A42: Other financing flows over 13 weeks | B42: 0 | C42: 0 | D42: 0 | E42: =INDEX($B42:$D42,MATCH(13W_FORECAST!$C$4,$B$4:$D$4,0)) -> 0 | F42: €m | G42: Model assumption | H42: 2025 'other financing' (−€1.1bn) includes demerger-related items and is not treated as recurring.
A43: E. Surplus-cash investment
A44: Surplus-cash investment yield (annual) | B44: 0.02 | C44: 0.02 | D44: 0.02 | E44: =INDEX($B44:$D44,MATCH(13W_FORECAST!$C$4,$B$4:$D$4,0)) -> 0.02 | F44: % | G44: Disclosed | H44: Proxy: ECB deposit facility rate 2.00% (unchanged at the 5 Feb 2026 decision). Model assumption for a short-term cash investment (modelled proxy), not Unilever pricing.
A45: Share of surplus that is investable | B45: 1 | C45: 1 | D45: 1 | E45: =INDEX($B45:$D45,MATCH(13W_FORECAST!$C$4,$B$4:$D$4,0)) -> 1 | F45: % | G45: Model assumption | H45: Simplification: ~85% of group cash sits in foreign subsidiaries (AR2025), so not all surplus can be pooled centrally. See limitations.
A46: Maximum investment maturity | B46: 13 | C46: 13 | D46: 13 | E46: =INDEX($B46:$D46,MATCH(13W_FORECAST!$C$4,$B$4:$D$4,0)) -> 13 | F46: weeks | G46: Model assumption | H46: Instruments must mature within the 13-week horizon (documentation; accrual is weekly).
A47: Operating headroom kept uninvested above the buffer | B47: 0 | C47: 0 | D47: 0 | E47: =INDEX($B47:$D47,MATCH(13W_FORECAST!$C$4,$B$4:$D$4,0)) -> 0 | F47: €m | G47: Model assumption | H47: Buffer is already sized on stressed outflows; raise this to hold extra uninvested cash.
A48: F. FX liquidity
A49: Non-EUR currencies vs EUR (uniform shock) | B49: 0 | C49: -0.05 | D49: -0.1 | E49: =INDEX($B49:$D49,MATCH(13W_FORECAST!$C$4,$B$4:$D$4,0)) -> 0 | F49: % | G49: Model assumption | H49: Negative = EUR strengthens, so non-EUR operating flows are worth less in EUR. Applied to operating inflows and outflows only (financing is EUR-denominated).
A50: Operating inflows — EUR share | B50: 0.2 | C50: 0.2 | D50: 0.2 | E50: =INDEX($B50:$D50,MATCH(13W_FORECAST!$C$4,$B$4:$D$4,0)) -> 0.2 | F50: % | G50: Model assumption | H50: Illustrative modelling assumptions — not Unilever-disclosed operating cash-flow currency data. Unilever does not disclose cash flows by currency; shares loosely reflect its geographic mix (Europe ~20%, North America ~20%, emerging markets ~60%). Replace if better data is available.
A51: Operating inflows — GBP share | B51: 0.05 | C51: 0.05 | D51: 0.05 | E51: =INDEX($B51:$D51,MATCH(13W_FORECAST!$C$4,$B$4:$D$4,0)) -> 0.05 | F51: % | G51: Model assumption | H51: Illustrative modelling assumptions — not Unilever-disclosed operating cash-flow currency data. Unilever does not disclose cash flows by currency; shares loosely reflect its geographic mix (Europe ~20%, North America ~20%, emerging markets ~60%). Replace if better data is available.
A52: Operating inflows — USD share | B52: 0.2 | C52: 0.2 | D52: 0.2 | E52: =INDEX($B52:$D52,MATCH(13W_FORECAST!$C$4,$B$4:$D$4,0)) -> 0.2 | F52: % | G52: Model assumption | H52: Illustrative modelling assumptions — not Unilever-disclosed operating cash-flow currency data. Unilever does not disclose cash flows by currency; shares loosely reflect its geographic mix (Europe ~20%, North America ~20%, emerging markets ~60%). Replace if better data is available.
A53: Operating inflows — other currencies share | B53: 0.55 | C53: 0.55 | D53: 0.55 | E53: =INDEX($B53:$D53,MATCH(13W_FORECAST!$C$4,$B$4:$D$4,0)) -> 0.55 | F53: % | G53: Model assumption | H53: Illustrative modelling assumptions — not Unilever-disclosed operating cash-flow currency data. Unilever does not disclose cash flows by currency; shares loosely reflect its geographic mix (Europe ~20%, North America ~20%, emerging markets ~60%). Replace if better data is available.
A54: Operating outflows — EUR share | B54: 0.25 | C54: 0.25 | D54: 0.25 | E54: =INDEX($B54:$D54,MATCH(13W_FORECAST!$C$4,$B$4:$D$4,0)) -> 0.25 | F54: % | G54: Model assumption | H54: Illustrative modelling assumptions — not Unilever-disclosed operating cash-flow currency data. Unilever does not disclose cash flows by currency; shares loosely reflect its geographic mix (Europe ~20%, North America ~20%, emerging markets ~60%). Replace if better data is available.
A55: Operating outflows — GBP share | B55: 0.07 | C55: 0.07 | D55: 0.07 | E55: =INDEX($B55:$D55,MATCH(13W_FORECAST!$C$4,$B$4:$D$4,0)) -> 0.07 | F55: % | G55: Model assumption | H55: Illustrative modelling assumptions — not Unilever-disclosed operating cash-flow currency data. Unilever does not disclose cash flows by currency; shares loosely reflect its geographic mix (Europe ~20%, North America ~20%, emerging markets ~60%). Replace if better data is available.
A56: Operating outflows — USD share | B56: 0.2 | C56: 0.2 | D56: 0.2 | E56: =INDEX($B56:$D56,MATCH(13W_FORECAST!$C$4,$B$4:$D$4,0)) -> 0.2 | F56: % | G56: Model assumption | H56: Illustrative modelling assumptions — not Unilever-disclosed operating cash-flow currency data. Unilever does not disclose cash flows by currency; shares loosely reflect its geographic mix (Europe ~20%, North America ~20%, emerging markets ~60%). Replace if better data is available.
A57: Operating outflows — other currencies share | B57: 0.48 | C57: 0.48 | D57: 0.48 | E57: =INDEX($B57:$D57,MATCH(13W_FORECAST!$C$4,$B$4:$D$4,0)) -> 0.48 | F57: % | G57: Model assumption | H57: Illustrative modelling assumptions — not Unilever-disclosed operating cash-flow currency data. Unilever does not disclose cash flows by currency; shares loosely reflect its geographic mix (Europe ~20%, North America ~20%, emerging markets ~60%). Replace if better data is available.
A58: Single-currency stress size (FX_LIQUIDITY table) | B58: 0.05 | C58: 0.05 | D58: 0.05 | E58: =INDEX($B58:$D58,MATCH(13W_FORECAST!$C$4,$B$4:$D$4,0)) -> 0.05 | F58: % | G58: Model assumption | H58: ±5% move of each currency against EUR (Step 3 brief).
A59: G. Minimum liquidity buffer methodology
A60: Coverage period | B60: 3 | C60: 3 | D60: 3 | E60: =INDEX($B60:$D60,MATCH(13W_FORECAST!$C$4,$B$4:$D$4,0)) -> 3 | F60: weeks | G60: Model assumption | H60: Buffer covers 3 weeks of stressed gross operating outflows. Modelled buffer, NOT Unilever's internal policy. Alternatives of 1–6 weeks are tested on LIQUIDITY_BUFFER.
A61: Stress uplift on weekly gross outflows | B61: 1.1 | C61: 1.1 | D61: 1.1 | E61: =INDEX($B61:$D61,MATCH(13W_FORECAST!$C$4,$B$4:$D$4,0)) -> 1.1 | F61: × | G61: Model assumption | H61: +10% on the base run-rate of weekly outflows.
A62: H. Optimisation and sensitivity grids
A63: Buffer grid — first level | B63: 1000 | C63: 1000 | D63: 1000 | E63: =INDEX($B63:$D63,MATCH(13W_FORECAST!$C$4,$B$4:$D$4,0)) -> 1000 | F63: €m | G63: Model assumption | H63: Buffer levels tested on OPTIMISATION.
A64: Buffer grid — step | B64: 500 | C64: 500 | D64: 500 | E64: =INDEX($B64:$D64,MATCH(13W_FORECAST!$C$4,$B$4:$D$4,0)) -> 500 | F64: €m | G64: Model assumption
A65: Funding-rate grid — first level | B65: 0.02 | C65: 0.02 | D65: 0.02 | E65: =INDEX($B65:$D65,MATCH(13W_FORECAST!$C$4,$B$4:$D$4,0)) -> 0.02 | F65: % | G65: Model assumption | H65: Funding-rate columns in the sensitivity tables.
A66: Funding-rate grid — step | B66: 0.01 | C66: 0.01 | D66: 0.01 | E66: =INDEX($B66:$D66,MATCH(13W_FORECAST!$C$4,$B$4:$D$4,0)) -> 0.01 | F66: % | G66: Model assumption
A67: Collection-delay grid — first level | B67: 0 | C67: 0 | D67: 0 | E67: =INDEX($B67:$D67,MATCH(13W_FORECAST!$C$4,$B$4:$D$4,0)) -> 0 | F67: days | G67: Model assumption | H67: Collection-delay rows in sensitivity 2.
A68: Collection-delay grid — step | B68: 7 | C68: 7 | D68: 7 | E68: =INDEX($B68:$D68,MATCH(13W_FORECAST!$C$4,$B$4:$D$4,0)) -> 7 | F68: days | G68: Model assumption
A69: Buffer increment for the findings box | B69: 500 | C69: 500 | D69: 500 | E69: =INDEX($B69:$D69,MATCH(13W_FORECAST!$C$4,$B$4:$D$4,0)) -> 500 | F69: €m | G69: Model assumption | H69: Used to state the cost of holding a larger buffer.
A70: Check tolerance | B70: 0.01 | C70: 0.01 | D70: 0.01 | E70: =INDEX($B70:$D70,MATCH(13W_FORECAST!$C$4,$B$4:$D$4,0)) -> 0.01 | F70: €m | G70: Model assumption | H70: Step 3 checks are exact formula reconciliations, so the tolerance is tight.
A72: Scenario columns must stay labelled exactly Base / Downside / Severe (the selector matches on them).

Sheet LIQUIDITY_DRIVERS
A1: LIQUIDITY_DRIVERS — FROM HISTORICAL FIGURES TO FORECAST DRIVERS
A2: Historical columns link to Step 2 (continuing basis; balance sheet has no 2023 Continuing). Forecast columns are annual drivers for each scenario; ACTIVE follows the selector.
A4: Driver | B4: 2023 Continuing | C4: 2024 | D4: 2025 | E4: Base | F4: Downside | G4: Severe | H4: ACTIVE | I4: Unit | J4: Class | K4: Note
A5: Revenue and collections
A6: Revenue (turnover) | B6: =HISTORICAL_IS!E6 -> 51680 | C6: =HISTORICAL_IS!F6 -> 52479 | D6: =HISTORICAL_IS!G6 -> 50503 | I6: €m | J6: Disclosed (via Step 2)
A7: Historical revenue growth (like-for-like) | C7: =HISTORICAL_IS!F19 -> 0.015460526 | D7: =HISTORICAL_IS!G19 -> -0.037653157 | I7: €m | J7: Derived
A8: Selected forecast growth | E8: =ASSUMPTIONS!$B$14 -> 0 | F8: =ASSUMPTIONS!$C$14 -> 0 | G8: =ASSUMPTIONS!$D$14 -> 0 | H8: =INDEX(E8:G8,MATCH(13W_FORECAST!$C$4,$E$4:$G$4,0)) -> 0 | I8: % | J8: Model assumption
A9: Forecast annual revenue | E9: =$D$6*(1+E8) -> 50503 | F9: =$D$6*(1+F8) -> 50503 | G9: =$D$6*(1+G8) -> 50503 | H9: =INDEX(E9:G9,MATCH(13W_FORECAST!$C$4,$E$4:$G$4,0)) -> 50503 | I9: €m | J9: Model output
A10: Collections shock | E10: =ASSUMPTIONS!$B$15 -> 0 | F10: =ASSUMPTIONS!$C$15 -> 0 | G10: =ASSUMPTIONS!$D$15 -> -0.05 | H10: =INDEX(E10:G10,MATCH(13W_FORECAST!$C$4,$E$4:$G$4,0)) -> 0 | I10: % | J10: Model assumption
A11: Forecast annual customer collections (run-rate) | E11: =E9*(1+E10) -> 50503 | F11: =F9*(1+F10) -> 50503 | G11: =G9*(1+G10) -> 47977.85 | H11: =INDEX(E11:G11,MATCH(13W_FORECAST!$C$4,$E$4:$G$4,0)) -> 50503 | I11: €m | J11: Model output | K11: Collections are NOT assumed equal to revenue by default: the shock and the delay below adjust them.
A12: Weekly customer collections (even profile) | E12: =E11/52 -> 971.21154 | F12: =F11/52 -> 971.21154 | G12: =G11/52 -> 922.65096 | H12: =INDEX(E12:G12,MATCH(13W_FORECAST!$C$4,$E$4:$G$4,0)) -> 971.21154 | I12: €m | J12: Model output
A13: Daily customer collections | E13: =E11/365 -> 138.36438 | F13: =F11/365 -> 138.36438 | G13: =G11/365 -> 131.44616 | H13: =INDEX(E13:G13,MATCH(13W_FORECAST!$C$4,$E$4:$G$4,0)) -> 138.36438 | I13: €m | J13: Model output
A14: Operating cash flow and operating payments
A15: Operating cash flow (before tax) | B15: =HISTORICAL_CF!E19 -> 10326 | C15: =HISTORICAL_CF!F19 -> 10913 | D15: =HISTORICAL_CF!G19 -> 10772 | I15: €m | J15: Disclosed (via Step 2)
A16: Operating profit | B16: =HISTORICAL_IS!E8 -> 8998 | C16: =HISTORICAL_IS!F8 -> 8829 | D16: =HISTORICAL_IS!G8 -> 9037 | I16: €m | J16: Disclosed (via Step 2)
A17: OCF conversion (OCF ÷ operating profit) | B17: =HISTORICAL_CF!E72 -> 1.1475884 | C17: =HISTORICAL_CF!F72 -> 1.2360403 | D17: =HISTORICAL_CF!G72 -> 1.1919885 | I17: €m | J17: Derived
A18: OCF margin (OCF ÷ revenue) | B18: =IFERROR(B15/B6,"") -> 0.1998065 | C18: =IFERROR(C15/C6,"") -> 0.20794985 | D18: =IFERROR(D15/D6,"") -> 0.21329426 | I18: €m | J18: Derived
A19: Forecast annual OCF (selected margin = 2025) | E19: =E9*$D$18 -> 10772 | F19: =F9*$D$18 -> 10772 | G19: =G9*$D$18 -> 10772 | H19: =INDEX(E19:G19,MATCH(13W_FORECAST!$C$4,$E$4:$G$4,0)) -> 10772 | I19: €m | J19: Model output | K19: Memo: the weekly engine builds OCF bottom-up; at Base this equals 2025 OCF.
A20: Cash operating payments (revenue − OCF), 2025 | D20: =D6-D15 -> 39731 | I20: €m | J20: Derived | K20: Everything collected but not retained as operating cash flow in 2025.
A21: of which employee benefits expense — cash payroll proxy | D21: =ASSUMPTIONS!$B$21 -> 6644 | I21: €m | J21: Disclosed
A22: of which pensions and provision payments | D22: =-(HISTORICAL_CF!G13+HISTORICAL_CF!G14) -> 204 | I22: €m | J22: Derived | K22: 2025 'pensions less payments' + 'provisions less payments' (cash-flow statement).
A23: of which supplier and other operating payments (residual) | D23: =D20-D21-D22 -> 32883 | I23: €m | J23: Derived
A24: Forecast annual supplier payments | E24: =$D$23*(1+E8) -> 32883 | F24: =$D$23*(1+F8) -> 32883 | G24: =$D$23*(1+G8) -> 32883 | H24: =INDEX(E24:G24,MATCH(13W_FORECAST!$C$4,$E$4:$G$4,0)) -> 32883 | I24: €m | J24: Model output | K24: Scales with revenue growth, NOT with the collections shock (conservative).
A25: Forecast annual payroll (employee benefits expense proxy) | E25: =$D$21 -> 6644 | F25: =$D$21 -> 6644 | G25: =$D$21 -> 6644 | H25: =INDEX(E25:G25,MATCH(13W_FORECAST!$C$4,$E$4:$G$4,0)) -> 6644 | I25: €m | J25: Model output | K25: Fixed in the short term.
A26: Forecast annual pensions and provision payments | E26: =$D$22 -> 204 | F26: =$D$22 -> 204 | G26: =$D$22 -> 204 | H26: =INDEX(E26:G26,MATCH(13W_FORECAST!$C$4,$E$4:$G$4,0)) -> 204 | I26: €m | J26: Model output
A27: Dividends from JVs, associates and other investments | C27: =RAW_DATA!F75 -> 261 | D27: =RAW_DATA!G75 -> 243 | I27: €m | J27: Disclosed (via Step 2)
A28: Forecast annual other operating inflows | E28: =$D$27 -> 243 | F28: =$D$27 -> 243 | G28: =$D$27 -> 243 | H28: =INDEX(E28:G28,MATCH(13W_FORECAST!$C$4,$E$4:$G$4,0)) -> 243 | I28: €m | J28: Model output
A29: Working capital
A30: Inventories (year-end) | C30: =HISTORICAL_BS!F6 -> 5177 | D30: =HISTORICAL_BS!G6 -> 4043 | I30: €m | J30: Disclosed (via Step 2) | K30: No 2023 Continuing balance sheet.
A31: Trade receivables (year-end) | C31: =HISTORICAL_BS!F7 -> 4227 | D31: =HISTORICAL_BS!G7 -> 4852 | I31: €m | J31: Disclosed (via Step 2)
A32: Trade payables (year-end) | C32: =HISTORICAL_BS!F26 -> 10258 | D32: =HISTORICAL_BS!G26 -> 10994 | I32: €m | J32: Disclosed (via Step 2)
A33: Cost of sales | B33: =HISTORICAL_IS!E7 -> 29180 | C33: =HISTORICAL_IS!F7 -> 27976 | D33: =HISTORICAL_IS!G7 -> 26794 | I33: €m | J33: Disclosed (via Step 2)
A34: DSO (trade receivables ÷ revenue × 365) | C34: =IFERROR(C31/C6*365,"") -> 29.399474 | D34: =IFERROR(D31/D6*365,"") -> 35.066828 | I34: days | J34: Derived
A35: DIO (inventories ÷ cost of sales × 365) | C35: =IFERROR(C30/C33*365,"") -> 67.543788 | D35: =IFERROR(D30/D33*365,"") -> 55.075577 | I35: days | J35: Derived
A36: DPO (trade payables ÷ cost of sales × 365) | C36: =IFERROR(C32/C33*365,"") -> 133.83507 | D36: =IFERROR(D32/D33*365,"") -> 149.76525 | I36: days | J36: Derived | K36: Inflated by supplier financing (€2.7bn at YE2025).
A37: Change in working capital (cash-flow statement) | B37: =HISTORICAL_CF!E12 -> 753 | C37: =HISTORICAL_CF!F12 -> -188 | D37: =HISTORICAL_CF!G12 -> 116 | I37: €m | J37: Disclosed (via Step 2)
A38: Simplified balance-sheet WC movement (Step 2) | D38: =WORKING_CAPITAL!G19 -> 1245 | I38: €m | J38: Derived | K38: 2025 includes the Ice Cream demerger effect.
A39: Forecast daily cost of sales | E39: =$D$33*(1+E8)/365 -> 73.408219 | F39: =$D$33*(1+F8)/365 -> 73.408219 | G39: =$D$33*(1+G8)/365 -> 73.408219 | H39: =INDEX(E39:G39,MATCH(13W_FORECAST!$C$4,$E$4:$G$4,0)) -> 73.408219 | I39: €m | J39: Model output
A40: Additional collection delay | E40: =ASSUMPTIONS!$B$16 -> 0 | F40: =ASSUMPTIONS!$C$16 -> 7 | G40: =ASSUMPTIONS!$D$16 -> 15 | H40: =INDEX(E40:G40,MATCH(13W_FORECAST!$C$4,$E$4:$G$4,0)) -> 0 | I40: days | J40: Model assumption
A41: Additional inventory days | E41: =ASSUMPTIONS!$B$18 -> 0 | F41: =ASSUMPTIONS!$C$18 -> 0 | G41: =ASSUMPTIONS!$D$18 -> 5 | H41: =INDEX(E41:G41,MATCH(13W_FORECAST!$C$4,$E$4:$G$4,0)) -> 0 | I41: days | J41: Model assumption
A42: Reduction in payables days | E42: =ASSUMPTIONS!$B$19 -> 0 | F42: =ASSUMPTIONS!$C$19 -> 0 | G42: =ASSUMPTIONS!$D$19 -> 5 | H42: =INDEX(E42:G42,MATCH(13W_FORECAST!$C$4,$E$4:$G$4,0)) -> 0 | I42: days | J42: Model assumption
A43: Cash tied up — receivables (daily collections × delay) | E43: =E13*E40 -> 0 | F43: =F13*F40 -> 968.55068 | G43: =G13*G40 -> 1971.6925 | H43: =INDEX(E43:G43,MATCH(13W_FORECAST!$C$4,$E$4:$G$4,0)) -> 0 | I43: €m | J43: Model output
A44: Cash tied up — inventory (daily cost of sales × days) | E44: =E39*E41 -> 0 | F44: =F39*F41 -> 0 | G44: =G39*G41 -> 367.0411 | H44: =INDEX(E44:G44,MATCH(13W_FORECAST!$C$4,$E$4:$G$4,0)) -> 0 | I44: €m | J44: Model output
A45: Cash lost — payables support (daily cost of sales × days) | E45: =E39*E42 -> 0 | F45: =F39*F42 -> 0 | G45: =G39*G42 -> 367.0411 | H45: =INDEX(E45:G45,MATCH(13W_FORECAST!$C$4,$E$4:$G$4,0)) -> 0 | I45: €m | J45: Model output
A46: Incremental working-capital cash requirement | E46: =E43+E44+E45 -> 0 | F46: =F43+F44+F45 -> 968.55068 | G46: =G43+G44+G45 -> 2705.7747 | H46: =INDEX(E46:G46,MATCH(13W_FORECAST!$C$4,$E$4:$G$4,0)) -> 0 | I46: €m | J46: Model output | K46: Fully felt once the extra days have elapsed (within 3 weeks at Severe).
A47: Capex
A48: Net capital expenditure | B48: =HISTORICAL_CF!E27 -> -1420 | C48: =HISTORICAL_CF!F27 -> -1599 | D48: =HISTORICAL_CF!G27 -> -1465 | I48: €m | J48: Disclosed (via Step 2)
A49: Capex ÷ revenue | B49: =HISTORICAL_CF!E74 -> 0.02747678 | C49: =HISTORICAL_CF!F74 -> 0.030469331 | D49: =HISTORICAL_CF!G74 -> 0.029008178 | I49: €m | J49: Derived
A50: Forecast annual capex (2025 intensity × forecast revenue) | E50: =$D$49*E9*ASSUMPTIONS!$B$25 -> 1465 | F50: =$D$49*F9*ASSUMPTIONS!$C$25 -> 1465 | G50: =$D$49*G9*ASSUMPTIONS!$D$25 -> 1465 | H50: =INDEX(E50:G50,MATCH(13W_FORECAST!$C$4,$E$4:$G$4,0)) -> 1465 | I50: €m | J50: Model output
A51: Tax
A52: Effective tax rate | B52: =HISTORICAL_IS!E22 -> 0.23067115 | C52: =HISTORICAL_IS!F22 -> 0.27858081 | D52: =HISTORICAL_IS!G22 -> 0.28540205 | I52: €m | J52: Derived
A53: Income tax paid | B53: =HISTORICAL_CF!E20 -> -1933 | C53: =HISTORICAL_CF!F20 -> -2452 | D53: =HISTORICAL_CF!G20 -> -2720 | I53: €m | J53: Disclosed (via Step 2)
A54: PBT margin | B54: =IFERROR(HISTORICAL_IS!E13/B6,"") -> 0.16693111 | C54: =IFERROR(HISTORICAL_IS!F13/C6,"") -> 0.15951142 | D54: =IFERROR(HISTORICAL_IS!G13/D6,"") -> 0.17212839 | I54: €m | J54: Derived
A55: Cash tax ÷ tax charge | B55: =IFERROR(-B53/HISTORICAL_IS!E14,"") -> 0.97135678 | C55: =IFERROR(-C53/HISTORICAL_IS!F14,"") -> 1.051458 | D55: =IFERROR(-D53/HISTORICAL_IS!G14,"") -> 1.0963321 | I55: €m | J55: Derived
A56: Forecast tax rate (2025 ETR) | E56: =$D$52 -> 0.28540205 | F56: =$D$52 -> 0.28540205 | G56: =$D$52 -> 0.28540205 | H56: =INDEX(E56:G56,MATCH(13W_FORECAST!$C$4,$E$4:$G$4,0)) -> 0.28540205 | I56: €m | J56: Model assumption
A57: Forecast annual PBT (2025 margin × forecast revenue) | E57: =$D$54*E9 -> 8693 | F57: =$D$54*F9 -> 8693 | G57: =$D$54*G9 -> 8693 | H57: =INDEX(E57:G57,MATCH(13W_FORECAST!$C$4,$E$4:$G$4,0)) -> 8693 | I57: €m | J57: Model output
A58: Forecast annual tax cash payments | E58: =E57*E56*$D$55*ASSUMPTIONS!$B$23 -> 2720 | F58: =F57*F56*$D$55*ASSUMPTIONS!$C$23 -> 2720 | G58: =G57*G56*$D$55*ASSUMPTIONS!$D$23 -> 2720 | H58: =INDEX(E58:G58,MATCH(13W_FORECAST!$C$4,$E$4:$G$4,0)) -> 2720 | I58: €m | J58: Model output | K58: PBT × ETR × 2025 cash-tax ratio. At Base this equals 2025 tax paid.
A59: Interest and debt
A60: Interest paid | B60: =HISTORICAL_CF!E40 -> -751 | C60: =HISTORICAL_CF!F40 -> -929 | D60: =HISTORICAL_CF!G40 -> -1018 | I60: €m | J60: Disclosed (via Step 2)
A61: Total financial liabilities (year-end) | C61: =HISTORICAL_BS!F50 -> 32053 | D61: =HISTORICAL_BS!G50 -> 28278 | I61: €m | J61: Disclosed (via Step 2)
A62: Current financial liabilities (year-end) | C62: =HISTORICAL_BS!F39 -> 6987 | D62: =HISTORICAL_BS!G39 -> 2582 | I62: €m | J62: Disclosed (via Step 2)
A63: Implied average interest rate (interest paid ÷ average liabilities) | D63: =IFERROR(-D60/AVERAGE(C61:D61),"") -> 0.033747161 | I63: €m | J63: Derived
A64: Floating-rate liabilities (total × (1 − fixed share)) | D64: =D61*(1-ASSUMPTIONS!$B$32) -> 4524.48 | I64: €m | J64: Derived | K64: Approximation: the disclosed fixed share excludes leases.
A65: Memo: implied +100bp annual cost (compare AR2025: €47m) | D65: =D64*0.01 -> 45.2448 | I65: €m | J65: Derived | K65: Cross-check only. Gross floating debt overstates Unilever's net sensitivity, which nets floating-rate cash.
A66: Interest-rate shock | E66: =ASSUMPTIONS!$B$31 -> 0 | F66: =ASSUMPTIONS!$C$31 -> 50 | G66: =ASSUMPTIONS!$D$31 -> 200 | H66: =INDEX(E66:G66,MATCH(13W_FORECAST!$C$4,$E$4:$G$4,0)) -> 0 | I66: bp | J66: Model assumption
A67: Forecast annual interest on existing debt | E67: =-$D$60+$D$64*E66/10000 -> 1018 | F67: =-$D$60+$D$64*F66/10000 -> 1040.6224 | G67: =-$D$60+$D$64*G66/10000 -> 1108.4896 | H67: =INDEX(E67:G67,MATCH(13W_FORECAST!$C$4,$E$4:$G$4,0)) -> 1018 | I67: €m | J67: Model output | K67: Based on existing (beginning-period) debt, so there is no circularity with new funding.
A68: Funding rate on liquidity drawings (base + shock) | E68: =ASSUMPTIONS!$B$34+E66/10000 -> 0.043 | F68: =ASSUMPTIONS!$C$34+F66/10000 -> 0.048 | G68: =ASSUMPTIONS!$D$34+G66/10000 -> 0.063 | H68: =INDEX(E68:G68,MATCH(13W_FORECAST!$C$4,$E$4:$G$4,0)) -> 0.043 | I68: €m | J68: Model assumption
A69: Scheduled debt maturities over the next 12 months | E69: =$D$62 -> 2582 | F69: =$D$62 -> 2582 | G69: =$D$62 -> 2582 | H69: =INDEX(E69:G69,MATCH(13W_FORECAST!$C$4,$E$4:$G$4,0)) -> 2582 | I69: €m | J69: Model output | K69: Current financial liabilities at YE2025 (includes lease principal and short-term debt), assumed to mature evenly.
A70: Distributions
A71: Dividends paid | B71: =HISTORICAL_CF!E39 -> -4363 | C71: =HISTORICAL_CF!F39 -> -4319 | D71: =HISTORICAL_CF!G39 -> -4453 | I71: €m | J71: Disclosed (via Step 2)
A72: Share buybacks | B72: =HISTORICAL_CF!E45 | C72: =HISTORICAL_CF!F45 -> -1508 | D72: =HISTORICAL_CF!G45 -> -1510 | I72: €m | J72: Disclosed (via Step 2)
A73: Forecast quarterly dividend payment | E73: =-$D$71/4*(1+ASSUMPTIONS!$B$37) -> 1113.25 | F73: =-$D$71/4*(1+ASSUMPTIONS!$C$37) -> 1113.25 | G73: =-$D$71/4*(1+ASSUMPTIONS!$D$37) -> 1113.25 | H73: =INDEX(E73:G73,MATCH(13W_FORECAST!$C$4,$E$4:$G$4,0)) -> 1113.25 | I73: €m | J73: Model output
A74: Forecast annual share buybacks | E74: =-$D$72*ASSUMPTIONS!$B$39 -> 1510 | F74: =-$D$72*ASSUMPTIONS!$C$39 -> 1510 | G74: =-$D$72*ASSUMPTIONS!$D$39 -> 1510 | H74: =INDEX(E74:G74,MATCH(13W_FORECAST!$C$4,$E$4:$G$4,0)) -> 1510 | I74: €m | J74: Model output
A75: Liquidity buffer input
A76: Weekly gross operating outflows (run-rate) | E76: =(E24+E25+E26+E58+E50+E67)/52 -> 864.11538 | F76: =(F24+F25+F26+F58+F50+F67)/52 -> 864.55043 | G76: =(G24+G25+G26+G58+G50+G67)/52 -> 865.85557 | H76: =INDEX(E76:G76,MATCH(13W_FORECAST!$C$4,$E$4:$G$4,0)) -> 864.11538 | I76: €m | J76: Model output | K76: Suppliers + payroll + pensions/provisions + tax + capex + interest. The buffer uses the BASE column, so the buffer does not move with the scenario.

Sheet 13W_FORECAST
A1: 13W_FORECAST — 13-WEEK CASH FORECAST ENGINE (MODEL OUTPUT)
A2: Forecast cash flows are model assumptions and model outputs. They are not Unilever confidential treasury forecasts. € million; inflows +, outflows −.
A4: Selected scenario | C4: Base | D4: ← dropdown: Base / Downside / Severe. Every Step 3 sheet follows this cell.
A5: Opening balance-sheet date | C5: =ASSUMPTIONS!$E$6 -> 46022
A7: Calendar | B7: 13-wk total | C7: W1 | D7: W2 | E7: W3 | F7: W4 | G7: W5 | H7: W6 | I7: W7 | J7: W8 | K7: W9 | L7: W10 | M7: W11 | N7: W12 | O7: W13 | P7: Class / note
A8: Week | C8: =COLUMN()-COLUMN($B$8) -> 1 | D8: =COLUMN()-COLUMN($B$8) -> 2 | E8: =COLUMN()-COLUMN($B$8) -> 3 | F8: =COLUMN()-COLUMN($B$8) -> 4 | G8: =COLUMN()-COLUMN($B$8) -> 5 | H8: =COLUMN()-COLUMN($B$8) -> 6 | I8: =COLUMN()-COLUMN($B$8) -> 7 | J8: =COLUMN()-COLUMN($B$8) -> 8 | ... O8: =COLUMN()-COLUMN($B$8) -> 13
A9: Start date | C9: =C5+1 -> 46023 | D9: =C9+ASSUMPTIONS!$E$7 -> 46030 | E9: =D9+ASSUMPTIONS!$E$7 -> 46037 | F9: =E9+ASSUMPTIONS!$E$7 -> 46044 | G9: =F9+ASSUMPTIONS!$E$7 -> 46051 | H9: =G9+ASSUMPTIONS!$E$7 -> 46058 | I9: =H9+ASSUMPTIONS!$E$7 -> 46065 | J9: =I9+ASSUMPTIONS!$E$7 -> 46072 | K9: =J9+ASSUMPTIONS!$E$7 -> 46079 | ... O9: =N9+ASSUMPTIONS!$E$7 -> 46107 | P9: Week 1 starts the day after the balance-sheet date.
A10: End date | C10: =C9+ASSUMPTIONS!$E$7-1 -> 46029 | D10: =D9+ASSUMPTIONS!$E$7-1 -> 46036 | E10: =E9+ASSUMPTIONS!$E$7-1 -> 46043 | F10: =F9+ASSUMPTIONS!$E$7-1 -> 46050 | G10: =G9+ASSUMPTIONS!$E$7-1 -> 46057 | H10: =H9+ASSUMPTIONS!$E$7-1 -> 46064 | I10: =I9+ASSUMPTIONS!$E$7-1 -> 46071 | J10: =J9+ASSUMPTIONS!$E$7-1 -> 46078 | ... O10: =O9+ASSUMPTIONS!$E$7-1 -> 46113
A11: Month-end week (1 = contains a month end) | B11: =SUM(C11:O11) -> 3 | C11: =IF(MONTH(C9)<>MONTH(C10+1),1,0) -> 0 | D11: =IF(MONTH(D9)<>MONTH(D10+1),1,0) -> 0 | E11: =IF(MONTH(E9)<>MONTH(E10+1),1,0) -> 0 | F11: =IF(MONTH(F9)<>MONTH(F10+1),1,0) -> 0 | G11: =IF(MONTH(G9)<>MONTH(G10+1),1,0) -> 1 | H11: =IF(MONTH(H9)<>MONTH(H10+1),1,0) -> 0 | I11: =IF(MONTH(I9)<>MONTH(I10+1),1,0) -> 0 | J11: =IF(MONTH(J9)<>MONTH(J10+1),1,0) -> 0 | ... O11: =IF(MONTH(O9)<>MONTH(O10+1),1,0) -> 1 | P11: Drives month-end payroll and tax payments.
A12: Scenario | C12: =$C$4 -> Base | D12: =$C$4 -> Base | E12: =$C$4 -> Base | F12: =$C$4 -> Base | G12: =$C$4 -> Base | H12: =$C$4 -> Base | I12: =$C$4 -> Base | J12: =$C$4 -> Base | ... O12: =$C$4 -> Base
A13: Chart label | C13: ="W"&C8 -> W1 | D13: ="W"&D8 -> W2 | E13: ="W"&E8 -> W3 | F13: ="W"&F8 -> W4 | G13: ="W"&G8 -> W5 | H13: ="W"&H8 -> W6 | I13: ="W"&I8 -> W7 | J13: ="W"&J8 -> W8 | ... O13: ="W"&O8 -> W13
A15: Opening liquidity position (31 Dec 2025) — kept separate, not lumped into 'cash'
A16: Cash & cash equivalents — balance sheet (opening cash) | C16: =HISTORICAL_BS!G12 -> 3941 | D16: Disclosed (via Step 2): €3,941m. This is the opening cash.
A17: Memo: cash per cash-flow statement (not used) | C17: =HISTORICAL_BS!G18 -> 3870 | D17: €3,870m is net of overdrafts plus a held-for-sale adjustment; it is not the opening balance.
A18: Other current financial assets | C18: =HISTORICAL_BS!G13 -> 1121 | D18: Disclosed (via Step 2). Liquid, but not cash.
A19: Restricted cash (FX / legal controls) | C19: =ASSUMPTIONS!$E$9 -> 160 | D19: Disclosed. Included in cash but not available to the group.
A20: Available liquidity (cash + other current financial assets − restricted) | C20: =C16+C18-C19 -> 4902 | D20: Derived.
A21: Undrawn committed facilities (EUR equivalent) | C21: =ASSUMPTIONS!$E$10/ASSUMPTIONS!$E$12+ASSUMPTIONS!$E$11 -> 7025.5319 | D21: Disclosed amounts; USD converted at the 31 Dec 2025 ECB rate.
A22: Total liquidity including undrawn facilities | C22: =C20+C21 -> 11927.532 | D22: Derived.
A24: €m | B24: 13-wk total | C24: W1 | D24: W2 | E24: W3 | F24: W4 | G24: W5 | H24: W6 | I24: W7 | J24: W8 | K24: W9 | L24: W10 | M24: W11 | N24: W12 | O24: W13 | P24: Class / note
A25: Opening cash | C25: =$C$16 -> 3941 | D25: =C57 -> 4203.8077 | E25: =D57 -> 4466.6154 | F25: =E57 -> 4729.4231 | G25: =F57 -> 4992.2308 | H25: =G57 -> 4474.7051 | I25: =H57 -> 4737.5128 | J25: =I57 -> 5000.3205 | K25: =J57 -> 5263.1282 | ... O25: =N57 -> 5534.0256 | P25: Model output. W1 = balance-sheet cash; later weeks = prior week's closing cash.
A26: Inflows
A27: Customer collections (run-rate) | B27: =SUM(C27:O27) -> 12625.75 | C27: =IF(ASSUMPTIONS!$E$17="Month-end",(LIQUIDITY_DRIVERS!$H$11)/12*13W_FORECAST!C$11,(LIQUIDITY_DRIVERS!$H$11)/52) -> 971.21154 | D27: =IF(ASSUMPTIONS!$E$17="Month-end",(LIQUIDITY_DRIVERS!$H$11)/12*13W_FORECAST!D$11,(LIQUIDITY_DRIVERS!$H$11)/52) -> 971.21154 | E27: =IF(ASSUMPTIONS!$E$17="Month-end",(LIQUIDITY_DRIVERS!$H$11)/12*13W_FORECAST!E$11,(LIQUIDITY_DRIVERS!$H$11)/52) -> 971.21154 | F27: =IF(ASSUMPTIONS!$E$17="Month-end",(LIQUIDITY_DRIVERS!$H$11)/12*13W_FORECAST!F$11,(LIQUIDITY_DRIVERS!$H$11)/52) -> 971.21154 | G27: =IF(ASSUMPTIONS!$E$17="Month-end",(LIQUIDITY_DRIVERS!$H$11)/12*13W_FORECAST!G$11,(LIQUIDITY_DRIVERS!$H$11)/52) -> 971.21154 | H27: =IF(ASSUMPTIONS!$E$17="Month-end",(LIQUIDITY_DRIVERS!$H$11)/12*13W_FORECAST!H$11,(LIQUIDITY_DRIVERS!$H$11)/52) -> 971.21154 | I27: =IF(ASSUMPTIONS!$E$17="Month-end",(LIQUIDITY_DRIVERS!$H$11)/12*13W_FORECAST!I$11,(LIQUIDITY_DRIVERS!$H$11)/52) -> 971.21154 | J27: =IF(ASSUMPTIONS!$E$17="Month-end",(LIQUIDITY_DRIVERS!$H$11)/12*13W_FORECAST!J$11,(LIQUIDITY_DRIVERS!$H$11)/52) -> 971.21154 | ... O27: =IF(ASSUMPTIONS!$E$17="Month-end",(LIQUIDITY_DRIVERS!$H$11)/12*13W_FORECAST!O$11,(LIQUIDITY_DRIVERS!$H$11)/52) -> 971.21154 | P27: Model output: forecast annual collections ÷ 52 (profile per ASSUMPTIONS).
A28: Collection delay — cash tied up | B28: =SUM(C28:O28) -> 0 | C28: =-LIQUIDITY_DRIVERS!$H$13*(MIN(ASSUMPTIONS!$E$16,ASSUMPTIONS!$E$7*13W_FORECAST!C$8)-MIN(ASSUMPTIONS!$E$16,ASSUMPTIONS!$E$7*(13W_FORECAST!C$8-1))) -> 0 | D28: =-LIQUIDITY_DRIVERS!$H$13*(MIN(ASSUMPTIONS!$E$16,ASSUMPTIONS!$E$7*13W_FORECAST!D$8)-MIN(ASSUMPTIONS!$E$16,ASSUMPTIONS!$E$7*(13W_FORECAST!D$8-1))) -> 0 | E28: =-LIQUIDITY_DRIVERS!$H$13*(MIN(ASSUMPTIONS!$E$16,ASSUMPTIONS!$E$7*13W_FORECAST!E$8)-MIN(ASSUMPTIONS!$E$16,ASSUMPTIONS!$E$7*(13W_FORECAST!E$8-1))) -> 0 | F28: =-LIQUIDITY_DRIVERS!$H$13*(MIN(ASSUMPTIONS!$E$16,ASSUMPTIONS!$E$7*13W_FORECAST!F$8)-MIN(ASSUMPTIONS!$E$16,ASSUMPTIONS!$E$7*(13W_FORECAST!F$8-1))) -> 0 | G28: =-LIQUIDITY_DRIVERS!$H$13*(MIN(ASSUMPTIONS!$E$16,ASSUMPTIONS!$E$7*13W_FORECAST!G$8)-MIN(ASSUMPTIONS!$E$16,ASSUMPTIONS!$E$7*(13W_FORECAST!G$8-1))) -> 0 | H28: =-LIQUIDITY_DRIVERS!$H$13*(MIN(ASSUMPTIONS!$E$16,ASSUMPTIONS!$E$7*13W_FORECAST!H$8)-MIN(ASSUMPTIONS!$E$16,ASSUMPTIONS!$E$7*(13W_FORECAST!H$8-1))) -> 0 | I28: =-LIQUIDITY_DRIVERS!$H$13*(MIN(ASSUMPTIONS!$E$16,ASSUMPTIONS!$E$7*13W_FORECAST!I$8)-MIN(ASSUMPTIONS!$E$16,ASSUMPTIONS!$E$7*(13W_FORECAST!I$8-1))) -> 0 | J28: =-LIQUIDITY_DRIVERS!$H$13*(MIN(ASSUMPTIONS!$E$16,ASSUMPTIONS!$E$7*13W_FORECAST!J$8)-MIN(ASSUMPTIONS!$E$16,ASSUMPTIONS!$E$7*(13W_FORECAST!J$8-1))) -> 0 | ... O28: =-LIQUIDITY_DRIVERS!$H$13*(MIN(ASSUMPTIONS!$E$16,ASSUMPTIONS!$E$7*13W_FORECAST!O$8)-MIN(ASSUMPTIONS!$E$16,ASSUMPTIONS!$E$7*(13W_FORECAST!O$8-1))) -> 0 | P28: Model output: daily collections × extra days, phased in day by day.
A29: Other operating inflows (JV / associate dividends) | B29: =SUM(C29:O29) -> 60.75 | C29: =IF(ASSUMPTIONS!$E$28="Month-end",(LIQUIDITY_DRIVERS!$H$28)/12*13W_FORECAST!C$11,(LIQUIDITY_DRIVERS!$H$28)/52) -> 4.6730769 | D29: =IF(ASSUMPTIONS!$E$28="Month-end",(LIQUIDITY_DRIVERS!$H$28)/12*13W_FORECAST!D$11,(LIQUIDITY_DRIVERS!$H$28)/52) -> 4.6730769 | E29: =IF(ASSUMPTIONS!$E$28="Month-end",(LIQUIDITY_DRIVERS!$H$28)/12*13W_FORECAST!E$11,(LIQUIDITY_DRIVERS!$H$28)/52) -> 4.6730769 | F29: =IF(ASSUMPTIONS!$E$28="Month-end",(LIQUIDITY_DRIVERS!$H$28)/12*13W_FORECAST!F$11,(LIQUIDITY_DRIVERS!$H$28)/52) -> 4.6730769 | G29: =IF(ASSUMPTIONS!$E$28="Month-end",(LIQUIDITY_DRIVERS!$H$28)/12*13W_FORECAST!G$11,(LIQUIDITY_DRIVERS!$H$28)/52) -> 4.6730769 | H29: =IF(ASSUMPTIONS!$E$28="Month-end",(LIQUIDITY_DRIVERS!$H$28)/12*13W_FORECAST!H$11,(LIQUIDITY_DRIVERS!$H$28)/52) -> 4.6730769 | I29: =IF(ASSUMPTIONS!$E$28="Month-end",(LIQUIDITY_DRIVERS!$H$28)/12*13W_FORECAST!I$11,(LIQUIDITY_DRIVERS!$H$28)/52) -> 4.6730769 | J29: =IF(ASSUMPTIONS!$E$28="Month-end",(LIQUIDITY_DRIVERS!$H$28)/12*13W_FORECAST!J$11,(LIQUIDITY_DRIVERS!$H$28)/52) -> 4.6730769 | ... O29: =IF(ASSUMPTIONS!$E$28="Month-end",(LIQUIDITY_DRIVERS!$H$28)/12*13W_FORECAST!O$11,(LIQUIDITY_DRIVERS!$H$28)/52) -> 4.6730769 | P29: Model output.
A30: Asset / investment maturities | B30: =SUM(C30:O30) -> 0 | C30: =ASSUMPTIONS!$E$29/13 -> 0 | D30: =ASSUMPTIONS!$E$29/13 -> 0 | E30: =ASSUMPTIONS!$E$29/13 -> 0 | F30: =ASSUMPTIONS!$E$29/13 -> 0 | G30: =ASSUMPTIONS!$E$29/13 -> 0 | H30: =ASSUMPTIONS!$E$29/13 -> 0 | I30: =ASSUMPTIONS!$E$29/13 -> 0 | J30: =ASSUMPTIONS!$E$29/13 -> 0 | ... O30: =ASSUMPTIONS!$E$29/13 -> 0 | P30: Model assumption: rolled over (0).
A31: Total inflows | B31: =SUM(C31:O31) -> 12686.5 | C31: =SUM(C27:C30) -> 975.88462 | D31: =SUM(D27:D30) -> 975.88462 | E31: =SUM(E27:E30) -> 975.88462 | F31: =SUM(F27:F30) -> 975.88462 | G31: =SUM(G27:G30) -> 975.88462 | H31: =SUM(H27:H30) -> 975.88462 | I31: =SUM(I27:I30) -> 975.88462 | J31: =SUM(J27:J30) -> 975.88462 | ... O31: =SUM(O27:O30) -> 975.88462
A32: Operating outflows
A33: Supplier and other operating payments (run-rate) | B33: =SUM(C33:O33) -> -8220.75 | C33: =-IF(ASSUMPTIONS!$E$20="Month-end",(LIQUIDITY_DRIVERS!$H$24)/12*13W_FORECAST!C$11,(LIQUIDITY_DRIVERS!$H$24)/52) -> -632.36538 | D33: =-IF(ASSUMPTIONS!$E$20="Month-end",(LIQUIDITY_DRIVERS!$H$24)/12*13W_FORECAST!D$11,(LIQUIDITY_DRIVERS!$H$24)/52) -> -632.36538 | E33: =-IF(ASSUMPTIONS!$E$20="Month-end",(LIQUIDITY_DRIVERS!$H$24)/12*13W_FORECAST!E$11,(LIQUIDITY_DRIVERS!$H$24)/52) -> -632.36538 | F33: =-IF(ASSUMPTIONS!$E$20="Month-end",(LIQUIDITY_DRIVERS!$H$24)/12*13W_FORECAST!F$11,(LIQUIDITY_DRIVERS!$H$24)/52) -> -632.36538 | G33: =-IF(ASSUMPTIONS!$E$20="Month-end",(LIQUIDITY_DRIVERS!$H$24)/12*13W_FORECAST!G$11,(LIQUIDITY_DRIVERS!$H$24)/52) -> -632.36538 | H33: =-IF(ASSUMPTIONS!$E$20="Month-end",(LIQUIDITY_DRIVERS!$H$24)/12*13W_FORECAST!H$11,(LIQUIDITY_DRIVERS!$H$24)/52) -> -632.36538 | I33: =-IF(ASSUMPTIONS!$E$20="Month-end",(LIQUIDITY_DRIVERS!$H$24)/12*13W_FORECAST!I$11,(LIQUIDITY_DRIVERS!$H$24)/52) -> -632.36538 | J33: =-IF(ASSUMPTIONS!$E$20="Month-end",(LIQUIDITY_DRIVERS!$H$24)/12*13W_FORECAST!J$11,(LIQUIDITY_DRIVERS!$H$24)/52) -> -632.36538 | ... O33: =-IF(ASSUMPTIONS!$E$20="Month-end",(LIQUIDITY_DRIVERS!$H$24)/12*13W_FORECAST!O$11,(LIQUIDITY_DRIVERS!$H$24)/52) -> -632.36538 | P33: Model output.
A34: WC stress — inventory build | B34: =SUM(C34:O34) -> 0 | C34: =-LIQUIDITY_DRIVERS!$H$39*(MIN(ASSUMPTIONS!$E$18,ASSUMPTIONS!$E$7*13W_FORECAST!C$8)-MIN(ASSUMPTIONS!$E$18,ASSUMPTIONS!$E$7*(13W_FORECAST!C$8-1))) -> 0 | D34: =-LIQUIDITY_DRIVERS!$H$39*(MIN(ASSUMPTIONS!$E$18,ASSUMPTIONS!$E$7*13W_FORECAST!D$8)-MIN(ASSUMPTIONS!$E$18,ASSUMPTIONS!$E$7*(13W_FORECAST!D$8-1))) -> 0 | E34: =-LIQUIDITY_DRIVERS!$H$39*(MIN(ASSUMPTIONS!$E$18,ASSUMPTIONS!$E$7*13W_FORECAST!E$8)-MIN(ASSUMPTIONS!$E$18,ASSUMPTIONS!$E$7*(13W_FORECAST!E$8-1))) -> 0 | F34: =-LIQUIDITY_DRIVERS!$H$39*(MIN(ASSUMPTIONS!$E$18,ASSUMPTIONS!$E$7*13W_FORECAST!F$8)-MIN(ASSUMPTIONS!$E$18,ASSUMPTIONS!$E$7*(13W_FORECAST!F$8-1))) -> 0 | G34: =-LIQUIDITY_DRIVERS!$H$39*(MIN(ASSUMPTIONS!$E$18,ASSUMPTIONS!$E$7*13W_FORECAST!G$8)-MIN(ASSUMPTIONS!$E$18,ASSUMPTIONS!$E$7*(13W_FORECAST!G$8-1))) -> 0 | H34: =-LIQUIDITY_DRIVERS!$H$39*(MIN(ASSUMPTIONS!$E$18,ASSUMPTIONS!$E$7*13W_FORECAST!H$8)-MIN(ASSUMPTIONS!$E$18,ASSUMPTIONS!$E$7*(13W_FORECAST!H$8-1))) -> 0 | I34: =-LIQUIDITY_DRIVERS!$H$39*(MIN(ASSUMPTIONS!$E$18,ASSUMPTIONS!$E$7*13W_FORECAST!I$8)-MIN(ASSUMPTIONS!$E$18,ASSUMPTIONS!$E$7*(13W_FORECAST!I$8-1))) -> 0 | J34: =-LIQUIDITY_DRIVERS!$H$39*(MIN(ASSUMPTIONS!$E$18,ASSUMPTIONS!$E$7*13W_FORECAST!J$8)-MIN(ASSUMPTIONS!$E$18,ASSUMPTIONS!$E$7*(13W_FORECAST!J$8-1))) -> 0 | ... O34: =-LIQUIDITY_DRIVERS!$H$39*(MIN(ASSUMPTIONS!$E$18,ASSUMPTIONS!$E$7*13W_FORECAST!O$8)-MIN(ASSUMPTIONS!$E$18,ASSUMPTIONS!$E$7*(13W_FORECAST!O$8-1))) -> 0 | P34: Model output.
A35: WC stress — reduced payables support | B35: =SUM(C35:O35) -> 0 | C35: =-LIQUIDITY_DRIVERS!$H$39*(MIN(ASSUMPTIONS!$E$19,ASSUMPTIONS!$E$7*13W_FORECAST!C$8)-MIN(ASSUMPTIONS!$E$19,ASSUMPTIONS!$E$7*(13W_FORECAST!C$8-1))) -> 0 | D35: =-LIQUIDITY_DRIVERS!$H$39*(MIN(ASSUMPTIONS!$E$19,ASSUMPTIONS!$E$7*13W_FORECAST!D$8)-MIN(ASSUMPTIONS!$E$19,ASSUMPTIONS!$E$7*(13W_FORECAST!D$8-1))) -> 0 | E35: =-LIQUIDITY_DRIVERS!$H$39*(MIN(ASSUMPTIONS!$E$19,ASSUMPTIONS!$E$7*13W_FORECAST!E$8)-MIN(ASSUMPTIONS!$E$19,ASSUMPTIONS!$E$7*(13W_FORECAST!E$8-1))) -> 0 | F35: =-LIQUIDITY_DRIVERS!$H$39*(MIN(ASSUMPTIONS!$E$19,ASSUMPTIONS!$E$7*13W_FORECAST!F$8)-MIN(ASSUMPTIONS!$E$19,ASSUMPTIONS!$E$7*(13W_FORECAST!F$8-1))) -> 0 | G35: =-LIQUIDITY_DRIVERS!$H$39*(MIN(ASSUMPTIONS!$E$19,ASSUMPTIONS!$E$7*13W_FORECAST!G$8)-MIN(ASSUMPTIONS!$E$19,ASSUMPTIONS!$E$7*(13W_FORECAST!G$8-1))) -> 0 | H35: =-LIQUIDITY_DRIVERS!$H$39*(MIN(ASSUMPTIONS!$E$19,ASSUMPTIONS!$E$7*13W_FORECAST!H$8)-MIN(ASSUMPTIONS!$E$19,ASSUMPTIONS!$E$7*(13W_FORECAST!H$8-1))) -> 0 | I35: =-LIQUIDITY_DRIVERS!$H$39*(MIN(ASSUMPTIONS!$E$19,ASSUMPTIONS!$E$7*13W_FORECAST!I$8)-MIN(ASSUMPTIONS!$E$19,ASSUMPTIONS!$E$7*(13W_FORECAST!I$8-1))) -> 0 | J35: =-LIQUIDITY_DRIVERS!$H$39*(MIN(ASSUMPTIONS!$E$19,ASSUMPTIONS!$E$7*13W_FORECAST!J$8)-MIN(ASSUMPTIONS!$E$19,ASSUMPTIONS!$E$7*(13W_FORECAST!J$8-1))) -> 0 | ... O35: =-LIQUIDITY_DRIVERS!$H$39*(MIN(ASSUMPTIONS!$E$19,ASSUMPTIONS!$E$7*13W_FORECAST!O$8)-MIN(ASSUMPTIONS!$E$19,ASSUMPTIONS!$E$7*(13W_FORECAST!O$8-1))) -> 0 | P35: Model output.
A36: Payroll (employee benefits expense — cash payroll proxy) | B36: =SUM(C36:O36) -> -1661 | C36: =-IF(ASSUMPTIONS!$E$22="Month-end",(LIQUIDITY_DRIVERS!$H$25)/12*13W_FORECAST!C$11,(LIQUIDITY_DRIVERS!$H$25)/52) -> 0 | D36: =-IF(ASSUMPTIONS!$E$22="Month-end",(LIQUIDITY_DRIVERS!$H$25)/12*13W_FORECAST!D$11,(LIQUIDITY_DRIVERS!$H$25)/52) -> 0 | E36: =-IF(ASSUMPTIONS!$E$22="Month-end",(LIQUIDITY_DRIVERS!$H$25)/12*13W_FORECAST!E$11,(LIQUIDITY_DRIVERS!$H$25)/52) -> 0 | F36: =-IF(ASSUMPTIONS!$E$22="Month-end",(LIQUIDITY_DRIVERS!$H$25)/12*13W_FORECAST!F$11,(LIQUIDITY_DRIVERS!$H$25)/52) -> 0 | G36: =-IF(ASSUMPTIONS!$E$22="Month-end",(LIQUIDITY_DRIVERS!$H$25)/12*13W_FORECAST!G$11,(LIQUIDITY_DRIVERS!$H$25)/52) -> -553.66667 | H36: =-IF(ASSUMPTIONS!$E$22="Month-end",(LIQUIDITY_DRIVERS!$H$25)/12*13W_FORECAST!H$11,(LIQUIDITY_DRIVERS!$H$25)/52) -> 0 | I36: =-IF(ASSUMPTIONS!$E$22="Month-end",(LIQUIDITY_DRIVERS!$H$25)/12*13W_FORECAST!I$11,(LIQUIDITY_DRIVERS!$H$25)/52) -> 0 | J36: =-IF(ASSUMPTIONS!$E$22="Month-end",(LIQUIDITY_DRIVERS!$H$25)/12*13W_FORECAST!J$11,(LIQUIDITY_DRIVERS!$H$25)/52) -> 0 | ... O36: =-IF(ASSUMPTIONS!$E$22="Month-end",(LIQUIDITY_DRIVERS!$H$25)/12*13W_FORECAST!O$11,(LIQUIDITY_DRIVERS!$H$25)/52) -> -553.66667 | P36: Model output.
A37: Tax | B37: =SUM(C37:O37) -> -680 | C37: =-IF(ASSUMPTIONS!$E$24="Month-end",(LIQUIDITY_DRIVERS!$H$58)/12*13W_FORECAST!C$11,(LIQUIDITY_DRIVERS!$H$58)/52) -> 0 | D37: =-IF(ASSUMPTIONS!$E$24="Month-end",(LIQUIDITY_DRIVERS!$H$58)/12*13W_FORECAST!D$11,(LIQUIDITY_DRIVERS!$H$58)/52) -> 0 | E37: =-IF(ASSUMPTIONS!$E$24="Month-end",(LIQUIDITY_DRIVERS!$H$58)/12*13W_FORECAST!E$11,(LIQUIDITY_DRIVERS!$H$58)/52) -> 0 | F37: =-IF(ASSUMPTIONS!$E$24="Month-end",(LIQUIDITY_DRIVERS!$H$58)/12*13W_FORECAST!F$11,(LIQUIDITY_DRIVERS!$H$58)/52) -> 0 | G37: =-IF(ASSUMPTIONS!$E$24="Month-end",(LIQUIDITY_DRIVERS!$H$58)/12*13W_FORECAST!G$11,(LIQUIDITY_DRIVERS!$H$58)/52) -> -226.66667 | H37: =-IF(ASSUMPTIONS!$E$24="Month-end",(LIQUIDITY_DRIVERS!$H$58)/12*13W_FORECAST!H$11,(LIQUIDITY_DRIVERS!$H$58)/52) -> 0 | I37: =-IF(ASSUMPTIONS!$E$24="Month-end",(LIQUIDITY_DRIVERS!$H$58)/12*13W_FORECAST!I$11,(LIQUIDITY_DRIVERS!$H$58)/52) -> 0 | J37: =-IF(ASSUMPTIONS!$E$24="Month-end",(LIQUIDITY_DRIVERS!$H$58)/12*13W_FORECAST!J$11,(LIQUIDITY_DRIVERS!$H$58)/52) -> 0 | ... O37: =-IF(ASSUMPTIONS!$E$24="Month-end",(LIQUIDITY_DRIVERS!$H$58)/12*13W_FORECAST!O$11,(LIQUIDITY_DRIVERS!$H$58)/52) -> -226.66667 | P37: Model output.
A38: Capex | B38: =SUM(C38:O38) -> -366.25 | C38: =-IF(ASSUMPTIONS!$E$26="Month-end",(LIQUIDITY_DRIVERS!$H$50)/12*13W_FORECAST!C$11,(LIQUIDITY_DRIVERS!$H$50)/52) -> -28.173077 | D38: =-IF(ASSUMPTIONS!$E$26="Month-end",(LIQUIDITY_DRIVERS!$H$50)/12*13W_FORECAST!D$11,(LIQUIDITY_DRIVERS!$H$50)/52) -> -28.173077 | E38: =-IF(ASSUMPTIONS!$E$26="Month-end",(LIQUIDITY_DRIVERS!$H$50)/12*13W_FORECAST!E$11,(LIQUIDITY_DRIVERS!$H$50)/52) -> -28.173077 | F38: =-IF(ASSUMPTIONS!$E$26="Month-end",(LIQUIDITY_DRIVERS!$H$50)/12*13W_FORECAST!F$11,(LIQUIDITY_DRIVERS!$H$50)/52) -> -28.173077 | G38: =-IF(ASSUMPTIONS!$E$26="Month-end",(LIQUIDITY_DRIVERS!$H$50)/12*13W_FORECAST!G$11,(LIQUIDITY_DRIVERS!$H$50)/52) -> -28.173077 | H38: =-IF(ASSUMPTIONS!$E$26="Month-end",(LIQUIDITY_DRIVERS!$H$50)/12*13W_FORECAST!H$11,(LIQUIDITY_DRIVERS!$H$50)/52) -> -28.173077 | I38: =-IF(ASSUMPTIONS!$E$26="Month-end",(LIQUIDITY_DRIVERS!$H$50)/12*13W_FORECAST!I$11,(LIQUIDITY_DRIVERS!$H$50)/52) -> -28.173077 | J38: =-IF(ASSUMPTIONS!$E$26="Month-end",(LIQUIDITY_DRIVERS!$H$50)/12*13W_FORECAST!J$11,(LIQUIDITY_DRIVERS!$H$50)/52) -> -28.173077 | ... O38: =-IF(ASSUMPTIONS!$E$26="Month-end",(LIQUIDITY_DRIVERS!$H$50)/12*13W_FORECAST!O$11,(LIQUIDITY_DRIVERS!$H$50)/52) -> -28.173077 | P38: Model output.
A39: Interest on existing debt (incl. floating-rate shock) | B39: =SUM(C39:O39) -> -254.5 | C39: =-IF(ASSUMPTIONS!$E$33="Month-end",(LIQUIDITY_DRIVERS!$H$67)/12*13W_FORECAST!C$11,(LIQUIDITY_DRIVERS!$H$67)/52) -> -19.576923 | D39: =-IF(ASSUMPTIONS!$E$33="Month-end",(LIQUIDITY_DRIVERS!$H$67)/12*13W_FORECAST!D$11,(LIQUIDITY_DRIVERS!$H$67)/52) -> -19.576923 | E39: =-IF(ASSUMPTIONS!$E$33="Month-end",(LIQUIDITY_DRIVERS!$H$67)/12*13W_FORECAST!E$11,(LIQUIDITY_DRIVERS!$H$67)/52) -> -19.576923 | F39: =-IF(ASSUMPTIONS!$E$33="Month-end",(LIQUIDITY_DRIVERS!$H$67)/12*13W_FORECAST!F$11,(LIQUIDITY_DRIVERS!$H$67)/52) -> -19.576923 | G39: =-IF(ASSUMPTIONS!$E$33="Month-end",(LIQUIDITY_DRIVERS!$H$67)/12*13W_FORECAST!G$11,(LIQUIDITY_DRIVERS!$H$67)/52) -> -19.576923 | H39: =-IF(ASSUMPTIONS!$E$33="Month-end",(LIQUIDITY_DRIVERS!$H$67)/12*13W_FORECAST!H$11,(LIQUIDITY_DRIVERS!$H$67)/52) -> -19.576923 | I39: =-IF(ASSUMPTIONS!$E$33="Month-end",(LIQUIDITY_DRIVERS!$H$67)/12*13W_FORECAST!I$11,(LIQUIDITY_DRIVERS!$H$67)/52) -> -19.576923 | J39: =-IF(ASSUMPTIONS!$E$33="Month-end",(LIQUIDITY_DRIVERS!$H$67)/12*13W_FORECAST!J$11,(LIQUIDITY_DRIVERS!$H$67)/52) -> -19.576923 | ... O39: =-IF(ASSUMPTIONS!$E$33="Month-end",(LIQUIDITY_DRIVERS!$H$67)/12*13W_FORECAST!O$11,(LIQUIDITY_DRIVERS!$H$67)/52) -> -19.576923 | P39: Model output.
A40: Other operating outflows (pensions, provisions) | B40: =SUM(C40:O40) -> -51 | C40: =-IF(ASSUMPTIONS!$E$27="Month-end",(LIQUIDITY_DRIVERS!$H$26)/12*13W_FORECAST!C$11,(LIQUIDITY_DRIVERS!$H$26)/52) -> -3.9230769 | D40: =-IF(ASSUMPTIONS!$E$27="Month-end",(LIQUIDITY_DRIVERS!$H$26)/12*13W_FORECAST!D$11,(LIQUIDITY_DRIVERS!$H$26)/52) -> -3.9230769 | E40: =-IF(ASSUMPTIONS!$E$27="Month-end",(LIQUIDITY_DRIVERS!$H$26)/12*13W_FORECAST!E$11,(LIQUIDITY_DRIVERS!$H$26)/52) -> -3.9230769 | F40: =-IF(ASSUMPTIONS!$E$27="Month-end",(LIQUIDITY_DRIVERS!$H$26)/12*13W_FORECAST!F$11,(LIQUIDITY_DRIVERS!$H$26)/52) -> -3.9230769 | G40: =-IF(ASSUMPTIONS!$E$27="Month-end",(LIQUIDITY_DRIVERS!$H$26)/12*13W_FORECAST!G$11,(LIQUIDITY_DRIVERS!$H$26)/52) -> -3.9230769 | H40: =-IF(ASSUMPTIONS!$E$27="Month-end",(LIQUIDITY_DRIVERS!$H$26)/12*13W_FORECAST!H$11,(LIQUIDITY_DRIVERS!$H$26)/52) -> -3.9230769 | I40: =-IF(ASSUMPTIONS!$E$27="Month-end",(LIQUIDITY_DRIVERS!$H$26)/12*13W_FORECAST!I$11,(LIQUIDITY_DRIVERS!$H$26)/52) -> -3.9230769 | J40: =-IF(ASSUMPTIONS!$E$27="Month-end",(LIQUIDITY_DRIVERS!$H$26)/12*13W_FORECAST!J$11,(LIQUIDITY_DRIVERS!$H$26)/52) -> -3.9230769 | ... O40: =-IF(ASSUMPTIONS!$E$27="Month-end",(LIQUIDITY_DRIVERS!$H$26)/12*13W_FORECAST!O$11,(LIQUIDITY_DRIVERS!$H$26)/52) -> -3.9230769 | P40: Model output.
A41: Total operating outflows | B41: =SUM(C41:O41) -> -11233.5 | C41: =SUM(C33:C40) -> -684.03846 | D41: =SUM(D33:D40) -> -684.03846 | E41: =SUM(E33:E40) -> -684.03846 | F41: =SUM(F33:F40) -> -684.03846 | G41: =SUM(G33:G40) -> -1464.3718 | H41: =SUM(H33:H40) -> -684.03846 | I41: =SUM(I33:I40) -> -684.03846 | J41: =SUM(J33:J40) -> -684.03846 | ... O41: =SUM(O33:O40) -> -1464.3718
A42: FX impact on non-EUR operating flows | B42: =SUM(C42:O42) -> 0 | C42: =ASSUMPTIONS!$E$49*((1-ASSUMPTIONS!$E$50)*C31+(1-ASSUMPTIONS!$E$54)*C41) -> 0 | D42: =ASSUMPTIONS!$E$49*((1-ASSUMPTIONS!$E$50)*D31+(1-ASSUMPTIONS!$E$54)*D41) -> 0 | E42: =ASSUMPTIONS!$E$49*((1-ASSUMPTIONS!$E$50)*E31+(1-ASSUMPTIONS!$E$54)*E41) -> 0 | F42: =ASSUMPTIONS!$E$49*((1-ASSUMPTIONS!$E$50)*F31+(1-ASSUMPTIONS!$E$54)*F41) -> 0 | G42: =ASSUMPTIONS!$E$49*((1-ASSUMPTIONS!$E$50)*G31+(1-ASSUMPTIONS!$E$54)*G41) -> 0 | H42: =ASSUMPTIONS!$E$49*((1-ASSUMPTIONS!$E$50)*H31+(1-ASSUMPTIONS!$E$54)*H41) -> 0 | I42: =ASSUMPTIONS!$E$49*((1-ASSUMPTIONS!$E$50)*I31+(1-ASSUMPTIONS!$E$54)*I41) -> 0 | J42: =ASSUMPTIONS!$E$49*((1-ASSUMPTIONS!$E$50)*J31+(1-ASSUMPTIONS!$E$54)*J41) -> 0 | ... O42: =ASSUMPTIONS!$E$49*((1-ASSUMPTIONS!$E$50)*O31+(1-ASSUMPTIONS!$E$54)*O41) -> 0 | P42: Model output: shock × (non-EUR share of inflows + non-EUR share of outflows). Detail on FX_LIQUIDITY.
A43: Operating net cash flow | B43: =SUM(C43:O43) -> 1453 | C43: =C31+C41+C42 -> 291.84615 | D43: =D31+D41+D42 -> 291.84615 | E43: =E31+E41+E42 -> 291.84615 | F43: =F31+F41+F42 -> 291.84615 | G43: =G31+G41+G42 -> -488.48718 | H43: =H31+H41+H42 -> 291.84615 | I43: =I31+I41+I42 -> 291.84615 | J43: =J31+J41+J42 -> 291.84615 | ... O43: =O31+O41+O42 -> -488.48718
A44: Financing
A45: Debt drawdowns — scheduled refinancing | B45: =SUM(C45:O45) -> 645.5 | C45: =LIQUIDITY_DRIVERS!$H$69/52*ASSUMPTIONS!$E$41 -> 49.653846 | D45: =LIQUIDITY_DRIVERS!$H$69/52*ASSUMPTIONS!$E$41 -> 49.653846 | E45: =LIQUIDITY_DRIVERS!$H$69/52*ASSUMPTIONS!$E$41 -> 49.653846 | F45: =LIQUIDITY_DRIVERS!$H$69/52*ASSUMPTIONS!$E$41 -> 49.653846 | G45: =LIQUIDITY_DRIVERS!$H$69/52*ASSUMPTIONS!$E$41 -> 49.653846 | H45: =LIQUIDITY_DRIVERS!$H$69/52*ASSUMPTIONS!$E$41 -> 49.653846 | I45: =LIQUIDITY_DRIVERS!$H$69/52*ASSUMPTIONS!$E$41 -> 49.653846 | J45: =LIQUIDITY_DRIVERS!$H$69/52*ASSUMPTIONS!$E$41 -> 49.653846 | ... O45: =LIQUIDITY_DRIVERS!$H$69/52*ASSUMPTIONS!$E$41 -> 49.653846 | P45: Model output.
A46: Debt repayments — scheduled maturities | B46: =SUM(C46:O46) -> -645.5 | C46: =-LIQUIDITY_DRIVERS!$H$69/52 -> -49.653846 | D46: =-LIQUIDITY_DRIVERS!$H$69/52 -> -49.653846 | E46: =-LIQUIDITY_DRIVERS!$H$69/52 -> -49.653846 | F46: =-LIQUIDITY_DRIVERS!$H$69/52 -> -49.653846 | G46: =-LIQUIDITY_DRIVERS!$H$69/52 -> -49.653846 | H46: =-LIQUIDITY_DRIVERS!$H$69/52 -> -49.653846 | I46: =-LIQUIDITY_DRIVERS!$H$69/52 -> -49.653846 | J46: =-LIQUIDITY_DRIVERS!$H$69/52 -> -49.653846 | ... O46: =-LIQUIDITY_DRIVERS!$H$69/52 -> -49.653846 | P46: Model output.
A47: Dividends | B47: =SUM(C47:O47) -> 0 | C47: =-LIQUIDITY_DRIVERS!$H$73*AND(ASSUMPTIONS!$E$38>=13W_FORECAST!C$9,ASSUMPTIONS!$E$38<=13W_FORECAST!C$10) -> 0 | D47: =-LIQUIDITY_DRIVERS!$H$73*AND(ASSUMPTIONS!$E$38>=13W_FORECAST!D$9,ASSUMPTIONS!$E$38<=13W_FORECAST!D$10) -> 0 | E47: =-LIQUIDITY_DRIVERS!$H$73*AND(ASSUMPTIONS!$E$38>=13W_FORECAST!E$9,ASSUMPTIONS!$E$38<=13W_FORECAST!E$10) -> 0 | F47: =-LIQUIDITY_DRIVERS!$H$73*AND(ASSUMPTIONS!$E$38>=13W_FORECAST!F$9,ASSUMPTIONS!$E$38<=13W_FORECAST!F$10) -> 0 | G47: =-LIQUIDITY_DRIVERS!$H$73*AND(ASSUMPTIONS!$E$38>=13W_FORECAST!G$9,ASSUMPTIONS!$E$38<=13W_FORECAST!G$10) -> 0 | H47: =-LIQUIDITY_DRIVERS!$H$73*AND(ASSUMPTIONS!$E$38>=13W_FORECAST!H$9,ASSUMPTIONS!$E$38<=13W_FORECAST!H$10) -> 0 | I47: =-LIQUIDITY_DRIVERS!$H$73*AND(ASSUMPTIONS!$E$38>=13W_FORECAST!I$9,ASSUMPTIONS!$E$38<=13W_FORECAST!I$10) -> 0 | J47: =-LIQUIDITY_DRIVERS!$H$73*AND(ASSUMPTIONS!$E$38>=13W_FORECAST!J$9,ASSUMPTIONS!$E$38<=13W_FORECAST!J$10) -> 0 | ... O47: =-LIQUIDITY_DRIVERS!$H$73*AND(ASSUMPTIONS!$E$38>=13W_FORECAST!O$9,ASSUMPTIONS!$E$38<=13W_FORECAST!O$10) -> 0 | P47: Model output.
A48: Share buybacks | B48: =SUM(C48:O48) -> -377.5 | C48: =-IF(ASSUMPTIONS!$E$40="Month-end",(LIQUIDITY_DRIVERS!$H$74)/12*13W_FORECAST!C$11,(LIQUIDITY_DRIVERS!$H$74)/52) -> -29.038462 | D48: =-IF(ASSUMPTIONS!$E$40="Month-end",(LIQUIDITY_DRIVERS!$H$74)/12*13W_FORECAST!D$11,(LIQUIDITY_DRIVERS!$H$74)/52) -> -29.038462 | E48: =-IF(ASSUMPTIONS!$E$40="Month-end",(LIQUIDITY_DRIVERS!$H$74)/12*13W_FORECAST!E$11,(LIQUIDITY_DRIVERS!$H$74)/52) -> -29.038462 | F48: =-IF(ASSUMPTIONS!$E$40="Month-end",(LIQUIDITY_DRIVERS!$H$74)/12*13W_FORECAST!F$11,(LIQUIDITY_DRIVERS!$H$74)/52) -> -29.038462 | G48: =-IF(ASSUMPTIONS!$E$40="Month-end",(LIQUIDITY_DRIVERS!$H$74)/12*13W_FORECAST!G$11,(LIQUIDITY_DRIVERS!$H$74)/52) -> -29.038462 | H48: =-IF(ASSUMPTIONS!$E$40="Month-end",(LIQUIDITY_DRIVERS!$H$74)/12*13W_FORECAST!H$11,(LIQUIDITY_DRIVERS!$H$74)/52) -> -29.038462 | I48: =-IF(ASSUMPTIONS!$E$40="Month-end",(LIQUIDITY_DRIVERS!$H$74)/12*13W_FORECAST!I$11,(LIQUIDITY_DRIVERS!$H$74)/52) -> -29.038462 | J48: =-IF(ASSUMPTIONS!$E$40="Month-end",(LIQUIDITY_DRIVERS!$H$74)/12*13W_FORECAST!J$11,(LIQUIDITY_DRIVERS!$H$74)/52) -> -29.038462 | ... O48: =-IF(ASSUMPTIONS!$E$40="Month-end",(LIQUIDITY_DRIVERS!$H$74)/12*13W_FORECAST!O$11,(LIQUIDITY_DRIVERS!$H$74)/52) -> -29.038462 | P48: Model output.
A49: Other financing | B49: =SUM(C49:O49) -> 0 | C49: =ASSUMPTIONS!$E$42/13 -> 0 | D49: =ASSUMPTIONS!$E$42/13 -> 0 | E49: =ASSUMPTIONS!$E$42/13 -> 0 | F49: =ASSUMPTIONS!$E$42/13 -> 0 | G49: =ASSUMPTIONS!$E$42/13 -> 0 | H49: =ASSUMPTIONS!$E$42/13 -> 0 | I49: =ASSUMPTIONS!$E$42/13 -> 0 | J49: =ASSUMPTIONS!$E$42/13 -> 0 | ... O49: =ASSUMPTIONS!$E$42/13 -> 0 | P49: Model output.
A50: Net scheduled financing | B50: =SUM(C50:O50) -> -377.5 | C50: =SUM(C45:C49) -> -29.038462 | D50: =SUM(D45:D49) -> -29.038462 | E50: =SUM(E45:E49) -> -29.038462 | F50: =SUM(F45:F49) -> -29.038462 | G50: =SUM(G45:G49) -> -29.038462 | H50: =SUM(H45:H49) -> -29.038462 | I50: =SUM(I45:I49) -> -29.038462 | J50: =SUM(J45:J49) -> -29.038462 | ... O50: =SUM(O45:O49) -> -29.038462
A51: Closing cash before liquidity funding | B51: =MIN(C51:O51) -> 4203.8077 | C51: =C25+C43+C50 -> 4203.8077 | D51: =D25+D43+D50 -> 4466.6154 | E51: =E25+E43+E50 -> 4729.4231 | F51: =F25+F43+F50 -> 4992.2308 | G51: =G25+G43+G50 -> 4474.7051 | H51: =H25+H43+H50 -> 4737.5128 | I51: =I25+I43+I50 -> 5000.3205 | J51: =J25+J43+J50 -> 5263.1282 | ... O51: =O25+O43+O50 -> 5016.5 | P51: Model output. 13-wk column shows the minimum.
A52: Minimum liquidity buffer | C52: =LIQUIDITY_BUFFER!$C$10 -> 3011.5808 | D52: =LIQUIDITY_BUFFER!$C$10 -> 3011.5808 | E52: =LIQUIDITY_BUFFER!$C$10 -> 3011.5808 | F52: =LIQUIDITY_BUFFER!$C$10 -> 3011.5808 | G52: =LIQUIDITY_BUFFER!$C$10 -> 3011.5808 | H52: =LIQUIDITY_BUFFER!$C$10 -> 3011.5808 | I52: =LIQUIDITY_BUFFER!$C$10 -> 3011.5808 | J52: =LIQUIDITY_BUFFER!$C$10 -> 3011.5808 | ... O52: =LIQUIDITY_BUFFER!$C$10 -> 3011.5808 | P52: From LIQUIDITY_BUFFER methodology.
A53: Debt drawdowns — liquidity facility | B53: =SUM(C53:O53) -> 0 | C53: =MAX(0,C52-C51) -> 0 | D53: =MAX(0,D52-D51) -> 0 | E53: =MAX(0,E52-E51) -> 0 | F53: =MAX(0,F52-F51) -> 0 | G53: =MAX(0,G52-G51) -> 0 | H53: =MAX(0,H52-H51) -> 0 | I53: =MAX(0,I52-I51) -> 0 | J53: =MAX(0,J52-J51) -> 0 | ... O53: =MAX(0,O52-O51) -> 0 | P53: Model output: draws exactly enough to restore the buffer.
A54: Debt repayments — liquidity facility | B54: =SUM(C54:O54) -> 0 | C54: =-MIN(0,MAX(0,C51-C52)) -> 0 | D54: =-MIN(C59,MAX(0,D51-D52)) -> 0 | E54: =-MIN(D59,MAX(0,E51-E52)) -> 0 | F54: =-MIN(E59,MAX(0,F51-F52)) -> 0 | G54: =-MIN(F59,MAX(0,G51-G52)) -> 0 | H54: =-MIN(G59,MAX(0,H51-H52)) -> 0 | I54: =-MIN(H59,MAX(0,I51-I52)) -> 0 | J54: =-MIN(I59,MAX(0,J51-J52)) -> 0 | K54: =-MIN(J59,MAX(0,K51-K52)) -> 0 | ... O54: =-MIN(N59,MAX(0,O51-O52)) -> 0 | P54: Model output: repays the outstanding drawing once cash is above the buffer.
A55: Net financing cash flow | B55: =SUM(C55:O55) -> -377.5 | C55: =C50+C53+C54 -> -29.038462 | D55: =D50+D53+D54 -> -29.038462 | E55: =E50+E53+E54 -> -29.038462 | F55: =F50+F53+F54 -> -29.038462 | G55: =G50+G53+G54 -> -29.038462 | H55: =H50+H53+H54 -> -29.038462 | I55: =I50+I53+I54 -> -29.038462 | J55: =J50+J53+J54 -> -29.038462 | ... O55: =O50+O53+O54 -> -29.038462
A56: Net cash movement | B56: =SUM(C56:O56) -> 1075.5 | C56: =C43+C55 -> 262.80769 | D56: =D43+D55 -> 262.80769 | E56: =E43+E55 -> 262.80769 | F56: =F43+F55 -> 262.80769 | G56: =G43+G55 -> -517.52564 | H56: =H43+H55 -> 262.80769 | I56: =I43+I55 -> 262.80769 | J56: =J43+J55 -> 262.80769 | ... O56: =O43+O55 -> -517.52564
A57: Closing cash | B57: =MIN(C57:O57) -> 4203.8077 | C57: =C25+C56 -> 4203.8077 | D57: =D25+D56 -> 4466.6154 | E57: =E25+E56 -> 4729.4231 | F57: =F25+F56 -> 4992.2308 | G57: =G25+G56 -> 4474.7051 | H57: =H25+H56 -> 4737.5128 | I57: =I25+I56 -> 5000.3205 | J57: =J25+J56 -> 5263.1282 | ... O57: =O25+O56 -> 5016.5 | P57: Model output = opening + net movement. Never typed.
A58: Memo
A59: Liquidity facility drawn (outstanding) | B59: =MAX(C59:O59) -> 0 | C59: =C53+C54 -> 0 | D59: =C59+D53+D54 -> 0 | E59: =D59+E53+E54 -> 0 | F59: =E59+F53+F54 -> 0 | G59: =F59+G53+G54 -> 0 | H59: =G59+H53+H54 -> 0 | I59: =H59+I53+I54 -> 0 | J59: =I59+J53+J54 -> 0 | K59: =J59+K53+K54 -> 0 | ... O59: =N59+O53+O54 -> 0 | P59: 13-wk column shows the peak.
A60: Cumulative cash before any liquidity funding | B60: =MIN(C60:O60) -> 4203.8077 | C60: =$C$16+SUM($C$43:C43)+SUM($C$50:C50) -> 4203.8077 | D60: =$C$16+SUM($C$43:D43)+SUM($C$50:D50) -> 4466.6154 | E60: =$C$16+SUM($C$43:E43)+SUM($C$50:E50) -> 4729.4231 | F60: =$C$16+SUM($C$43:F43)+SUM($C$50:F50) -> 4992.2308 | G60: =$C$16+SUM($C$43:G43)+SUM($C$50:G50) -> 4474.7051 | H60: =$C$16+SUM($C$43:H43)+SUM($C$50:H50) -> 4737.5128 | I60: =$C$16+SUM($C$43:I43)+SUM($C$50:I50) -> 5000.3205 | J60: =$C$16+SUM($C$43:J43)+SUM($C$50:J50) -> 5263.1282 | ... O60: =$C$16+SUM($C$43:O43)+SUM($C$50:O50) -> 5016.5 | P60: Closed-form path used by OPTIMISATION and the sensitivities. Check 11 proves drawn = MAX(0, buffer − this).

Sheet SCENARIOS
A1: SCENARIOS — THREE SCENARIOS, ONE ENGINE
A2: Driver table links to ASSUMPTIONS. The results block recomputes weekly net cash for each scenario with the SAME formula generator as 13W_FORECAST; Check 12 reconciles it to the engine.
A4: Driver | B4: Unit | C4: Base | D4: Downside | E4: Severe | F4: ACTIVE | G4: Description
A5: Revenue / collections level | B5: % | C5: =ASSUMPTIONS!B15 -> 0 | D5: =ASSUMPTIONS!C15 -> 0 | E5: =ASSUMPTIONS!D15 -> -0.05 | F5: =ASSUMPTIONS!E15 -> 0 | G5: Shock to customer collections.
A6: Revenue growth (annualised) | B6: % | C6: =ASSUMPTIONS!B14 -> 0 | D6: =ASSUMPTIONS!C14 -> 0 | E6: =ASSUMPTIONS!D14 -> 0 | F6: =ASSUMPTIONS!E14 -> 0
A7: Collection delay | B7: days | C7: =ASSUMPTIONS!B16 -> 0 | D7: =ASSUMPTIONS!C16 -> 7 | E7: =ASSUMPTIONS!D16 -> 15 | F7: =ASSUMPTIONS!E16 -> 0 | G7: Extra days before customers pay.
A8: Supplier payments (reduced payables support) | B8: days | C8: =ASSUMPTIONS!B19 -> 0 | D8: =ASSUMPTIONS!C19 -> 0 | E8: =ASSUMPTIONS!D19 -> 5 | F8: =ASSUMPTIONS!E19 -> 0 | G8: Suppliers paid earlier.
A9: Working capital — inventory build | B9: days | C9: =ASSUMPTIONS!B18 -> 0 | D9: =ASSUMPTIONS!C18 -> 0 | E9: =ASSUMPTIONS!D18 -> 5 | F9: =ASSUMPTIONS!E18 -> 0
A10: Capex | B10: × | C10: =ASSUMPTIONS!B25 -> 1 | D10: =ASSUMPTIONS!C25 -> 1 | E10: =ASSUMPTIONS!D25 -> 1 | F10: =ASSUMPTIONS!E25 -> 1 | G10: Unchanged in all scenarios.
A11: Tax | B11: × | C11: =ASSUMPTIONS!B23 -> 1 | D11: =ASSUMPTIONS!C23 -> 1 | E11: =ASSUMPTIONS!D23 -> 1 | F11: =ASSUMPTIONS!E23 -> 1 | G11: Unchanged in all scenarios.
A12: Interest rate | B12: bp | C12: =ASSUMPTIONS!B31 -> 0 | D12: =ASSUMPTIONS!C31 -> 50 | E12: =ASSUMPTIONS!D31 -> 200 | F12: =ASSUMPTIONS!E31 -> 0 | G12: Floating-rate debt and new funding.
A13: FX (non-EUR vs EUR) | B13: % | C13: =ASSUMPTIONS!B49 -> 0 | D13: =ASSUMPTIONS!C49 -> -0.05 | E13: =ASSUMPTIONS!D49 -> -0.1 | F13: =ASSUMPTIONS!E49 -> 0 | G13: Negative = EUR strengthens.
A15: Scenario results — weekly net cash before liquidity funding (same generator as the engine)
A16: €m | B16: 13-wk total | C16: W1 | D16: W2 | E16: W3 | F16: W4 | G16: W5 | H16: W6 | I16: W7 | J16: W8 | K16: W9 | L16: W10 | M16: W11 | N16: W12 | O16: W13 | P16: Note
A17: Base — weekly net cash flow (operating + scheduled financing) | B17: =SUM(C17:O17) -> 1075.5 | C17: =((IF(ASSUMPTIONS!$B$17="Month-end",(LIQUIDITY_DRIVERS!$E$11)/12*13W_FORECAST!C$11,(LIQUIDITY_DRIVERS!$E$11)/52))+(-LIQUIDITY_DRIVERS!$E$13*(MIN(ASSUMPTIONS!$B$16,ASSUMPTIONS!$B$7*13W_FORECAST!C$8)-MIN(ASSUMPTIONS!$B$16,ASSUMPTIONS!$B$7*(13W_FORECAST!C$8-1))))+(IF(ASSUMPTIONS!$B$28="Month-end",(LIQUIDITY_DRIVERS!$E$28)/12*13W_FORECAST!C$11,(LIQUIDITY_DRIVERS!$E$28)/52))+(ASSUMPTIONS!$B$29/13))*(1+ASSUMPTIONS!$B$49*(1-ASSUMPTIONS!$B$50))+((-IF(ASSUMPTIONS!$B$20="Month-end",(LIQUIDITY_DRIVERS!$E$24)/12*13W_FORECAST!C$11,(LIQUIDITY_DRIVERS!$E$24)/52))+(-LIQUIDITY_DRIVERS!$E$39*(MIN(ASSUMPTIONS!$B$18,ASSUMPTIONS!$B$7*13W_FORECAST!C$8)-MIN(ASSUMPTIONS!$B$18,ASSUMPTIONS!$B$7*(13W_FORECAST!C$8-1))))+(-LIQUIDITY_DRIVERS!$E$39*(MIN(ASSUMPTIONS!$B$19,ASSUMPTIONS!$B$7*13W_FORECAST!C$8)-MIN(ASSUMPTIONS!$B$19,ASSUMPTIONS!$B$7*(13W_FORECAST!C$8-1))))+(-IF(ASSUMPTIONS!$B$22="Month-end",(LIQUIDITY_DRIVERS!$E$25)/12*13W_FORECAST!C$11,(LIQUIDITY_DRIVERS!$E$25)/52))+(-IF(ASSUMPTIONS!$B$24="Month-end",(LIQUIDITY_DRIVERS!$E$58)/12*13W_FORECAST!C$11,(LIQUIDITY_DRIVERS!$E$58)/52))+(-IF(ASSUMPTIONS!$B$26="Month-end",(LIQUIDITY_DRIVERS!$E$50)/12*13W_FORECAST!C$11,(LIQUIDITY_DRIVERS!$E$50)/52))+(-IF(ASSUMPTIONS!$B$33="Month-end",(LIQUIDITY_DRIVERS!$E$67)/12*13W_FORECAST!C$11,(LIQUIDITY_DRIVERS!$E$67)/52))+(-IF(ASSUMPTIONS!$B$27="Month-end",(LIQUIDITY_DRIVERS!$E$26)/12*13W_FORECAST!C$11,(LIQUIDITY_DRIVERS!$E$26)/52)))*(1+ASSUMPTIONS!$B$49*(1-ASSUMPTIONS!$B$54))+(LIQUIDITY_DRIVERS!$E$69/52*ASSUMPTIONS!$B$41)+(-LIQUIDITY_DRIVERS!$E$69/52)+(-LIQUIDITY_DRIVERS!$E$73*AND(ASSUMPTIONS!$B$38>=13W_FORECAST!C$9,ASSUMPTIONS!$B$38<=13W_FORECAST!C$10))+(-IF(ASSUMPTIONS!$B$40="Month-end",(LIQUIDITY_DRIVERS!$E$74)/12*13W_FORECAST!C$11,(LIQUIDITY_DRIVERS!$E$74)/52))+(ASSUMPTIONS!$B$42/13) -> 262.80769 | D17: =((IF(ASSUMPTIONS!$B$17="Month-end",(LIQUIDITY_DRIVERS!$E$11)/12*13W_FORECAST!D$11,(LIQUIDITY_DRIVERS!$E$11)/52))+(-LIQUIDITY_DRIVERS!$E$13*(MIN(ASSUMPTIONS!$B$16,ASSUMPTIONS!$B$7*13W_FORECAST!D$8)-MIN(ASSUMPTIONS!$B$16,ASSUMPTIONS!$B$7*(13W_FORECAST!D$8-1))))+(IF(ASSUMPTIONS!$B$28="Month-end",(LIQUIDITY_DRIVERS!$E$28)/12*13W_FORECAST!D$11,(LIQUIDITY_DRIVERS!$E$28)/52))+(ASSUMPTIONS!$B$29/13))*(1+ASSUMPTIONS!$B$49*(1-ASSUMPTIONS!$B$50))+((-IF(ASSUMPTIONS!$B$20="Month-end",(LIQUIDITY_DRIVERS!$E$24)/12*13W_FORECAST!D$11,(LIQUIDITY_DRIVERS!$E$24)/52))+(-LIQUIDITY_DRIVERS!$E$39*(MIN(ASSUMPTIONS!$B$18,ASSUMPTIONS!$B$7*13W_FORECAST!D$8)-MIN(ASSUMPTIONS!$B$18,ASSUMPTIONS!$B$7*(13W_FORECAST!D$8-1))))+(-LIQUIDITY_DRIVERS!$E$39*(MIN(ASSUMPTIONS!$B$19,ASSUMPTIONS!$B$7*13W_FORECAST!D$8)-MIN(ASSUMPTIONS!$B$19,ASSUMPTIONS!$B$7*(13W_FORECAST!D$8-1))))+(-IF(ASSUMPTIONS!$B$22="Month-end",(LIQUIDITY_DRIVERS!$E$25)/12*13W_FORECAST!D$11,(LIQUIDITY_DRIVERS!$E$25)/52))+(-IF(ASSUMPTIONS!$B$24="Month-end",(LIQUIDITY_DRIVERS!$E$58)/12*13W_FORECAST!D$11,(LIQUIDITY_DRIVERS!$E$58)/52))+(-IF(ASSUMPTIONS!$B$26="Month-end",(LIQUIDITY_DRIVERS!$E$50)/12*13W_FORECAST!D$11,(LIQUIDITY_DRIVERS!$E$50)/52))+(-IF(ASSUMPTIONS!$B$33="Month-end",(LIQUIDITY_DRIVERS!$E$67)/12*13W_FORECAST!D$11,(LIQUIDITY_DRIVERS!$E$67)/52))+(-IF(ASSUMPTIONS!$B$27="Month-end",(LIQUIDITY_DRIVERS!$E$26)/12*13W_FORECAST!D$11,(LIQUIDITY_DRIVERS!$E$26)/52)))*(1+ASSUMPTIONS!$B$49*(1-ASSUMPTIONS!$B$54))+(LIQUIDITY_DRIVERS!$E$69/52*ASSUMPTIONS!$B$41)+(-LIQUIDITY_DRIVERS!$E$69/52)+(-LIQUIDITY_DRIVERS!$E$73*AND(ASSUMPTIONS!$B$38>=13W_FORECAST!D$9,ASSUMPTIONS!$B$38<=13W_FORECAST!D$10))+(-IF(ASSUMPTIONS!$B$40="Month-end",(LIQUIDITY_DRIVERS!$E$74)/12*13W_FORECAST!D$11,(LIQUIDITY_DRIVERS!$E$74)/52))+(ASSUMPTIONS!$B$42/13) -> 262.80769 | E17: =((IF(ASSUMPTIONS!$B$17="Month-end",(LIQUIDITY_DRIVERS!$E$11)/12*13W_FORECAST!E$11,(LIQUIDITY_DRIVERS!$E$11)/52))+(-LIQUIDITY_DRIVERS!$E$13*(MIN(ASSUMPTIONS!$B$16,ASSUMPTIONS!$B$7*13W_FORECAST!E$8)-MIN(ASSUMPTIONS!$B$16,ASSUMPTIONS!$B$7*(13W_FORECAST!E$8-1))))+(IF(ASSUMPTIONS!$B$28="Month-end",(LIQUIDITY_DRIVERS!$E$28)/12*13W_FORECAST!E$11,(LIQUIDITY_DRIVERS!$E$28)/52))+(ASSUMPTIONS!$B$29/13))*(1+ASSUMPTIONS!$B$49*(1-ASSUMPTIONS!$B$50))+((-IF(ASSUMPTIONS!$B$20="Month-end",(LIQUIDITY_DRIVERS!$E$24)/12*13W_FORECAST!E$11,(LIQUIDITY_DRIVERS!$E$24)/52))+(-LIQUIDITY_DRIVERS!$E$39*(MIN(ASSUMPTIONS!$B$18,ASSUMPTIONS!$B$7*13W_FORECAST!E$8)-MIN(ASSUMPTIONS!$B$18,ASSUMPTIONS!$B$7*(13W_FORECAST!E$8-1))))+(-LIQUIDITY_DRIVERS!$E$39*(MIN(ASSUMPTIONS!$B$19,ASSUMPTIONS!$B$7*13W_FORECAST!E$8)-MIN(ASSUMPTIONS!$B$19,ASSUMPTIONS!$B$7*(13W_FORECAST!E$8-1))))+(-IF(ASSUMPTIONS!$B$22="Month-end",(LIQUIDITY_DRIVERS!$E$25)/12*13W_FORECAST!E$11,(LIQUIDITY_DRIVERS!$E$25)/52))+(-IF(ASSUMPTIONS!$B$24="Month-end",(LIQUIDITY_DRIVERS!$E$58)/12*13W_FORECAST!E$11,(LIQUIDITY_DRIVERS!$E$58)/52))+(-IF(ASSUMPTIONS!$B$26="Month-end",(LIQUIDITY_DRIVERS!$E$50)/12*13W_FORECAST!E$11,(LIQUIDITY_DRIVERS!$E$50)/52))+(-IF(ASSUMPTIONS!$B$33="Month-end",(LIQUIDITY_DRIVERS!$E$67)/12*13W_FORECAST!E$11,(LIQUIDITY_DRIVERS!$E$67)/52))+(-IF(ASSUMPTIONS!$B$27="Month-end",(LIQUIDITY_DRIVERS!$E$26)/12*13W_FORECAST!E$11,(LIQUIDITY_DRIVERS!$E$26)/52)))*(1+ASSUMPTIONS!$B$49*(1-ASSUMPTIONS!$B$54))+(LIQUIDITY_DRIVERS!$E$69/52*ASSUMPTIONS!$B$41)+(-LIQUIDITY_DRIVERS!$E$69/52)+(-LIQUIDITY_DRIVERS!$E$73*AND(ASSUMPTIONS!$B$38>=13W_FORECAST!E$9,ASSUMPTIONS!$B$38<=13W_FORECAST!E$10))+(-IF(ASSUMPTIONS!$B$40="Month-end",(LIQUIDITY_DRIVERS!$E$74)/12*13W_FORECAST!E$11,(LIQUIDITY_DRIVERS!$E$74)/52))+(ASSUMPTIONS!$B$42/13) -> 262.80769 | F17: =((IF(ASSUMPTIONS!$B$17="Month-end",(LIQUIDITY_DRIVERS!$E$11)/12*13W_FORECAST!F$11,(LIQUIDITY_DRIVERS!$E$11)/52))+(-LIQUIDITY_DRIVERS!$E$13*(MIN(ASSUMPTIONS!$B$16,ASSUMPTIONS!$B$7*13W_FORECAST!F$8)-MIN(ASSUMPTIONS!$B$16,ASSUMPTIONS!$B$7*(13W_FORECAST!F$8-1))))+(IF(ASSUMPTIONS!$B$28="Month-end",(LIQUIDITY_DRIVERS!$E$28)/12*13W_FORECAST!F$11,(LIQUIDITY_DRIVERS!$E$28)/52))+(ASSUMPTIONS!$B$29/13))*(1+ASSUMPTIONS!$B$49*(1-ASSUMPTIONS!$B$50))+((-IF(ASSUMPTIONS!$B$20="Month-end",(LIQUIDITY_DRIVERS!$E$24)/12*13W_FORECAST!F$11,(LIQUIDITY_DRIVERS!$E$24)/52))+(-LIQUIDITY_DRIVERS!$E$39*(MIN(ASSUMPTIONS!$B$18,ASSUMPTIONS!$B$7*13W_FORECAST!F$8)-MIN(ASSUMPTIONS!$B$18,ASSUMPTIONS!$B$7*(13W_FORECAST!F$8-1))))+(-LIQUIDITY_DRIVERS!$E$39*(MIN(ASSUMPTIONS!$B$19,ASSUMPTIONS!$B$7*13W_FORECAST!F$8)-MIN(ASSUMPTIONS!$B$19,ASSUMPTIONS!$B$7*(13W_FORECAST!F$8-1))))+(-IF(ASSUMPTIONS!$B$22="Month-end",(LIQUIDITY_DRIVERS!$E$25)/12*13W_FORECAST!F$11,(LIQUIDITY_DRIVERS!$E$25)/52))+(-IF(ASSUMPTIONS!$B$24="Month-end",(LIQUIDITY_DRIVERS!$E$58)/12*13W_FORECAST!F$11,(LIQUIDITY_DRIVERS!$E$58)/52))+(-IF(ASSUMPTIONS!$B$26="Month-end",(LIQUIDITY_DRIVERS!$E$50)/12*13W_FORECAST!F$11,(LIQUIDITY_DRIVERS!$E$50)/52))+(-IF(ASSUMPTIONS!$B$33="Month-end",(LIQUIDITY_DRIVERS!$E$67)/12*13W_FORECAST!F$11,(LIQUIDITY_DRIVERS!$E$67)/52))+(-IF(ASSUMPTIONS!$B$27="Month-end",(LIQUIDITY_DRIVERS!$E$26)/12*13W_FORECAST!F$11,(LIQUIDITY_DRIVERS!$E$26)/52)))*(1+ASSUMPTIONS!$B$49*(1-ASSUMPTIONS!$B$54))+(LIQUIDITY_DRIVERS!$E$69/52*ASSUMPTIONS!$B$41)+(-LIQUIDITY_DRIVERS!$E$69/52)+(-LIQUIDITY_DRIVERS!$E$73*AND(ASSUMPTIONS!$B$38>=13W_FORECAST!F$9,ASSUMPTIONS!$B$38<=13W_FORECAST!F$10))+(-IF(ASSUMPTIONS!$B$40="Month-end",(LIQUIDITY_DRIVERS!$E$74)/12*13W_FORECAST!F$11,(LIQUIDITY_DRIVERS!$E$74)/52))+(ASSUMPTIONS!$B$42/13) -> 262.80769 | G17: =((IF(ASSUMPTIONS!$B$17="Month-end",(LIQUIDITY_DRIVERS!$E$11)/12*13W_FORECAST!G$11,(LIQUIDITY_DRIVERS!$E$11)/52))+(-LIQUIDITY_DRIVERS!$E$13*(MIN(ASSUMPTIONS!$B$16,ASSUMPTIONS!$B$7*13W_FORECAST!G$8)-MIN(ASSUMPTIONS!$B$16,ASSUMPTIONS!$B$7*(13W_FORECAST!G$8-1))))+(IF(ASSUMPTIONS!$B$28="Month-end",(LIQUIDITY_DRIVERS!$E$28)/12*13W_FORECAST!G$11,(LIQUIDITY_DRIVERS!$E$28)/52))+(ASSUMPTIONS!$B$29/13))*(1+ASSUMPTIONS!$B$49*(1-ASSUMPTIONS!$B$50))+((-IF(ASSUMPTIONS!$B$20="Month-end",(LIQUIDITY_DRIVERS!$E$24)/12*13W_FORECAST!G$11,(LIQUIDITY_DRIVERS!$E$24)/52))+(-LIQUIDITY_DRIVERS!$E$39*(MIN(ASSUMPTIONS!$B$18,ASSUMPTIONS!$B$7*13W_FORECAST!G$8)-MIN(ASSUMPTIONS!$B$18,ASSUMPTIONS!$B$7*(13W_FORECAST!G$8-1))))+(-LIQUIDITY_DRIVERS!$E$39*(MIN(ASSUMPTIONS!$B$19,ASSUMPTIONS!$B$7*13W_FORECAST!G$8)-MIN(ASSUMPTIONS!$B$19,ASSUMPTIONS!$B$7*(13W_FORECAST!G$8-1))))+(-IF(ASSUMPTIONS!$B$22="Month-end",(LIQUIDITY_DRIVERS!$E$25)/12*13W_FORECAST!G$11,(LIQUIDITY_DRIVERS!$E$25)/52))+(-IF(ASSUMPTIONS!$B$24="Month-end",(LIQUIDITY_DRIVERS!$E$58)/12*13W_FORECAST!G$11,(LIQUIDITY_DRIVERS!$E$58)/52))+(-IF(ASSUMPTIONS!$B$26="Month-end",(LIQUIDITY_DRIVERS!$E$50)/12*13W_FORECAST!G$11,(LIQUIDITY_DRIVERS!$E$50)/52))+(-IF(ASSUMPTIONS!$B$33="Month-end",(LIQUIDITY_DRIVERS!$E$67)/12*13W_FORECAST!G$11,(LIQUIDITY_DRIVERS!$E$67)/52))+(-IF(ASSUMPTIONS!$B$27="Month-end",(LIQUIDITY_DRIVERS!$E$26)/12*13W_FORECAST!G$11,(LIQUIDITY_DRIVERS!$E$26)/52)))*(1+ASSUMPTIONS!$B$49*(1-ASSUMPTIONS!$B$54))+(LIQUIDITY_DRIVERS!$E$69/52*ASSUMPTIONS!$B$41)+(-LIQUIDITY_DRIVERS!$E$69/52)+(-LIQUIDITY_DRIVERS!$E$73*AND(ASSUMPTIONS!$B$38>=13W_FORECAST!G$9,ASSUMPTIONS!$B$38<=13W_FORECAST!G$10))+(-IF(ASSUMPTIONS!$B$40="Month-end",(LIQUIDITY_DRIVERS!$E$74)/12*13W_FORECAST!G$11,(LIQUIDITY_DRIVERS!$E$74)/52))+(ASSUMPTIONS!$B$42/13) -> -517.52564 | H17: =((IF(ASSUMPTIONS!$B$17="Month-end",(LIQUIDITY_DRIVERS!$E$11)/12*13W_FORECAST!H$11,(LIQUIDITY_DRIVERS!$E$11)/52))+(-LIQUIDITY_DRIVERS!$E$13*(MIN(ASSUMPTIONS!$B$16,ASSUMPTIONS!$B$7*13W_FORECAST!H$8)-MIN(ASSUMPTIONS!$B$16,ASSUMPTIONS!$B$7*(13W_FORECAST!H$8-1))))+(IF(ASSUMPTIONS!$B$28="Month-end",(LIQUIDITY_DRIVERS!$E$28)/12*13W_FORECAST!H$11,(LIQUIDITY_DRIVERS!$E$28)/52))+(ASSUMPTIONS!$B$29/13))*(1+ASSUMPTIONS!$B$49*(1-ASSUMPTIONS!$B$50))+((-IF(ASSUMPTIONS!$B$20="Month-end",(LIQUIDITY_DRIVERS!$E$24)/12*13W_FORECAST!H$11,(LIQUIDITY_DRIVERS!$E$24)/52))+(-LIQUIDITY_DRIVERS!$E$39*(MIN(ASSUMPTIONS!$B$18,ASSUMPTIONS!$B$7*13W_FORECAST!H$8)-MIN(ASSUMPTIONS!$B$18,ASSUMPTIONS!$B$7*(13W_FORECAST!H$8-1))))+(-LIQUIDITY_DRIVERS!$E$39*(MIN(ASSUMPTIONS!$B$19,ASSUMPTIONS!$B$7*13W_FORECAST!H$8)-MIN(ASSUMPTIONS!$B$19,ASSUMPTIONS!$B$7*(13W_FORECAST!H$8-1))))+(-IF(ASSUMPTIONS!$B$22="Month-end",(LIQUIDITY_DRIVERS!$E$25)/12*13W_FORECAST!H$11,(LIQUIDITY_DRIVERS!$E$25)/52))+(-IF(ASSUMPTIONS!$B$24="Month-end",(LIQUIDITY_DRIVERS!$E$58)/12*13W_FORECAST!H$11,(LIQUIDITY_DRIVERS!$E$58)/52))+(-IF(ASSUMPTIONS!$B$26="Month-end",(LIQUIDITY_DRIVERS!$E$50)/12*13W_FORECAST!H$11,(LIQUIDITY_DRIVERS!$E$50)/52))+(-IF(ASSUMPTIONS!$B$33="Month-end",(LIQUIDITY_DRIVERS!$E$67)/12*13W_FORECAST!H$11,(LIQUIDITY_DRIVERS!$E$67)/52))+(-IF(ASSUMPTIONS!$B$27="Month-end",(LIQUIDITY_DRIVERS!$E$26)/12*13W_FORECAST!H$11,(LIQUIDITY_DRIVERS!$E$26)/52)))*(1+ASSUMPTIONS!$B$49*(1-ASSUMPTIONS!$B$54))+(LIQUIDITY_DRIVERS!$E$69/52*ASSUMPTIONS!$B$41)+(-LIQUIDITY_DRIVERS!$E$69/52)+(-LIQUIDITY_DRIVERS!$E$73*AND(ASSUMPTIONS!$B$38>=13W_FORECAST!H$9,ASSUMPTIONS!$B$38<=13W_FORECAST!H$10))+(-IF(ASSUMPTIONS!$B$40="Month-end",(LIQUIDITY_DRIVERS!$E$74)/12*13W_FORECAST!H$11,(LIQUIDITY_DRIVERS!$E$74)/52))+(ASSUMPTIONS!$B$42/13) -> 262.80769 | I17: =((IF(ASSUMPTIONS!$B$17="Month-end",(LIQUIDITY_DRIVERS!$E$11)/12*13W_FORECAST!I$11,(LIQUIDITY_DRIVERS!$E$11)/52))+(-LIQUIDITY_DRIVERS!$E$13*(MIN(ASSUMPTIONS!$B$16,ASSUMPTIONS!$B$7*13W_FORECAST!I$8)-MIN(ASSUMPTIONS!$B$16,ASSUMPTIONS!$B$7*(13W_FORECAST!I$8-1))))+(IF(ASSUMPTIONS!$B$28="Month-end",(LIQUIDITY_DRIVERS!$E$28)/12*13W_FORECAST!I$11,(LIQUIDITY_DRIVERS!$E$28)/52))+(ASSUMPTIONS!$B$29/13))*(1+ASSUMPTIONS!$B$49*(1-ASSUMPTIONS!$B$50))+((-IF(ASSUMPTIONS!$B$20="Month-end",(LIQUIDITY_DRIVERS!$E$24)/12*13W_FORECAST!I$11,(LIQUIDITY_DRIVERS!$E$24)/52))+(-LIQUIDITY_DRIVERS!$E$39*(MIN(ASSUMPTIONS!$B$18,ASSUMPTIONS!$B$7*13W_FORECAST!I$8)-MIN(ASSUMPTIONS!$B$18,ASSUMPTIONS!$B$7*(13W_FORECAST!I$8-1))))+(-LIQUIDITY_DRIVERS!$E$39*(MIN(ASSUMPTIONS!$B$19,ASSUMPTIONS!$B$7*13W_FORECAST!I$8)-MIN(ASSUMPTIONS!$B$19,ASSUMPTIONS!$B$7*(13W_FORECAST!I$8-1))))+(-IF(ASSUMPTIONS!$B$22="Month-end",(LIQUIDITY_DRIVERS!$E$25)/12*13W_FORECAST!I$11,(LIQUIDITY_DRIVERS!$E$25)/52))+(-IF(ASSUMPTIONS!$B$24="Month-end",(LIQUIDITY_DRIVERS!$E$58)/12*13W_FORECAST!I$11,(LIQUIDITY_DRIVERS!$E$58)/52))+(-IF(ASSUMPTIONS!$B$26="Month-end",(LIQUIDITY_DRIVERS!$E$50)/12*13W_FORECAST!I$11,(LIQUIDITY_DRIVERS!$E$50)/52))+(-IF(ASSUMPTIONS!$B$33="Month-end",(LIQUIDITY_DRIVERS!$E$67)/12*13W_FORECAST!I$11,(LIQUIDITY_DRIVERS!$E$67)/52))+(-IF(ASSUMPTIONS!$B$27="Month-end",(LIQUIDITY_DRIVERS!$E$26)/12*13W_FORECAST!I$11,(LIQUIDITY_DRIVERS!$E$26)/52)))*(1+ASSUMPTIONS!$B$49*(1-ASSUMPTIONS!$B$54))+(LIQUIDITY_DRIVERS!$E$69/52*ASSUMPTIONS!$B$41)+(-LIQUIDITY_DRIVERS!$E$69/52)+(-LIQUIDITY_DRIVERS!$E$73*AND(ASSUMPTIONS!$B$38>=13W_FORECAST!I$9,ASSUMPTIONS!$B$38<=13W_FORECAST!I$10))+(-IF(ASSUMPTIONS!$B$40="Month-end",(LIQUIDITY_DRIVERS!$E$74)/12*13W_FORECAST!I$11,(LIQUIDITY_DRIVERS!$E$74)/52))+(ASSUMPTIONS!$B$42/13) -> 262.80769 | J17: =((IF(ASSUMPTIONS!$B$17="Month-end",(LIQUIDITY_DRIVERS!$E$11)/12*13W_FORECAST!J$11,(LIQUIDITY_DRIVERS!$E$11)/52))+(-LIQUIDITY_DRIVERS!$E$13*(MIN(ASSUMPTIONS!$B$16,ASSUMPTIONS!$B$7*13W_FORECAST!J$8)-MIN(ASSUMPTIONS!$B$16,ASSUMPTIONS!$B$7*(13W_FORECAST!J$8-1))))+(IF(ASSUMPTIONS!$B$28="Month-end",(LIQUIDITY_DRIVERS!$E$28)/12*13W_FORECAST!J$11,(LIQUIDITY_DRIVERS!$E$28)/52))+(ASSUMPTIONS!$B$29/13))*(1+ASSUMPTIONS!$B$49*(1-ASSUMPTIONS!$B$50))+((-IF(ASSUMPTIONS!$B$20="Month-end",(LIQUIDITY_DRIVERS!$E$24)/12*13W_FORECAST!J$11,(LIQUIDITY_DRIVERS!$E$24)/52))+(-LIQUIDITY_DRIVERS!$E$39*(MIN(ASSUMPTIONS!$B$18,ASSUMPTIONS!$B$7*13W_FORECAST!J$8)-MIN(ASSUMPTIONS!$B$18,ASSUMPTIONS!$B$7*(13W_FORECAST!J$8-1))))+(-LIQUIDITY_DRIVERS!$E$39*(MIN(ASSUMPTIONS!$B$19,ASSUMPTIONS!$B$7*13W_FORECAST!J$8)-MIN(ASSUMPTIONS!$B$19,ASSUMPTIONS!$B$7*(13W_FORECAST!J$8-1))))+(-IF(ASSUMPTIONS!$B$22="Month-end",(LIQUIDITY_DRIVERS!$E$25)/12*13W_FORECAST!J$11,(LIQUIDITY_DRIVERS!$E$25)/52))+(-IF(ASSUMPTIONS!$B$24="Month-end",(LIQUIDITY_DRIVERS!$E$58)/12*13W_FORECAST!J$11,(LIQUIDITY_DRIVERS!$E$58)/52))+(-IF(ASSUMPTIONS!$B$26="Month-end",(LIQUIDITY_DRIVERS!$E$50)/12*13W_FORECAST!J$11,(LIQUIDITY_DRIVERS!$E$50)/52))+(-IF(ASSUMPTIONS!$B$33="Month-end",(LIQUIDITY_DRIVERS!$E$67)/12*13W_FORECAST!J$11,(LIQUIDITY_DRIVERS!$E$67)/52))+(-IF(ASSUMPTIONS!$B$27="Month-end",(LIQUIDITY_DRIVERS!$E$26)/12*13W_FORECAST!J$11,(LIQUIDITY_DRIVERS!$E$26)/52)))*(1+ASSUMPTIONS!$B$49*(1-ASSUMPTIONS!$B$54))+(LIQUIDITY_DRIVERS!$E$69/52*ASSUMPTIONS!$B$41)+(-LIQUIDITY_DRIVERS!$E$69/52)+(-LIQUIDITY_DRIVERS!$E$73*AND(ASSUMPTIONS!$B$38>=13W_FORECAST!J$9,ASSUMPTIONS!$B$38<=13W_FORECAST!J$10))+(-IF(ASSUMPTIONS!$B$40="Month-end",(LIQUIDITY_DRIVERS!$E$74)/12*13W_FORECAST!J$11,(LIQUIDITY_DRIVERS!$E$74)/52))+(ASSUMPTIONS!$B$42/13) -> 262.80769 | ... O17: =((IF(ASSUMPTIONS!$B$17="Month-end",(LIQUIDITY_DRIVERS!$E$11)/12*13W_FORECAST!O$11,(LIQUIDITY_DRIVERS!$E$11)/52))+(-LIQUIDITY_DRIVERS!$E$13*(MIN(ASSUMPTIONS!$B$16,ASSUMPTIONS!$B$7*13W_FORECAST!O$8)-MIN(ASSUMPTIONS!$B$16,ASSUMPTIONS!$B$7*(13W_FORECAST!O$8-1))))+(IF(ASSUMPTIONS!$B$28="Month-end",(LIQUIDITY_DRIVERS!$E$28)/12*13W_FORECAST!O$11,(LIQUIDITY_DRIVERS!$E$28)/52))+(ASSUMPTIONS!$B$29/13))*(1+ASSUMPTIONS!$B$49*(1-ASSUMPTIONS!$B$50))+((-IF(ASSUMPTIONS!$B$20="Month-end",(LIQUIDITY_DRIVERS!$E$24)/12*13W_FORECAST!O$11,(LIQUIDITY_DRIVERS!$E$24)/52))+(-LIQUIDITY_DRIVERS!$E$39*(MIN(ASSUMPTIONS!$B$18,ASSUMPTIONS!$B$7*13W_FORECAST!O$8)-MIN(ASSUMPTIONS!$B$18,ASSUMPTIONS!$B$7*(13W_FORECAST!O$8-1))))+(-LIQUIDITY_DRIVERS!$E$39*(MIN(ASSUMPTIONS!$B$19,ASSUMPTIONS!$B$7*13W_FORECAST!O$8)-MIN(ASSUMPTIONS!$B$19,ASSUMPTIONS!$B$7*(13W_FORECAST!O$8-1))))+(-IF(ASSUMPTIONS!$B$22="Month-end",(LIQUIDITY_DRIVERS!$E$25)/12*13W_FORECAST!O$11,(LIQUIDITY_DRIVERS!$E$25)/52))+(-IF(ASSUMPTIONS!$B$24="Month-end",(LIQUIDITY_DRIVERS!$E$58)/12*13W_FORECAST!O$11,(LIQUIDITY_DRIVERS!$E$58)/52))+(-IF(ASSUMPTIONS!$B$26="Month-end",(LIQUIDITY_DRIVERS!$E$50)/12*13W_FORECAST!O$11,(LIQUIDITY_DRIVERS!$E$50)/52))+(-IF(ASSUMPTIONS!$B$33="Month-end",(LIQUIDITY_DRIVERS!$E$67)/12*13W_FORECAST!O$11,(LIQUIDITY_DRIVERS!$E$67)/52))+(-IF(ASSUMPTIONS!$B$27="Month-end",(LIQUIDITY_DRIVERS!$E$26)/12*13W_FORECAST!O$11,(LIQUIDITY_DRIVERS!$E$26)/52)))*(1+ASSUMPTIONS!$B$49*(1-ASSUMPTIONS!$B$54))+(LIQUIDITY_DRIVERS!$E$69/52*ASSUMPTIONS!$B$41)+(-LIQUIDITY_DRIVERS!$E$69/52)+(-LIQUIDITY_DRIVERS!$E$73*AND(ASSUMPTIONS!$B$38>=13W_FORECAST!O$9,ASSUMPTIONS!$B$38<=13W_FORECAST!O$10))+(-IF(ASSUMPTIONS!$B$40="Month-end",(LIQUIDITY_DRIVERS!$E$74)/12*13W_FORECAST!O$11,(LIQUIDITY_DRIVERS!$E$74)/52))+(ASSUMPTIONS!$B$42/13) -> -517.52564
